Workbook

Sheet MainTablesFigures

Sheet Data
BP1: Share haven profits (excluding Puerto Rico) in total (domestic + foreign) profits
B2: Compustat (full sample, no winsorization) | H2: Compustat winsorized | O2: BEA survey | AD2: NIPA | AV2: NIPA, details | BQ2: Preferred series | BZ2: Robustness | CJ2: Tax rates computations | CQ2: Comparisons of aggregates
A3: year | B3: Profit (+) | C3: For. profits (+) | D3: Share foreign (+) | E3: Profit (all) | F3: For. profits (all) | G3: Share foreign (all) | H3: Profit (all) | I3: For. profits (all) | J3: Share foreign (all) | K3: Check | L3: Check | M3: Check | O3: Profit type return of parents | P3: Profit-type return of majority-owned affiliates (MOFA) | Q3: MOFA profit-type / (MOFA profit-type + parent profit type) | R3: Pre-tax DI equity income (no current cost adjustment) | S3: Memo: DI investmetn income with CCAdj + foreign taxes paid | T3: Pre-tax DI equity income / (Pre-tax DI equity income + parent profit type return) | U3: (Same, interpolated for missing years in the 1980) | V3: Taxes paid by majority-owned affiliates | W3: Taxes paid by parent | X3: Tax rate of parents | Y3: Ta rate of affiliates | Z3: Tax rate all | AA3: Tax rates of affiliates, corr for current-cost adj | AB3: Tax rates all, corr for current-cost adj | AD3: Total pre-tax profits (domestic + foreign), S-corp corrected | AE3: Equals: half of S-corp profits | AF3: Plus: C-corp profits | AG3: Total pre-tax profits (domestic + foreign), S-corp corrected | AH3: Equals: domestic profit | AI3: Plus: foreign pre-tax profit | AK3: Total pre-tax profits (domestic + foreign), no S-corp correction | AL3: Equals: Pre-tax domestic corporate profits | AM3: Plus: foreign pre-tax profit | AN3: Total pre-tax profits (domestic + foreign), no S-corp correction | AO3: Equals: C-corp profits | AP3: Plus: S-corps profits | AQ3: Check | AR3: Share of foreign pre-tax profit in US corporations' pre-tax profit (no S-corp correction) | AS3: Share of foreign pre-tax profit in US corporations' pre-tax profit (with S-corps correction) | AT3: Corrected CBCR data | AV3: Corporate profits in national income | AW3: Minus: Fed profits | AX3: Minus: PI dividends received from RoW | AY3: Plus: PI dividends paid to RoW | AZ3: Equals: global income of US-headquartered corp | BA3: Minus: DI equity income received from RoW, with current-cost adj | BB3: Equals: domestic income of US-headquarterd corp | BC3: Memo: DI equity income received from RoW, without current-cost adjustment | BD3: Memo: current-cost adjustment | BE3: Current-cost adjustment / DI equity income without ccadj | BF3: Memo: total DI income with CCAdj | BG3: pre-tax DI equity income without CCAdj | BI3: Foreign profit outflows | BJ3: Equals | BK3: PI dividends | BL3: DI divs + retained | BM3: Diff geographical coverage btw NIPA and BoP | BQ3: NIPA (S-corp corrected) | BR3: Ireland | BS3: [Check] | BT3: Netherlands + Luxembourg | BU3: Switzerland | BV3: Bermuda and Carribbean havens | BW3: Singapore | BX3: Check | BZ3: NIPA (no S-corp correction) | CA3: Compustat (positive profit) | CB3: Multinationals (BEA survey) | CC3: Ireland | CD3: Netherlands + Luxembourg | CE3: Switzerland | CF3: Bermuda and Carribbean havens | CG3: Singapore | CH3: Check | CJ3: Taxes paid to the US | CK3: Federal | CL3: State | CM3: Taxes paid abroad (all affiliates) | CN3: Effective US+foreign rate on global profits | CO3: (wright-zucman) | CQ3: Memo: BEA survey total profit / NIPA total profit | CR3: Memo: BEA survey foreign profit / NIPA foreign profit | CS3: Memo: BEA survey domestic profit / NIPA domestic profit (no S-corp correction) | CT3: Memo: BEA survey domestic profit / NIPA domestic profit (with S-corp correction) | CU3: BEA survey profit / NIPA profit (with S-corp correction) | CV3: Memo: Compustat total profit / NIPA total profit | CW3: Compustat foreign profits / pre-tax DI equity income at current-cost | CX3: Compustat US profit / BEA US income of parents | CY3: Compustat foreign profits / profit-type return of MOFA | CZ3: MOFA profit-type / pre-tax DI equity income at current-cost | DA3: After-tax MOFA profit-type return / DI equity income at current cost | DB3: Memo: Compustat pifo / BEA profit-type return
A4: Source / Note | B4: File compustat_all_etrs.xlsx | H4: File compustat_all_etrs.xlsx | O4: BEA USDIA survey Table I.P.1. Computed as net income + foreign income taxes paid - income from equity investments - capital gains before 1994 | P4: BEA USDIA survey Table II.F.1. Computed as net income + foreign income taxes paid - income from equity investments - capital gains before 1994 | S4: Used for country level series since BEA does not publish DI equity income by country | V4: BEA USDIA survey II.D.1 | W4: BEA USDIA survey Table I.P.1 | AB4: No correction for parents | AD4: Half of S-corp profits are removed as they do not reflect true profit but disguised wages (see Saez-Zucman 2020). Fed profits are removed | AF4: Excluding Fed | AI4: DI equity income received without current-cost adjustment, divided by 1- foreign income tax rate of MOFA, plus current-cost adjustment | AP4: Estimated based on BEA (2021) prototype estimates: https://www.bea.gov/system/files/2021-05/prototype-nipa-estimates-of-profits-for-s-corporations.pdf. Includes foreign profits (not separately identified) | BA4: ITA Table 4.2 line 12 | BB4: Excludes Puerto Rico | BC4: ITA Table 4.2 line 12 minus 16 | BD4: ITA Table 4.2 line 16 | BF4: ITA Table 4.2 line 11 | BI4: NIPA 4.1 34 + 35 | BL4: ITA 4.2 | CB4: Check exact sample | CK4: NIPA Table 3.2. 1982: OMB has much more than NIPA for fed tax, explains the gap with BEA survey: clarify why | CL4: NIPA Table 3.3
A5: 1982 | O5: =102.041+46.05-25.713-4.981 -> 117.397 | P5: =WrightZucman!O26 -> 53.575 | Q5: =P5/(P5+O5) -> 0.3133554 | R5: =BC5/(1-Y5) -> 63.745992 | T5: =R5/(R5+O5) -> 0.35190979 | U5: =T5 -> 0.35190979 | V5: 30.156 | W5: =46.05 -> 46.05 | X5: =W5/O5 -> 0.39225875 | Y5: =V5/P5 -> 0.56287448 | Z5: =(V5+W5)/(O5+P5) -> 0.44572211 | AA5: =V5/(P5/(1-BE5)) -> 0.50041468 | AB5: =(V5+W5)/(P5/(1-BE5)+O5) -> 0.42894529 | AD5: =BB5-0.5*AP5+AI5 -> 253.25677 | AE5: =0.5*AP5 -> 1.4732248 | AF5: =AD5-AE5 -> 251.78354 | AG5: =AD5 -> 253.25677 | AH5: =AG5-AI5 -> 186.03278 | AI5: =BC5/(1-Y5)+BD5 -> 67.223992 | AK5: =AL5+AM5 -> 254.72999 | AL5: =BB5 -> 187.506 | AM5: =AI5 -> 67.223992 | AN5: =AK5 -> 254.72999 | AO5: =AN5-AP5 -> 251.78354 | AP5: 2.9464497 | AQ5: =AF5-AO5 -> 0 | AR5: =Data!AM5/Data!AK5 -> 0.26390293 | AS5: =Data!AI5/Data!AG5 -> 0.26543809 | AV5: ='[1]Assets(BoP)'!$D74 -> 229.9 | AW5: 15.2 | AX5: ='[1]Assets(BoP)'!$CI74 -> 0 | AY5: =BK5 -> 4.149 | AZ5: =AV5-AW5-AX5+AY5 -> 218.849 | BA5: 31.343 | BB5: =AZ5-BA5 -> 187.506 | BC5: =BA5-BD5 -> 27.865 | BD5: 3.478 | BE5: =BD5/BA5 -> 0.11096577 | BF5: 29.469 | BG5: =BC5/(1-Y5) -> 63.745992 | BI5: ='[1]Assets(BoP)'!$Q74 -> 4.1 | BK5: =BI5-BL5 -> 4.149 | BL5: -0.049 | BM5: 0 | BP5: 1982 | BQ5: =Data!AR5*WrightZucman!B26 -> 0.03953495 | BR5: =$BQ5*WrightZucman!C26/WrightZucman!$B26 -> 0.003719024 | BS5: =WrightZucman!C26*Data!AS5-BR5 -> 2.1634007e-05 | BT5: =$BQ5*WrightZucman!D26/WrightZucman!$B26 -> 0.0049554148 | BU5: =$BQ5*WrightZucman!E26/WrightZucman!$B26 -> 0.0071917551 | BV5: =$BQ5*WrightZucman!F26/WrightZucman!$B26 -> 0.020585168 | BW5: =$BQ5*WrightZucman!G26/WrightZucman!$B26 -> 0.0030835881 | BX5: =BQ5-BR5-BT5-BU5-BV5-BW5 -> 6.0715322e-18 | BZ5: =Data!AR5*WrightZucman!B26 -> 0.03953495 | CB5: =Data!Q5*WrightZucman!B26 -> 0.046943359 | CC5: =WrightZucman!C26*Data!$Q5 -> 0.0044159278 | CD5: =WrightZucman!D26*Data!$Q5 -> 0.0058840044 | CE5: =WrightZucman!E26*Data!$Q5 -> 0.00853941 | CF5: =WrightZucman!F26*Data!$Q5 -> 0.024442599 | CG5: =WrightZucman!G26*Data!$Q5 -> 0.0036614182 | CH5: =CB5-CC5-CD5-CE5-CF5-CG5 -> -5.6378513e-18 | CJ5: =CK5+CL5 -> 47.8 | CK5: 33.8 | CL5: 14 | CM5: =BC5*Y5/(1-Y5) -> 35.880992 | CN5: =(CJ5+CM5)/AD5 -> 0.33041957 | CO5: ='[1]Assets(BoP)'!$BN74 -> 0.29823491 | CQ5: =(O5+P5)/AD5 -> 0.67509351 | CR5: =P5/AI5 -> 0.7969625 | CS5: =O5/AL5 -> 0.6260973 | CT5: =O5/(AL5-0.5*AP5) -> 0.63105547 | CU5: =(O5+P5)/AD5 -> 0.67509351 | CZ5: =P5/(BC5/(1-Y5)) -> 0.840445 | DA5: =(P5-V5)/BC5 -> 0.840445
A6: 1983 | P6: =WrightZucman!O27 -> 58.034 | U6: =U5+(U$12-U$5)/7 -> 0.35370218 | V6: 30.122 | Y6: =V6/P6 -> 0.51904056 | AA6: =V6/(P6/(1-BE6)) -> 0.47489911 | AD6: =BB6-0.5*AP6+AI6 -> 301.02016 | AE6: =0.5*AP6 -> 3.2879 | AF6: =AD6-AE6 -> 297.73226 | AG6: =AD6 -> 301.02016 | AH6: =AG6-AI6 -> 230.8431 | AI6: =BC6/(1-Y6)+BD6 -> 70.177064 | AK6: =AL6+AM6 -> 304.30806 | AL6: =BB6 -> 234.131 | AM6: =AI6 -> 70.177064 | AN6: =AK6 -> 304.30806 | AO6: =AN6-AP6 -> 297.73226 | AP6: 6.5758 | AQ6: =AF6-AO6 -> 0 | AR6: =Data!AM6/Data!AK6 -> 0.23061191 | AS6: =Data!AI6/Data!AG6 -> 0.23313077 | AV6: ='[1]Assets(BoP)'!$D75 -> 279.8 | AW6: 14.6 | AX6: ='[1]Assets(BoP)'!$CI75 -> 0 | AY6: =BK6 -> 4.242 | AZ6: =AV6-AW6-AX6+AY6 -> 269.442 | BA6: 35.311 | BB6: =AZ6-BA6 -> 234.131 | BC6: =BA6-BD6 -> 32.308 | BD6: 3.003 | BE6: =BD6/BA6 -> 0.08504432 | BF6: 31.75 | BG6: =BC6/(1-Y6) -> 67.174064 | BI6: ='[1]Assets(BoP)'!$Q75 -> 6.1 | BK6: =BI6-BL6 -> 4.242 | BL6: 1.858 | BM6: 0 | BP6: 1983 | BQ6: =Data!AR6*WrightZucman!B27 -> 0.032286621 | BR6: =$BQ6*WrightZucman!C27/WrightZucman!$B27 -> 0.0037949198 | BS6: =WrightZucman!C27*Data!AS6-BR6 -> 4.1450103e-05 | BT6: =$BQ6*WrightZucman!D27/WrightZucman!$B27 -> 0.0061910838 | BU6: =$BQ6*WrightZucman!E27/WrightZucman!$B27 -> 0.0049314088 | BV6: =$BQ6*WrightZucman!F27/WrightZucman!$B27 -> 0.01446838 | BW6: =$BQ6*WrightZucman!G27/WrightZucman!$B27 -> 0.0029008287 | BX6: =BQ6-BR6-BT6-BU6-BV6-BW6 -> 0 | BZ6: =Data!AR6*WrightZucman!B27 -> 0.032286621 | CJ6: =CK6+CL6 -> 63 | CK6: 47.1 | CL6: 15.9 | CM6: =BC6*Y6/(1-Y6) -> 34.866064 | CN6: =(CJ6+CM6)/AD6 -> 0.32511465 | CO6: ='[1]Assets(BoP)'!$BN75 -> 0.30131738 | CR6: =P6/AI6 -> 0.82696535 | CZ6: =P6/(BC6/(1-Y6)) -> 0.86393463 | DA6: =(P6-V6)/BC6 -> 0.86393463
A7: 1984 | B7: 148424.94 | C7: 47432.283 | D7: 0.31957084 | E7: 143785.13 | F7: 47667.634 | G7: 0.33151992 | H7: 143785.13 | I7: 47667.634 | J7: 0.33151992 | K7: =C7/B7-D7 -> 0 | L7: =I7/H7-J7 -> 0 | M7: =F7/E7-G7 -> 0 | P7: =WrightZucman!O28 -> 64.46 | U7: =U6+(U$12-U$5)/7 -> 0.35549457 | V7: 33.587 | Y7: =V7/P7 -> 0.52105182 | AA7: =V7/(P7/(1-BE7)) -> 0.47687751 | AD7: =BB7-0.5*AP7+AI7 -> 359.02108 | AE7: =0.5*AP7 -> 6.050477 | AF7: =AD7-AE7 -> 352.9706 | AG7: =AD7 -> 359.02108 | AH7: =AG7-AI7 -> 279.88052 | AI7: =BC7/(1-Y7)+BD7 -> 79.140552 | AK7: =AL7+AM7 -> 365.07155 | AL7: =BB7 -> 285.931 | AM7: =AI7 -> 79.140552 | AN7: =AK7 -> 365.07155 | AO7: =AN7-AP7 -> 352.9706 | AP7: 12.100954 | AQ7: =AF7-AO7 -> 0 | AR7: =Data!AM7/Data!AK7 -> 0.21678093 | AS7: =Data!AI7/Data!AG7 -> 0.22043428 | AV7: ='[1]Assets(BoP)'!$D76 -> 337.9 | AW7: 16.4 | AX7: ='[1]Assets(BoP)'!$CI76 -> 0 | AY7: =BK7 -> 4.087 | AZ7: =AV7-AW7-AX7+AY7 -> 325.587 | BA7: 39.656 | BB7: =AZ7-BA7 -> 285.931 | BC7: =BA7-BD7 -> 36.294 | BD7: 3.362 | BE7: =BD7/BA7 -> 0.0847791 | BF7: 35.326 | BG7: =BC7/(1-Y7) -> 75.778552 | BI7: ='[1]Assets(BoP)'!$Q76 -> 9.6 | BK7: =BI7-BL7 -> 4.087 | BL7: 5.513 | BM7: 0 | BP7: 1984 | BQ7: =Data!AR7*WrightZucman!B28 -> 0.028885067 | BR7: =$BQ7*WrightZucman!C28/WrightZucman!$B28 -> 0.0037195115 | BS7: =WrightZucman!C28*Data!AS7-BR7 -> 6.2683838e-05 | BT7: =$BQ7*WrightZucman!D28/WrightZucman!$B28 -> 0.0053135879 | BU7: =$BQ7*WrightZucman!E28/WrightZucman!$B28 -> 0.0050445455 | BV7: =$BQ7*WrightZucman!F28/WrightZucman!$B28 -> 0.012342321 | BW7: =$BQ7*WrightZucman!G28/WrightZucman!$B28 -> 0.0024651012 | BX7: =BQ7-BR7-BT7-BU7-BV7-BW7 -> 0 | BZ7: =Data!AR7*WrightZucman!B28 -> 0.028885067 | CA7: =Data!D7*WrightZucman!B28 -> 0.042581352 | CJ7: =CK7+CL7 -> 78 | CK7: 59.2 | CL7: 18.8 | CM7: =BC7*Y7/(1-Y7) -> 39.484552 | CN7: =(CJ7+CM7)/AD7 -> 0.32723581 | CO7: ='[1]Assets(BoP)'!$BN76 -> 0.30129275 | CR7: =P7/AI7 -> 0.81450026 | CV7: =(E7/1000000000)/AD7 -> 4.0049216e-07 | CW7: =(F7/1000)/(BC7/(1-Y7)) -> 0.6290386 | CY7: =(F7/1000000000)/P7 -> 7.3949168e-07 | CZ7: =P7/(BC7/(1-Y7)) -> 0.85063647 | DA7: =(P7-V7)/BC7 -> 0.85063647 | DB7: =(F7/1000)/P7 -> 0.73949168
A8: 1985 | B8: 140025.54 | C8: 49873.311 | D8: 0.35617295 | E8: 131427.74 | F8: 50738.892 | G8: 0.38605924 | H8: 131427.74 | I8: 50738.892 | J8: 0.38605924 | K8: =C8/B8-D8 -> 0 | L8: =I8/H8-J8 -> 0 | M8: =F8/E8-G8 -> 0 | P8: =WrightZucman!O29 -> 62.681 | U8: =U7+(U$12-U$5)/7 -> 0.35728696 | V8: 33.105 | Y8: =V8/P8 -> 0.52815048 | AA8: =V8/(P8/(1-BE8)) -> 0.45405906 | AD8: =BB8-0.5*AP8+AI8 -> 374.39414 | AE8: =0.5*AP8 -> 6.5841638 | AF8: =AD8-AE8 -> 367.80998 | AG8: =AD8 -> 374.39414 | AH8: =AG8-AI8 -> 296.91484 | AI8: =BC8/(1-Y8)+BD8 -> 77.479308 | AK8: =AL8+AM8 -> 380.97831 | AL8: =BB8 -> 303.499 | AM8: =AI8 -> 77.479308 | AN8: =AK8 -> 380.97831 | AO8: =AN8-AP8 -> 367.80998 | AP8: 13.168328 | AQ8: =AF8-AO8 -> 0 | AR8: =Data!AM8/Data!AK8 -> 0.20336934 | AS8: =Data!AI8/Data!AG8 -> 0.20694583 | AV8: ='[1]Assets(BoP)'!$D77 -> 354.5 | AW8: 16.3 | AX8: ='[1]Assets(BoP)'!$CI77 -> 0 | AY8: =BK8 -> 4.783 | AZ8: =AV8-AW8-AX8+AY8 -> 342.983 | BA8: 39.484 | BB8: =AZ8-BA8 -> 303.499 | BC8: =BA8-BD8 -> 33.945 | BD8: 5.539 | BE8: =BD8/BA8 -> 0.14028467 | BF8: 35.41 | BG8: =BC8/(1-Y8) -> 71.940308 | BI8: ='[1]Assets(BoP)'!$Q77 -> 8.7 | BK8: =BI8-BL8 -> 4.783 | BL8: 3.917 | BM8: 0 | BP8: 1985 | BQ8: =Data!AR8*WrightZucman!B29 -> 0.028554962 | BR8: =$BQ8*WrightZucman!C29/WrightZucman!$B29 -> 0.0036078989 | BS8: =WrightZucman!C29*Data!AS8-BR8 -> 6.3449169e-05 | BT8: =$BQ8*WrightZucman!D29/WrightZucman!$B29 -> 0.0059699046 | BU8: =$BQ8*WrightZucman!E29/WrightZucman!$B29 -> 0.0056162526 | BV8: =$BQ8*WrightZucman!F29/WrightZucman!$B29 -> 0.01170296 | BW8: =$BQ8*WrightZucman!G29/WrightZucman!$B29 -> 0.0016579463 | BX8: =BQ8-BR8-BT8-BU8-BV8-BW8 -> 0 | BZ8: =Data!AR8*WrightZucman!B29 -> 0.028554962 | CA8: =Data!D8*WrightZucman!B29 -> 0.050010022 | CJ8: =CK8+CL8 -> 78.7 | CK8: 58.5 | CL8: 20.2 | CM8: =BC8*Y8/(1-Y8) -> 37.995308 | CN8: =(CJ8+CM8)/AD8 -> 0.31169106 | CO8: ='[1]Assets(BoP)'!$BN77 -> 0.29848576 | CR8: =P8/AI8 -> 0.8090031 | CV8: =(E8/1000000000)/AD8 -> 3.5104111e-07 | CW8: =(F8/1000)/(BC8/(1-Y8)) -> 0.70529156 | CY8: =(F8/1000000000)/P8 -> 8.0947802e-07 | CZ8: =P8/(BC8/(1-Y8)) -> 0.8712918 | DA8: =(P8-V8)/BC8 -> 0.8712918 | DB8: =(F8/1000)/P8 -> 0.80947802
A9: 1986 | B9: 129779.73 | C9: 44262.633 | D9: 0.34105968 | E9: 115241.08 | F9: 44880.514 | G9: 0.38944893 | H9: 116659.98 | I9: 44963.068 | J9: 0.38541983 | K9: =C9/B9-D9 -> 0 | L9: =I9/H9-J9 -> 0 | M9: =F9/E9-G9 -> 0 | P9: =WrightZucman!O30 -> 56.36 | U9: =U8+(U$12-U$5)/7 -> 0.35907935 | V9: 24.454 | Y9: =V9/P9 -> 0.43388928 | AA9: =V9/(P9/(1-BE9)) -> 0.38677704 | AD9: =BB9-0.5*AP9+AI9 -> 335.62667 | AE9: =0.5*AP9 -> 6.2336909 | AF9: =AD9-AE9 -> 329.39298 | AG9: =AD9 -> 335.62667 | AH9: =AG9-AI9 -> 268.13131 | AI9: =BC9/(1-Y9)+BD9 -> 67.495359 | AK9: =AL9+AM9 -> 341.86036 | AL9: =BB9 -> 274.365 | AM9: =AI9 -> 67.495359 | AN9: =AK9 -> 341.86036 | AO9: =AN9-AP9 -> 329.39298 | AP9: 12.467382 | AQ9: =AF9-AO9 -> 0 | AR9: =Data!AM9/Data!AK9 -> 0.19743547 | AS9: =Data!AI9/Data!AG9 -> 0.20110249 | AV9: ='[1]Assets(BoP)'!$D78 -> 324.4 | AW9: 15.5 | AX9: ='[1]Assets(BoP)'!$CI78 -> 0 | AY9: =BK9 -> 5.564 | AZ9: =AV9-AW9-AX9+AY9 -> 314.464 | BA9: 40.099 | BB9: =AZ9-BA9 -> 274.365 | BC9: =BA9-BD9 -> 35.745 | BD9: 4.354 | BE9: =BD9/BA9 -> 0.10858126 | BF9: 36.938 | BG9: =BC9/(1-Y9) -> 63.141359 | BI9: ='[1]Assets(BoP)'!$Q78 -> 9.3 | BK9: =BI9-BL9 -> 5.564 | BL9: 3.736 | BM9: 0 | BP9: 1986 | BQ9: =Data!AR9*WrightZucman!B30 -> 0.029005778 | BR9: =$BQ9*WrightZucman!C30/WrightZucman!$B30 -> 0.0030266899 | BS9: =WrightZucman!C30*Data!AS9-BR9 -> 5.6215584e-05 | BT9: =$BQ9*WrightZucman!D30/WrightZucman!$B30 -> 0.0085721182 | BU9: =$BQ9*WrightZucman!E30/WrightZucman!$B30 -> 0.0056365093 | BV9: =$BQ9*WrightZucman!F30/WrightZucman!$B30 -> 0.0092026786 | BW9: =$BQ9*WrightZucman!G30/WrightZucman!$B30 -> 0.002567782 | BX9: =BQ9-BR9-BT9-BU9-BV9-BW9 -> 0 | BZ9: =Data!AR9*WrightZucman!B30 -> 0.029005778 | CA9: =Data!D9*WrightZucman!B30 -> 0.050106 | CJ9: =CK9+CL9 -> 88.7 | CK9: 66 | CL9: 22.7 | CM9: =BC9*Y9/(1-Y9) -> 27.396359 | CN9: =(CJ9+CM9)/AD9 -> 0.34590922 | CO9: ='[1]Assets(BoP)'!$BN78 -> 0.3517539 | CR9: =P9/AI9 -> 0.83502038 | CV9: =(E9/1000000000)/AD9 -> 3.433609e-07 | CW9: =(F9/1000)/(BC9/(1-Y9)) -> 0.71079424 | CY9: =(F9/1000000000)/P9 -> 7.9631856e-07 | CZ9: =P9/(BC9/(1-Y9)) -> 0.89260036 | DA9: =(P9-V9)/BC9 -> 0.89260036 | DB9: =(F9/1000)/P9 -> 0.79631856
A10: 1987 | B10: 146090.89 | C10: 48273.071 | D10: 0.33043177 | E10: 134045.91 | F10: 50815.005 | G10: 0.37908657 | H10: 138340.81 | I10: 49215.388 | J10: 0.35575465 | K10: =C10/B10-D10 -> 0 | L10: =I10/H10-J10 -> 0 | M10: =F10/E10-G10 -> 0 | P10: =WrightZucman!O31 -> 70.626 | U10: =U9+(U$12-U$5)/7 -> 0.36087174 | V10: 27.928 | Y10: =V10/P10 -> 0.39543511 | AA10: =V10/(P10/(1-BE10)) -> 0.35572642 | AD10: =BB10-0.5*AP10+AI10 -> 372.81728 | AE10: =0.5*AP10 -> 12.22623 | AF10: =AD10-AE10 -> 360.59105 | AG10: =AD10 -> 372.81728 | AH10: =AG10-AI10 -> 295.62577 | AI10: =BC10/(1-Y10)+BD10 -> 77.19151 | AK10: =AL10+AM10 -> 385.04351 | AL10: =BB10 -> 307.852 | AM10: =AI10 -> 77.19151 | AN10: =AK10 -> 385.04351 | AO10: =AN10-AP10 -> 360.59105 | AP10: 24.452461 | AQ10: =AF10-AO10 -> 0 | AR10: =Data!AM10/Data!AK10 -> 0.20047477 | AS10: =Data!AI10/Data!AG10 -> 0.20704917 | AV10: ='[1]Assets(BoP)'!$D79 -> 366 | AW10: 16.2 | AX10: ='[1]Assets(BoP)'!$CI79 -> 0 | AY10: =BK10 -> 6.649 | AZ10: =AV10-AW10-AX10+AY10 -> 356.449 | BA10: 48.597 | BB10: =AZ10-BA10 -> 307.852 | BC10: =BA10-BD10 -> 43.717 | BD10: 4.88 | BE10: =BD10/BA10 -> 0.10041772 | BF10: 46.287 | BG10: =BC10/(1-Y10) -> 72.31151 | BI10: ='[1]Assets(BoP)'!$Q79 -> 10.9 | BK10: =BI10-BL10 -> 6.649 | BL10: 4.251 | BM10: 0 | BP10: 1987 | BQ10: =Data!AR10*WrightZucman!B31 -> 0.034300925 | BR10: =$BQ10*WrightZucman!C31/WrightZucman!$B31 -> 0.0056430188 | BS10: =WrightZucman!C31*Data!AS10-BR10 -> 0.00018505807 | BT10: =$BQ10*WrightZucman!D31/WrightZucman!$B31 -> 0.010380543 | BU10: =$BQ10*WrightZucman!E31/WrightZucman!$B31 -> 0.0060716384 | BV10: =$BQ10*WrightZucman!F31/WrightZucman!$B31 -> 0.0094949185 | BW10: =$BQ10*WrightZucman!G31/WrightZucman!$B31 -> 0.0027108063 | BX10: =BQ10-BR10-BT10-BU10-BV10-BW10 -> 0 | BZ10: =Data!AR10*WrightZucman!B31 -> 0.034300925 | CA10: =Data!D10*WrightZucman!B31 -> 0.056536367 | CJ10: =CK10+CL10 -> 109.3 | CK10: 85.4 | CL10: 23.9 | CM10: =BC10*Y10/(1-Y10) -> 28.59451 | CN10: =(CJ10+CM10)/AD10 -> 0.36987156 | CO10: ='[1]Assets(BoP)'!$BN79 -> 0.38003278 | CR10: =P10/AI10 -> 0.91494518 | CV10: =(E10/1000000000)/AD10 -> 3.5954855e-07 | CW10: =(F10/1000)/(BC10/(1-Y10)) -> 0.70272361 | CY10: =(F10/1000000000)/P10 -> 7.1949431e-07 | CZ10: =P10/(BC10/(1-Y10)) -> 0.97669099 | DA10: =(P10-V10)/BC10 -> 0.97669099 | DB10: =(F10/1000)/P10 -> 0.71949431
A11: 1988 | B11: 172288.08 | C11: 63305.276 | D11: 0.36743852 | E11: 167419.38 | F11: 64231.958 | G11: 0.38365905 | H11: 167419.38 | I11: 64231.958 | J11: 0.38365905 | K11: =C11/B11-D11 -> 0 | L11: =I11/H11-J11 -> 0 | M11: =F11/E11-G11 -> 0 | P11: =WrightZucman!O32 -> 80.267 | U11: =U10+(U$12-U$5)/7 -> 0.36266413 | V11: 30.842 | Y11: =V11/P11 -> 0.38424259 | AA11: =V11/(P11/(1-BE11)) -> 0.35897413 | AD11: =BB11-0.5*AP11+AI11 -> 415.05704 | AE11: =0.5*AP11 -> 23.534675 | AF11: =AD11-AE11 -> 391.52236 | AG11: =AD11 -> 415.05704 | AH11: =AG11-AI11 -> 320.48033 | AI11: =BC11/(1-Y11)+BD11 -> 94.576711 | AK11: =AL11+AM11 -> 438.59171 | AL11: =BB11 -> 344.015 | AM11: =AI11 -> 94.576711 | AN11: =AK11 -> 438.59171 | AO11: =AN11-AP11 -> 391.52236 | AP11: 47.06935 | AQ11: =AF11-AO11 -> 0 | AR11: =Data!AM11/Data!AK11 -> 0.21563725 | AS11: =Data!AI11/Data!AG11 -> 0.22786437 | AV11: ='[1]Assets(BoP)'!$D80 -> 414.5 | AW11: 18.1 | AX11: ='[1]Assets(BoP)'!$CI80 -> 0 | AY11: =BK11 -> 7.361 | AZ11: =AV11-AW11-AX11+AY11 -> 403.761 | BA11: 59.746 | BB11: =AZ11-BA11 -> 344.015 | BC11: =BA11-BD11 -> 55.817 | BD11: 3.929 | BE11: =BD11/BA11 -> 0.065761725 | BF11: 58.445 | BG11: =BC11/(1-Y11) -> 90.647711 | BI11: ='[1]Assets(BoP)'!$Q80 -> 14.6 | BK11: =BI11-BL11 -> 7.361 | BL11: 7.239 | BM11: 0 | BP11: 1988 | BQ11: =Data!AR11*WrightZucman!B32 -> 0.030150583 | BR11: =$BQ11*WrightZucman!C32/WrightZucman!$B32 -> 0.0049404725 | BS11: =WrightZucman!C32*Data!AS11-BR11 -> 0.00028013599 | BT11: =$BQ11*WrightZucman!D32/WrightZucman!$B32 -> 0.011801792 | BU11: =$BQ11*WrightZucman!E32/WrightZucman!$B32 -> 0.0055153834 | BV11: =$BQ11*WrightZucman!F32/WrightZucman!$B32 -> 0.004814207 | BW11: =$BQ11*WrightZucman!G32/WrightZucman!$B32 -> 0.0030787284 | BX11: =BQ11-BR11-BT11-BU11-BV11-BW11 -> 0 | BZ11: =Data!AR11*WrightZucman!B32 -> 0.030150583 | CA11: =Data!D11*WrightZucman!B32 -> 0.051375565 | CJ11: =CK11+CL11 -> 119.8 | CK11: 93.8 | CL11: 26 | CM11: =BC11*Y11/(1-Y11) -> 34.830711 | CN11: =(CJ11+CM11)/AD11 -> 0.37255292 | CO11: ='[1]Assets(BoP)'!$BN80 -> 0.39111072 | CR11: =P11/AI11 -> 0.8486973 | CV11: =(E11/1000000000)/AD11 -> 4.0336474e-07 | CW11: =(F11/1000)/(BC11/(1-Y11)) -> 0.70858885 | CY11: =(F11/1000000000)/P11 -> 8.0022871e-07 | CZ11: =P11/(BC11/(1-Y11)) -> 0.88548292 | DA11: =(P11-V11)/BC11 -> 0.88548292 | DB11: =(F11/1000)/P11 -> 0.80022871
A12: 1989 | B12: 166283.96 | C12: 65590.438 | D12: 0.39444837 | E12: 159689.31 | F12: 66124.966 | G12: 0.41408513 | H12: 159689.31 | I12: 66087.898 | J12: 0.413853 | K12: =C12/B12-D12 -> 0 | L12: =I12/H12-J12 -> 0 | M12: =F12/E12-G12 -> 0 | O12: =170.663+60.446-49.377-22.056 -> 159.676 | P12: =WrightZucman!O33 -> 85.594 | Q12: =P12/(P12+O12) -> 0.34897868 | R12: =BC12/(1-Y12) -> 91.567235 | T12: =R12/(R12+O12) -> 0.36445652 | U12: =T12 -> 0.36445652 | V12: 33.291 | W12: =60.446 -> 60.446 | X12: =W12/O12 -> 0.37855407 | Y12: =V12/P12 -> 0.38894081 | Z12: =(V12+W12)/(O12+P12) -> 0.38217882 | AA12: =V12/(P12/(1-BE12)) -> 0.35216528 | AB12: =(V12+W12)/(P12/(1-BE12)+O12) -> 0.36874088 | AD12: =BB12-0.5*AP12+AI12 -> 413.26943 | AE12: =0.5*AP12 -> 24.513808 | AF12: =AD12-AE12 -> 388.75562 | AG12: =AD12 -> 413.26943 | AH12: =AG12-AI12 -> 315.85919 | AI12: =BC12/(1-Y12)+BD12 -> 97.410235 | AK12: =AL12+AM12 -> 437.78323 | AL12: =BB12 -> 340.373 | AM12: =AI12 -> 97.410235 | AN12: =AK12 -> 437.78323 | AO12: =AN12-AP12 -> 388.75562 | AP12: 49.027616 | AQ12: =AF12-AO12 -> 0 | AR12: =Data!AM12/Data!AK12 -> 0.22250792 | AS12: =Data!AI12/Data!AG12 -> 0.23570637 | AV12: ='[1]Assets(BoP)'!$D81 -> 414.3 | AW12: 20.7 | AX12: ='[1]Assets(BoP)'!$CI81 -> 0 | AY12: =BK12 -> 8.569 | AZ12: =AV12-AW12-AX12+AY12 -> 402.169 | BA12: 61.796 | BB12: =AZ12-BA12 -> 340.373 | BC12: =BA12-BD12 -> 55.953 | BD12: 5.843 | BE12: =BD12/BA12 -> 0.094553046 | BF12: 61.981 | BG12: =BC12/(1-Y12) -> 91.567235 | BI12: ='[1]Assets(BoP)'!$Q81 -> 8.4 | BK12: =BI12-BL12 -> 8.569 | BL12: -0.169 | BM12: 0 | BP12: 1989 | BQ12: =Data!AR12*WrightZucman!B33 -> 0.037366273 | BR12: =$BQ12*WrightZucman!C33/WrightZucman!$B33 -> 0.0069642581 | BS12: =WrightZucman!C33*Data!AS12-BR12 -> 0.0004130973 | BT12: =$BQ12*WrightZucman!D33/WrightZucman!$B33 -> 0.01091561 | BU12: =$BQ12*WrightZucman!E33/WrightZucman!$B33 -> 0.0055552891 | BV12: =$BQ12*WrightZucman!F33/WrightZucman!$B33 -> 0.01073104 | BW12: =$BQ12*WrightZucman!G33/WrightZucman!$B33 -> 0.0032000753 | BX12: =BQ12-BR12-BT12-BU12-BV12-BW12 -> 0 | BZ12: =Data!AR12*WrightZucman!B33 -> 0.037366273 | CA12: =Data!D12*WrightZucman!B33 -> 0.066240634 | CB12: =Data!Q12*WrightZucman!B33 -> 0.058604803 | CC12: =WrightZucman!C33*Data!$Q12 -> 0.010922657 | CD12: =WrightZucman!D33*Data!$Q12 -> 0.017119909 | CE12: =WrightZucman!E33*Data!$Q12 -> 0.0087128471 | CF12: =WrightZucman!F33*Data!$Q12 -> 0.016830432 | CG12: =WrightZucman!G33*Data!$Q12 -> 0.0050189587 | CH12: =CB12-CC12-CD12-CE12-CF12-CG12 -> 7.8062556e-18 | CJ12: =CK12+CL12 -> 119.8 | CK12: 95.6 | CL12: 24.2 | CM12: =BC12*Y12/(1-Y12) -> 35.614235 | CN12: =(CJ12+CM12)/AD12 -> 0.37606032 | CO12: ='[1]Assets(BoP)'!$BN81 -> 0.40047162 | CQ12: =(O12+P12)/AD12 -> 0.59348692 | CR12: =P12/AI12 -> 0.87869617 | CS12: =O12/AL12 -> 0.46912064 | CT12: =O12/(AL12-0.5*AP12) -> 0.50552906 | CU12: =(O12+P12)/AD12 -> 0.59348692 | CV12: =(E12/1000000000)/AD12 -> 3.8640484e-07 | CW12: =(F12/1000)/(BC12/(1-Y12)) -> 0.72214659 | CX12: =((E12-F12)/1000000000)/O12 -> 5.859637e-07 | CY12: =(F12/1000000000)/P12 -> 7.7254207e-07 | CZ12: =P12/(BC12/(1-Y12)) -> 0.93476668 | DA12: =(P12-V12)/BC12 -> 0.93476668 | DB12: =(F12/1000)/P12 -> 0.77254207
A13: 1990 | B13: 167372.79 | C13: 64101.505 | D13: 0.38298643 | E13: 156190.24 | F13: 68765.056 | G13: 0.44026474 | H13: 158439.14 | I13: 66020.98 | J13: 0.41669614 | K13: =C13/B13-D13 -> 0 | L13: =I13/H13-J13 -> 0 | M13: =F13/E13-G13 -> 0 | P13: =WrightZucman!O34 -> 84.575 | U13: =U12+(U$17-U$12)/5 -> 0.35222298 | V13: 31.693 | Y13: =V13/P13 -> 0.37473249 | AA13: =V13/(P13/(1-BE13)) -> 0.33853189 | AD13: =BB13-0.5*AP13+AI13 -> 415.42516 | AE13: =0.5*AP13 -> 24.645542 | AF13: =AD13-AE13 -> 390.77962 | AG13: =AD13 -> 415.42516 | AH13: =AG13-AI13 -> 316.48146 | AI13: =BC13/(1-Y13)+BD13 -> 98.943704 | AK13: =AL13+AM13 -> 440.0707 | AL13: =BB13 -> 341.127 | AM13: =AI13 -> 98.943704 | AN13: =AK13 -> 440.0707 | AO13: =AN13-AP13 -> 390.77962 | AP13: 49.291084 | AQ13: =AF13-AO13 -> 0 | AR13: =Data!AM13/Data!AK13 -> 0.22483593 | AS13: =Data!AI13/Data!AG13 -> 0.23817456 | AV13: ='[1]Assets(BoP)'!$D82 -> 417.7 | AW13: 21.9 | AX13: ='[1]Assets(BoP)'!$CI82 -> 0 | AY13: =BK13 -> 9.517 | AZ13: =AV13-AW13-AX13+AY13 -> 405.317 | BA13: 64.19 | BB13: =AZ13-BA13 -> 341.127 | BC13: =BA13-BD13 -> 57.989 | BD13: 6.201 | BE13: =BD13/BA13 -> 0.096603832 | BF13: 65.973 | BG13: =BC13/(1-Y13) -> 92.742704 | BI13: ='[1]Assets(BoP)'!$Q82 -> 4.8 | BK13: =BI13-BL13 -> 9.517 | BL13: -4.717 | BM13: 0 | BP13: 1990 | BQ13: =Data!AR13*WrightZucman!B34 -> 0.043972936 | BR13: =$BQ13*WrightZucman!C34/WrightZucman!$B34 -> 0.0083793419 | BS13: =WrightZucman!C34*Data!AS13-BR13 -> 0.00049711342 | BT13: =$BQ13*WrightZucman!D34/WrightZucman!$B34 -> 0.012563696 | BU13: =$BQ13*WrightZucman!E34/WrightZucman!$B34 -> 0.0068560668 | BV13: =$BQ13*WrightZucman!F34/WrightZucman!$B34 -> 0.010482153 | BW13: =$BQ13*WrightZucman!G34/WrightZucman!$B34 -> 0.0056916786 | BX13: =BQ13-BR13-BT13-BU13-BV13-BW13 -> 0 | BZ13: =Data!AR13*WrightZucman!B34 -> 0.043972936 | CA13: =Data!D13*WrightZucman!B34 -> 0.074903677 | CJ13: =CK13+CL13 -> 117 | CK13: 94.5 | CL13: 22.5 | CM13: =BC13*Y13/(1-Y13) -> 34.753704 | CN13: =(CJ13+CM13)/AD13 -> 0.36529733 | CO13: ='[1]Assets(BoP)'!$BN82 -> 0.40033205 | CR13: =P13/AI13 -> 0.854779 | CV13: =(E13/1000000000)/AD13 -> 3.7597685e-07 | CW13: =(F13/1000)/(BC13/(1-Y13)) -> 0.74146055 | CY13: =(F13/1000000000)/P13 -> 8.1306599e-07 | CZ13: =P13/(BC13/(1-Y13)) -> 0.91193157 | DA13: =(P13-V13)/BC13 -> 0.91193157 | DB13: =(F13/1000)/P13 -> 0.81306599
A14: 1991 | B14: 135501.25 | C14: 49338.892 | D14: 0.36412132 | E14: 108264.38 | F14: 52632.041 | G14: 0.48614365 | H14: 116142.38 | I14: 49483.292 | J14: 0.42605715 | K14: =C14/B14-D14 -> 0 | L14: =I14/H14-J14 -> 0 | M14: =F14/E14-G14 -> 0 | P14: =WrightZucman!O35 -> 73.301 | U14: =U13+(U$17-U$12)/5 -> 0.33998943 | V14: 26.877 | Y14: =V14/P14 -> 0.36666621 | AA14: =V14/(P14/(1-BE14)) -> 0.33353072 | AD14: =BB14-0.5*AP14+AI14 -> 450.29241 | AE14: =0.5*AP14 -> 21.480688 | AF14: =AD14-AE14 -> 428.81172 | AG14: =AD14 -> 450.29241 | AH14: =AG14-AI14 -> 362.56631 | AI14: =BC14/(1-Y14)+BD14 -> 87.726099 | AK14: =AL14+AM14 -> 471.7731 | AL14: =BB14 -> 384.047 | AM14: =AI14 -> 87.726099 | AN14: =AK14 -> 471.7731 | AO14: =AN14-AP14 -> 428.81172 | AP14: 42.961375 | AQ14: =AF14-AO14 -> 0 | AR14: =Data!AM14/Data!AK14 -> 0.18594977 | AS14: =Data!AI14/Data!AG14 -> 0.19482029 | AV14: ='[1]Assets(BoP)'!$D83 -> 452.6 | AW14: 20.8 | AX14: ='[1]Assets(BoP)'!$CI83 -> 0 | AY14: =BK14 -> 9.711 | AZ14: =AV14-AW14-AX14+AY14 -> 441.511 | BA14: 57.464 | BB14: =AZ14-BA14 -> 384.047 | BC14: =BA14-BD14 -> 52.271 | BD14: 5.193 | BE14: =BD14/BA14 -> 0.090369623 | BF14: 58.717 | BG14: =BC14/(1-Y14) -> 82.533099 | BI14: ='[1]Assets(BoP)'!$Q83 -> -1 | BK14: =BI14-BL14 -> 9.711 | BL14: -10.711 | BM14: 0 | BP14: 1991 | BQ14: =Data!AR14*WrightZucman!B35 -> 0.038729282 | BR14: =$BQ14*WrightZucman!C35/WrightZucman!$B35 -> 0.0076459066 | BS14: =WrightZucman!C35*Data!AS14-BR14 -> 0.00036473929 | BT14: =$BQ14*WrightZucman!D35/WrightZucman!$B35 -> 0.010898081 | BU14: =$BQ14*WrightZucman!E35/WrightZucman!$B35 -> 0.0070878113 | BV14: =$BQ14*WrightZucman!F35/WrightZucman!$B35 -> 0.0087164351 | BW14: =$BQ14*WrightZucman!G35/WrightZucman!$B35 -> 0.0043810487 | BX14: =BQ14-BR14-BT14-BU14-BV14-BW14 -> 0 | BZ14: =Data!AR14*WrightZucman!B35 -> 0.038729282 | CA14: =Data!D14*WrightZucman!B35 -> 0.075838531 | CJ14: =CK14+CL14 -> 112.8 | CK14: 89.2 | CL14: 23.6 | CM14: =BC14*Y14/(1-Y14) -> 30.262099 | CN14: =(CJ14+CM14)/AD14 -> 0.31770933 | CO14: ='[1]Assets(BoP)'!$BN83 -> 0.34828754 | CR14: =P14/AI14 -> 0.83556662 | CV14: =(E14/1000000000)/AD14 -> 2.4043128e-07 | CW14: =(F14/1000)/(BC14/(1-Y14)) -> 0.63770829 | CY14: =(F14/1000000000)/P14 -> 7.1802623e-07 | CZ14: =P14/(BC14/(1-Y14)) -> 0.88814065 | DA14: =(P14-V14)/BC14 -> 0.88814065 | DB14: =(F14/1000)/P14 -> 0.71802623
A15: 1992 | B15: 157749.97 | C15: 48112.432 | D15: 0.3049917 | E15: 125440.12 | F15: 47824.37 | G15: 0.38125258 | H15: 141441.82 | I15: 46567.968 | J15: 0.32923763 | K15: =C15/B15-D15 -> 0 | L15: =I15/H15-J15 -> 0 | M15: =F15/E15-G15 -> 0 | P15: =WrightZucman!O36 -> 69.447 | U15: =U14+(U$17-U$12)/5 -> 0.32775589 | V15: 26.686 | Y15: =V15/P15 -> 0.38426426 | AA15: =V15/(P15/(1-BE15)) -> 0.34595034 | AD15: =BB15-0.5*AP15+AI15 -> 467.32345 | AE15: =0.5*AP15 -> 32.913532 | AF15: =AD15-AE15 -> 434.40992 | AG15: =AD15 -> 467.32345 | AH15: =AG15-AI15 -> 379.30547 | AI15: =BC15/(1-Y15)+BD15 -> 88.017985 | AK15: =AL15+AM15 -> 500.23698 | AL15: =BB15 -> 412.219 | AM15: =AI15 -> 88.017985 | AN15: =AK15 -> 500.23698 | AO15: =AN15-AP15 -> 434.40992 | AP15: 65.827065 | AQ15: =AF15-AO15 -> 0 | AR15: =Data!AM15/Data!AK15 -> 0.17595257 | AS15: =Data!AI15/Data!AG15 -> 0.18834489 | AV15: ='[1]Assets(BoP)'!$D84 -> 477.2 | AW15: 18.4 | AX15: ='[1]Assets(BoP)'!$CI84 -> 0 | AY15: =BK15 -> 9.774 | AZ15: =AV15-AW15-AX15+AY15 -> 468.574 | BA15: 56.355 | BB15: =AZ15-BA15 -> 412.219 | BC15: =BA15-BD15 -> 50.736 | BD15: 5.619 | BE15: =BD15/BA15 -> 0.099707213 | BF15: 57.539 | BG15: =BC15/(1-Y15) -> 82.398985 | BI15: ='[1]Assets(BoP)'!$Q84 -> 5.2 | BK15: =BI15-BL15 -> 9.774 | BL15: -4.574 | BM15: 0 | BP15: 1992 | BQ15: =Data!AR15*WrightZucman!B36 -> 0.034173518 | BR15: =$BQ15*WrightZucman!C36/WrightZucman!$B36 -> 0.0087790065 | BS15: =WrightZucman!C36*Data!AS15-BR15 -> 0.00061830433 | BT15: =$BQ15*WrightZucman!D36/WrightZucman!$B36 -> 0.0095948334 | BU15: =$BQ15*WrightZucman!E36/WrightZucman!$B36 -> 0.003805503 | BV15: =$BQ15*WrightZucman!F36/WrightZucman!$B36 -> 0.0081785377 | BW15: =$BQ15*WrightZucman!G36/WrightZucman!$B36 -> 0.0038156375 | BX15: =BQ15-BR15-BT15-BU15-BV15-BW15 -> 0 | BZ15: =Data!AR15*WrightZucman!B36 -> 0.034173518 | CA15: =Data!D15*WrightZucman!B36 -> 0.059235504 | CJ15: =CK15+CL15 -> 126.4 | CK15: 102 | CL15: 24.4 | CM15: =BC15*Y15/(1-Y15) -> 31.662985 | CN15: =(CJ15+CM15)/AD15 -> 0.33823037 | CO15: ='[1]Assets(BoP)'!$BN84 -> 0.37780778 | CR15: =P15/AI15 -> 0.7890092 | CV15: =(E15/1000000000)/AD15 -> 2.6842248e-07 | CW15: =(F15/1000)/(BC15/(1-Y15)) -> 0.58039999 | CY15: =(F15/1000000000)/P15 -> 6.8864559e-07 | CZ15: =P15/(BC15/(1-Y15)) -> 0.84281378 | DA15: =(P15-V15)/BC15 -> 0.84281378 | DB15: =(F15/1000)/P15 -> 0.68864559
A16: 1993 | B16: 178070.18 | C16: 50243.837 | D16: 0.2821575 | E16: 147436.37 | F16: 46877.183 | G16: 0.31794858 | H16: 157103.17 | I16: 49368.896 | J16: 0.31424507 | K16: =C16/B16-D16 -> 0 | L16: =I16/H16-J16 -> 0 | M16: =F16/E16-G16 -> 0 | P16: =WrightZucman!O37 -> 73.787 | U16: =U15+(U$17-U$12)/5 -> 0.31552235 | V16: 24.316 | Y16: =V16/P16 -> 0.32954314 | AA16: =V16/(P16/(1-BE16)) -> 0.29585249 | AD16: =BB16-0.5*AP16+AI16 -> 513.45903 | AE16: =0.5*AP16 -> 33.460841 | AF16: =AD16-AE16 -> 479.99818 | AG16: =AD16 -> 513.45903 | AH16: =AG16-AI16 -> 418.96216 | AI16: =BC16/(1-Y16)+BD16 -> 94.496867 | AK16: =AL16+AM16 -> 546.91987 | AL16: =BB16 -> 452.423 | AM16: =AI16 -> 94.496867 | AN16: =AK16 -> 546.91987 | AO16: =AN16-AP16 -> 479.99818 | AP16: 66.921683 | AQ16: =AF16-AO16 -> 0 | AR16: =Data!AM16/Data!AK16 -> 0.1727801 | AS16: =Data!AI16/Data!AG16 -> 0.18403974 | AV16: ='[1]Assets(BoP)'!$D85 -> 524.6 | AW16: 16.8 | AX16: ='[1]Assets(BoP)'!$CI85 -> 0 | AY16: =BK16 -> 10.188 | AZ16: =AV16-AW16-AX16+AY16 -> 517.988 | BA16: 65.565 | BB16: =AZ16-BA16 -> 452.423 | BC16: =BA16-BD16 -> 58.862 | BD16: 6.703 | BE16: =BD16/BA16 -> 0.10223442 | BF16: 67.245 | BG16: =BC16/(1-Y16) -> 87.793867 | BI16: ='[1]Assets(BoP)'!$Q85 -> 12 | BK16: =BI16-BL16 -> 10.188 | BL16: 1.812 | BM16: 0 | BP16: 1993 | BQ16: =Data!AR16*WrightZucman!B37 -> 0.033246125 | BR16: =$BQ16*WrightZucman!C37/WrightZucman!$B37 -> 0.0077905238 | BS16: =WrightZucman!C37*Data!AS16-BR16 -> 0.00050768896 | BT16: =$BQ16*WrightZucman!D37/WrightZucman!$B37 -> 0.0072636624 | BU16: =$BQ16*WrightZucman!E37/WrightZucman!$B37 -> 0.0046715043 | BV16: =$BQ16*WrightZucman!F37/WrightZucman!$B37 -> 0.0075727544 | BW16: =$BQ16*WrightZucman!G37/WrightZucman!$B37 -> 0.0059476797 | BX16: =BQ16-BR16-BT16-BU16-BV16-BW16 -> 0 | BZ16: =Data!AR16*WrightZucman!B37 -> 0.033246125 | CA16: =Data!D16*WrightZucman!B37 -> 0.054292385 | CJ16: =CK16+CL16 -> 149.4 | CK16: 122.5 | CL16: 26.9 | CM16: =BC16*Y16/(1-Y16) -> 28.931867 | CN16: =(CJ16+CM16)/AD16 -> 0.3473147 | CO16: ='[1]Assets(BoP)'!$BN85 -> 0.38705472 | CR16: =P16/AI16 -> 0.7808407 | CV16: =(E16/1000000000)/AD16 -> 2.8714339e-07 | CW16: =(F16/1000)/(BC16/(1-Y16)) -> 0.53394599 | CY16: =(F16/1000000000)/P16 -> 6.3530409e-07 | CZ16: =P16/(BC16/(1-Y16)) -> 0.84045734 | DA16: =(P16-V16)/BC16 -> 0.84045734 | DB16: =(F16/1000)/P16 -> 0.63530409
A17: 1994 | B17: 239721.16 | C17: 73372.816 | D17: 0.30607568 | E17: 230103.77 | F17: 72384.577 | G17: 0.31457363 | H17: 231342.66 | I17: 73160.513 | J17: 0.31624307 | K17: =C17/B17-D17 -> 0 | L17: =I17/H17-J17 -> 0 | M17: =F17/E17-G17 -> 0 | O17: 238.853 | P17: =WrightZucman!O38 -> 84.9 | Q17: =P17/(P17+O17) -> 0.26223695 | R17: =BC17/(1-Y17) -> 103.97628 | T17: =R17/(R17+O17) -> 0.30328881 | U17: =T17 -> 0.30328881 | V17: 29.277 | W17: 93.957 | X17: =W17/O17 -> 0.39336747 | Y17: =V17/P17 -> 0.34484099 | Z17: =(V17+W17)/(O17+P17) -> 0.38064203 | AA17: =V17/(P17/(1-BE17)) -> 0.31305773 | AB17: =(V17+W17)/(P17/(1-BE17)+O17) -> 0.37077076 | AD17: =BB17-0.5*AP17+AI17 -> 605.6273 | AE17: =0.5*AP17 -> 47.872983 | AF17: =AD17-AE17 -> 557.75432 | AG17: =AD17 -> 605.6273 | AH17: =AG17-AI17 -> 494.73502 | AI17: =BC17/(1-Y17)+BD17 -> 110.89228 | AK17: =AL17+AM17 -> 653.50028 | AL17: =BB17 -> 542.608 | AM17: =AI17 -> 110.89228 | AN17: =AK17 -> 653.50028 | AO17: =AN17-AP17 -> 557.75432 | AP17: 95.745966 | AQ17: =AF17-AO17 -> 0 | AR17: =Data!AM17/Data!AK17 -> 0.16968973 | AS17: =Data!AI17/Data!AG17 -> 0.18310318 | AV17: ='[1]Assets(BoP)'!$D86 -> 624.8 | AW17: 18.6 | AX17: ='[1]Assets(BoP)'!$CI86 -> 0 | AY17: =BK17 -> 11.445 | AZ17: =AV17-AW17-AX17+AY17 -> 617.645 | BA17: 75.037 | BB17: =AZ17-BA17 -> 542.608 | BC17: =BA17-BD17 -> 68.121 | BD17: 6.916 | BE17: =BD17/BA17 -> 0.092167864 | BF17: 77.344 | BG17: =BC17/(1-Y17) -> 103.97628 | BI17: ='[1]Assets(BoP)'!$Q86 -> 26.6 | BK17: =BI17-BL17 -> 11.445 | BL17: 15.155 | BM17: 0 | BP17: 1994 | BQ17: =Data!AR17*WrightZucman!B38 -> 0.032121126 | BR17: =$BQ17*WrightZucman!C38/WrightZucman!$B38 -> 0.0077269786 | BS17: =WrightZucman!C38*Data!AS17-BR17 -> 0.00061079399 | BT17: =$BQ17*WrightZucman!D38/WrightZucman!$B38 -> 0.0079508331 | BU17: =$BQ17*WrightZucman!E38/WrightZucman!$B38 -> 0.0046829568 | BV17: =$BQ17*WrightZucman!F38/WrightZucman!$B38 -> 0.0060580632 | BW17: =$BQ17*WrightZucman!G38/WrightZucman!$B38 -> 0.0057022944 | BX17: =BQ17-BR17-BT17-BU17-BV17-BW17 -> 0 | BZ17: =Data!AR17*WrightZucman!B38 -> 0.032121126 | CA17: =Data!D17*WrightZucman!B38 -> 0.05793807 | CB17: =Data!Q17*WrightZucman!B38 -> 0.049639694 | CC17: =WrightZucman!C38*Data!$Q17 -> 0.011941202 | CD17: =WrightZucman!D38*Data!$Q17 -> 0.012287145 | CE17: =WrightZucman!E38*Data!$Q17 -> 0.0072369986 | CF17: =WrightZucman!F38*Data!$Q17 -> 0.0093620754 | CG17: =WrightZucman!G38*Data!$Q17 -> 0.0088122736 | CH17: =CB17-CC17-CD17-CE17-CF17-CG17 -> 0 | CJ17: =CK17+CL17 -> 166.3 | CK17: 136.3 | CL17: 30 | CM17: =BC17*Y17/(1-Y17) -> 35.855285 | CN17: =(CJ17+CM17)/AD17 -> 0.33379487 | CO17: ='[1]Assets(BoP)'!$BN86 -> 0.3642685 | CQ17: =(O17+P17)/AD17 -> 0.53457465 | CR17: =P17/AI17 -> 0.76560781 | CS17: =O17/AL17 -> 0.44019439 | CT17: =O17/(AL17-0.5*AP17) -> 0.48278976 | CU17: =(O17+P17)/AD17 -> 0.53457465 | CV17: =(E17/1000000000)/AD17 -> 3.7994286e-07 | CW17: =(F17/1000)/(BC17/(1-Y17)) -> 0.69616429 | CX17: =((E17-F17)/1000000000)/O17 -> 6.6031907e-07 | CY17: =(F17/1000000000)/P17 -> 8.525863e-07 | CZ17: =P17/(BC17/(1-Y17)) -> 0.81653235 | DA17: =(P17-V17)/BC17 -> 0.81653235 | DB17: =(F17/1000)/P17 -> 0.8525863
A18: 1995 | B18: 272903.04 | C18: 94225.192 | D18: 0.34526985 | E18: 255810.62 | F18: 93586.162 | G18: 0.36584159 | H18: 257936.19 | I18: 94016.584 | J18: 0.36449552 | K18: =C18/B18-D18 -> 0 | L18: =I18/H18-J18 -> 0 | M18: =F18/E18-G18 -> 0 | O18: 266.285 | P18: =WrightZucman!O39 -> 114.88 | Q18: =P18/(P18+O18) -> 0.30139179 | R18: =BC18/(1-Y18) -> 130.04804 | T18: =R18/(R18+O18) -> 0.32812819 | U18: =T18 -> 0.32812819 | V18: 38.801 | Y18: =V18/P18 -> 0.33775244 | AA18: =V18/(P18/(1-BE18)) -> 0.31345464 | AD18: =BB18-0.5*AP18+AI18 -> 687.21747 | AE18: =0.5*AP18 -> 52.024572 | AF18: =AD18-AE18 -> 635.1929 | AG18: =AD18 -> 687.21747 | AH18: =AG18-AI18 -> 550.49343 | AI18: =BC18/(1-Y18)+BD18 -> 136.72404 | AK18: =AL18+AM18 -> 739.24204 | AL18: =BB18 -> 602.518 | AM18: =AI18 -> 136.72404 | AN18: =AK18 -> 739.24204 | AO18: =AN18-AP18 -> 635.1929 | AP18: 104.04914 | AQ18: =AF18-AO18 -> 0 | AR18: =Data!AM18/Data!AK18 -> 0.18495166 | AS18: =Data!AI18/Data!AG18 -> 0.1989531 | AV18: ='[1]Assets(BoP)'!$D87 -> 706.2 | AW18: 23.1 | AX18: ='[1]Assets(BoP)'!$CI87 -> 0 | AY18: =BK18 -> 12.218 | AZ18: =AV18-AW18-AX18+AY18 -> 695.318 | BA18: 92.8 | BB18: =AZ18-BA18 -> 602.518 | BC18: =BA18-BD18 -> 86.124 | BD18: 6.676 | BE18: =BD18/BA18 -> 0.071939655 | BF18: 95.26 | BG18: =BC18/(1-Y18) -> 130.04804 | BI18: ='[1]Assets(BoP)'!$Q87 -> 34.4 | BK18: =BI18-BL18 -> 12.218 | BL18: 22.182 | BM18: 0 | BP18: 1995 | BQ18: =Data!AR18*WrightZucman!B39 -> 0.038560039 | BR18: =$BQ18*WrightZucman!C39/WrightZucman!$B39 -> 0.0084265059 | BS18: =WrightZucman!C39*Data!AS18-BR18 -> 0.00063791359 | BT18: =$BQ18*WrightZucman!D39/WrightZucman!$B39 -> 0.010955746 | BU18: =$BQ18*WrightZucman!E39/WrightZucman!$B39 -> 0.0057829593 | BV18: =$BQ18*WrightZucman!F39/WrightZucman!$B39 -> 0.007017795 | BW18: =$BQ18*WrightZucman!G39/WrightZucman!$B39 -> 0.0063770328 | BX18: =BQ18-BR18-BT18-BU18-BV18-BW18 -> 0 | BZ18: =Data!AR18*WrightZucman!B39 -> 0.038560039 | CA18: =Data!D18*WrightZucman!B39 -> 0.071984316 | CB18: =Data!Q18*WrightZucman!B39 -> 0.062836304 | CC18: =WrightZucman!C39*Data!$Q18 -> 0.013731586 | CD18: =WrightZucman!D39*Data!$Q18 -> 0.017853161 | CE18: =WrightZucman!E39*Data!$Q18 -> 0.0094237404 | CF18: =WrightZucman!F39*Data!$Q18 -> 0.011435992 | CG18: =WrightZucman!G39*Data!$Q18 -> 0.010391825 | CH18: =CB18-CC18-CD18-CE18-CF18-CG18 -> 0 | CJ18: =CK18+CL18 -> 187.6 | CK18: 155.9 | CL18: 31.7 | CM18: =BC18*Y18/(1-Y18) -> 43.924044 | CN18: =(CJ18+CM18)/AD18 -> 0.33690069 | CO18: ='[1]Assets(BoP)'!$BN87 -> 0.36090362 | CQ18: =(O18+P18)/AD18 -> 0.55464975 | CR18: =P18/AI18 -> 0.84023261 | CS18: =O18/AL18 -> 0.4419536 | CT18: =O18/(AL18-0.5*AP18) -> 0.48372058 | CU18: =(O18+P18)/AD18 -> 0.55464975 | CV18: =(E18/1000000000)/AD18 -> 3.7224114e-07 | CW18: =(F18/1000)/(BC18/(1-Y18)) -> 0.7196276 | CX18: =((E18-F18)/1000000000)/O18 -> 6.0921364e-07 | CY18: =(F18/1000000000)/P18 -> 8.1464278e-07 | CZ18: =P18/(BC18/(1-Y18)) -> 0.88336584 | DA18: =(P18-V18)/BC18 -> 0.88336584 | DB18: =(F18/1000)/P18 -> 0.81464278
A19: 1996 | B19: 315709.02 | C19: 105506.97 | D19: 0.33419057 | E19: 299652.96 | F19: 104925.67 | G19: 0.3501573 | H19: 300642.76 | I19: 104971.66 | J19: 0.34915746 | K19: =C19/B19-D19 -> 0 | L19: =I19/H19-J19 -> 0 | M19: =F19/E19-G19 -> 0 | O19: 327.324 | P19: =WrightZucman!O40 -> 130.287 | Q19: =P19/(P19+O19) -> 0.28471125 | R19: =BC19/(1-Y19) -> 142.16969 | T19: =R19/(R19+O19) -> 0.30281491 | U19: =T19 -> 0.30281491 | V19: 45.192 | Y19: =V19/P19 -> 0.346865 | AA19: =V19/(P19/(1-BE19)) -> 0.32107678 | AD19: =BB19-0.5*AP19+AI19 -> 766.52519 | AE19: =0.5*AP19 -> 62.996499 | AF19: =AD19-AE19 -> 703.52869 | AG19: =AD19 -> 766.52519 | AH19: =AG19-AI19 -> 616.8975 | AI19: =BC19/(1-Y19)+BD19 -> 149.62769 | AK19: =AL19+AM19 -> 829.52169 | AL19: =BB19 -> 679.894 | AM19: =AI19 -> 149.62769 | AN19: =AK19 -> 829.52169 | AO19: =AN19-AP19 -> 703.52869 | AP19: 125.993 | AQ19: =AF19-AO19 -> 0 | AR19: =Data!AM19/Data!AK19 -> 0.18037827 | AS19: =Data!AI19/Data!AG19 -> 0.19520257 | AV19: ='[1]Assets(BoP)'!$D88 -> 789.5 | AW19: 22.7 | AX19: ='[1]Assets(BoP)'!$CI88 -> 0 | AY19: =BK19 -> 13.408 | AZ19: =AV19-AW19-AX19+AY19 -> 780.208 | BA19: 100.314 | BB19: =AZ19-BA19 -> 679.894 | BC19: =BA19-BD19 -> 92.856 | BD19: 7.458 | BE19: =BD19/BA19 -> 0.074346552 | BF19: 102.505 | BG19: =BC19/(1-Y19) -> 142.16969 | BI19: ='[1]Assets(BoP)'!$Q88 -> 37.4 | BK19: =BI19-BL19 -> 13.408 | BL19: 23.992 | BM19: 0 | BP19: 1996 | BQ19: =Data!AR19*WrightZucman!B40 -> 0.035587768 | BR19: =$BQ19*WrightZucman!C40/WrightZucman!$B40 -> 0.0078513219 | BS19: =WrightZucman!C40*Data!AS19-BR19 -> 0.00064525706 | BT19: =$BQ19*WrightZucman!D40/WrightZucman!$B40 -> 0.0086930789 | BU19: =$BQ19*WrightZucman!E40/WrightZucman!$B40 -> 0.0040924894 | BV19: =$BQ19*WrightZucman!F40/WrightZucman!$B40 -> 0.0067866655 | BW19: =$BQ19*WrightZucman!G40/WrightZucman!$B40 -> 0.0081642119 | BX19: =BQ19-BR19-BT19-BU19-BV19-BW19 -> 0 | BZ19: =Data!AR19*WrightZucman!B40 -> 0.035587768 | CA19: =Data!D19*WrightZucman!B40 -> 0.065934195 | CB19: =Data!Q19*WrightZucman!B40 -> 0.056172164 | CC19: =WrightZucman!C40*Data!$Q19 -> 0.012392622 | CD19: =WrightZucman!D40*Data!$Q19 -> 0.013721261 | CE19: =WrightZucman!E40*Data!$Q19 -> 0.0064596349 | CF19: =WrightZucman!F40*Data!$Q19 -> 0.010712155 | CG19: =WrightZucman!G40*Data!$Q19 -> 0.012886491 | CH19: =CB19-CC19-CD19-CE19-CF19-CG19 -> 0 | CJ19: =CK19+CL19 -> 203.5 | CK19: 170.5 | CL19: 33 | CM19: =BC19*Y19/(1-Y19) -> 49.313689 | CN19: =(CJ19+CM19)/AD19 -> 0.32981785 | CO19: ='[1]Assets(BoP)'!$BN88 -> 0.36179959 | CQ19: =(O19+P19)/AD19 -> 0.59699408 | CR19: =P19/AI19 -> 0.87074124 | CS19: =O19/AL19 -> 0.48143387 | CT19: =O19/(AL19-0.5*AP19) -> 0.53059706 | CU19: =(O19+P19)/AD19 -> 0.59699408 | CV19: =(E19/1000000000)/AD19 -> 3.9092383e-07 | CW19: =(F19/1000)/(BC19/(1-Y19)) -> 0.73803124 | CX19: =((E19-F19)/1000000000)/O19 -> 5.9490685e-07 | CY19: =(F19/1000000000)/P19 -> 8.0534261e-07 | CZ19: =P19/(BC19/(1-Y19)) -> 0.91641897 | DA19: =(P19-V19)/BC19 -> 0.91641897 | DB19: =(F19/1000)/P19 -> 0.80534261
A20: 1997 | B20: 331969.38 | C20: 109998.45 | D20: 0.33135118 | E20: 313159.9 | F20: 108794.38 | G20: 0.34740839 | H20: 315072.49 | I20: 108904.21 | J20: 0.34564811 | K20: =C20/B20-D20 -> 0 | L20: =I20/H20-J20 -> 0 | M20: =F20/E20-G20 -> 0 | O20: 338.315 | P20: =WrightZucman!O41 -> 144.277 | Q20: =P20/(P20+O20) -> 0.29896268 | R20: =BC20/(1-Y20) -> 155.43308 | T20: =R20/(R20+O20) -> 0.31480239 | U20: =T20 -> 0.31480239 | V20: 47.58 | Y20: =V20/P20 -> 0.32978229 | AA20: =V20/(P20/(1-BE20)) -> 0.30346566 | AD20: =BB20-0.5*AP20+AI20 -> 835.16929 | AE20: =0.5*AP20 -> 75.619788 | AF20: =AD20-AE20 -> 759.5495 | AG20: =AD20 -> 835.16929 | AH20: =AG20-AI20 -> 670.70221 | AI20: =BC20/(1-Y20)+BD20 -> 164.46708 | AK20: =AL20+AM20 -> 910.78908 | AL20: =BB20 -> 746.322 | AM20: =AI20 -> 164.46708 | AN20: =AK20 -> 910.78908 | AO20: =AN20-AP20 -> 759.5495 | AP20: 151.23958 | AQ20: =AF20-AO20 -> 0 | AR20: =Data!AM20/Data!AK20 -> 0.18057647 | AS20: =Data!AI20/Data!AG20 -> 0.19692663 | AV20: ='[1]Assets(BoP)'!$D89 -> 869.7 | AW20: 24.4 | AX20: ='[1]Assets(BoP)'!$CI89 -> 0 | AY20: =BK20 -> 14.23 | AZ20: =AV20-AW20-AX20+AY20 -> 859.53 | BA20: 113.208 | BB20: =AZ20-BA20 -> 746.322 | BC20: =BA20-BD20 -> 104.174 | BD20: 9.034 | BE20: =BD20/BA20 -> 0.079800014 | BF20: 115.323 | BG20: =BC20/(1-Y20) -> 155.43308 | BI20: ='[1]Assets(BoP)'!$Q89 -> 48 | BK20: =BI20-BL20 -> 14.23 | BL20: 33.77 | BM20: 0 | BP20: 1997 | BQ20: =Data!AR20*WrightZucman!B41 -> 0.040587996 | BR20: =$BQ20*WrightZucman!C41/WrightZucman!$B41 -> 0.010166712 | BS20: =WrightZucman!C41*Data!AS20-BR20 -> 0.00092053742 | BT20: =$BQ20*WrightZucman!D41/WrightZucman!$B41 -> 0.0098412968 | BU20: =$BQ20*WrightZucman!E41/WrightZucman!$B41 -> 0.0041953487 | BV20: =$BQ20*WrightZucman!F41/WrightZucman!$B41 -> 0.010030288 | BW20: =$BQ20*WrightZucman!G41/WrightZucman!$B41 -> 0.0063543513 | BX20: =BQ20-BR20-BT20-BU20-BV20-BW20 -> 0 | BZ20: =Data!AR20*WrightZucman!B41 -> 0.040587996 | CA20: =Data!D20*WrightZucman!B41 -> 0.074477481 | CB20: =Data!Q20*WrightZucman!B41 -> 0.06719755 | CC20: =WrightZucman!C41*Data!$Q20 -> 0.016832024 | CD20: =WrightZucman!D41*Data!$Q20 -> 0.016293266 | CE20: =WrightZucman!E41*Data!$Q20 -> 0.0069458259 | CF20: =WrightZucman!F41*Data!$Q20 -> 0.01660616 | CG20: =WrightZucman!G41*Data!$Q20 -> 0.010520274 | CH20: =CB20-CC20-CD20-CE20-CF20-CG20 -> 0 | CJ20: =CK20+CL20 -> 216.4 | CK20: 182.3 | CL20: 34.1 | CM20: =BC20*Y20/(1-Y20) -> 51.259076 | CN20: =(CJ20+CM20)/AD20 -> 0.32048482 | CO20: ='[1]Assets(BoP)'!$BN89 -> 0.35102871 | CQ20: =(O20+P20)/AD20 -> 0.57783734 | CR20: =P20/AI20 -> 0.8772394 | CS20: =O20/AL20 -> 0.4533097 | CT20: =O20/(AL20-0.5*AP20) -> 0.50441909 | CU20: =(O20+P20)/AD20 -> 0.57783734 | CV20: =(E20/1000000000)/AD20 -> 3.7496578e-07 | CW20: =(F20/1000)/(BC20/(1-Y20)) -> 0.69994353 | CX20: =((E20-F20)/1000000000)/O20 -> 6.0406876e-07 | CY20: =(F20/1000000000)/P20 -> 7.5406598e-07 | CZ20: =P20/(BC20/(1-Y20)) -> 0.92822585 | DA20: =(P20-V20)/BC20 -> 0.92822585 | DB20: =(F20/1000)/P20 -> 0.75406598
A21: 1998 | B21: 311195.33 | C21: 90601.352 | D21: 0.29113982 | E21: 277527.31 | F21: 89122.299 | G21: 0.32112983 | H21: 281837.76 | I21: 88377.677 | J21: 0.31357642 | K21: =C21/B21-D21 -> 0 | L21: =I21/H21-J21 -> 0 | M21: =F21/E21-G21 -> 0 | O21: =[2]A!$D$16/1000 -> 353.618 | P21: =WrightZucman!O42 -> 124.176 | Q21: =P21/(P21+O21) -> 0.25989443 | R21: =BC21/(1-Y21) -> 132.52715 | T21: =R21/(R21+O21) -> 0.27260819 | U21: =T21 -> 0.27260819 | V21: 40.536 | Y21: =V21/P21 -> 0.32643989 | AA21: =V21/(P21/(1-BE21)) -> 0.28878308 | AD21: =BB21-0.5*AP21+AI21 -> 757.43911 | AE21: =0.5*AP21 -> 84.468035 | AF21: =AD21-AE21 -> 672.97108 | AG21: =AD21 -> 757.43911 | AH21: =AG21-AI21 -> 613.27197 | AI21: =BC21/(1-Y21)+BD21 -> 144.16715 | AK21: =AL21+AM21 -> 841.90715 | AL21: =BB21 -> 697.74 | AM21: =AI21 -> 144.16715 | AN21: =AK21 -> 841.90715 | AO21: =AN21-AP21 -> 672.97108 | AP21: 168.93607 | AQ21: =AF21-AO21 -> 0 | AR21: =Data!AM21/Data!AK21 -> 0.17123877 | AS21: =Data!AI21/Data!AG21 -> 0.19033497 | AV21: ='[1]Assets(BoP)'!$D90 -> 808.5 | AW21: 25.8 | AX21: ='[1]Assets(BoP)'!$CI90 -> 0 | AY21: =BK21 -> 15.945 | AZ21: =AV21-AW21-AX21+AY21 -> 798.645 | BA21: 100.905 | BB21: =AZ21-BA21 -> 697.74 | BC21: =BA21-BD21 -> 89.265 | BD21: 11.64 | BE21: =BD21/BA21 -> 0.11535603 | BF21: 103.963 | BG21: =BC21/(1-Y21) -> 132.52715 | BI21: ='[1]Assets(BoP)'!$Q90 -> 44 | BK21: =BI21-BL21 -> 15.945 | BL21: 28.055 | BM21: 0 | BP21: 1998 | BQ21: =Data!AR21*WrightZucman!B42 -> 0.045100213 | BR21: =$BQ21*WrightZucman!C42/WrightZucman!$B42 -> 0.014911133 | BS21: =WrightZucman!C42*Data!AS21-BR21 -> 0.0016628586 | BT21: =$BQ21*WrightZucman!D42/WrightZucman!$B42 -> 0.010211499 | BU21: =$BQ21*WrightZucman!E42/WrightZucman!$B42 -> 0.0047410039 | BV21: =$BQ21*WrightZucman!F42/WrightZucman!$B42 -> 0.01098236 | BW21: =$BQ21*WrightZucman!G42/WrightZucman!$B42 -> 0.0042542167 | BX21: =BQ21-BR21-BT21-BU21-BV21-BW21 -> 0 | BZ21: =Data!AR21*WrightZucman!B42 -> 0.045100213 | CA21: =Data!D21*WrightZucman!B42 -> 0.076679292 | CB21: =Data!Q21*WrightZucman!B42 -> 0.068450001 | CC21: =WrightZucman!C42*Data!$Q21 -> 0.022631092 | CD21: =WrightZucman!D42*Data!$Q21 -> 0.015498311 | CE21: =WrightZucman!E42*Data!$Q21 -> 0.0071955696 | CF21: =WrightZucman!F42*Data!$Q21 -> 0.016668271 | CG21: =WrightZucman!G42*Data!$Q21 -> 0.0064567575 | CH21: =CB21-CC21-CD21-CE21-CF21-CG21 -> 1.2143064e-17 | CJ21: =CK21+CL21 -> 212.6 | CK21: 177.7 | CL21: 34.9 | CM21: =BC21*Y21/(1-Y21) -> 43.262148 | CN21: =(CJ21+CM21)/AD21 -> 0.33779896 | CO21: ='[1]Assets(BoP)'!$BN90 -> 0.3872544 | CQ21: =(O21+P21)/AD21 -> 0.63080186 | CR21: =P21/AI21 -> 0.86133354 | CS21: =O21/AL21 -> 0.50680483 | CT21: =O21/(AL21-0.5*AP21) -> 0.57660878 | CU21: =(O21+P21)/AD21 -> 0.63080186 | CV21: =(E21/1000000000)/AD21 -> 3.6640214e-07 | CW21: =(F21/1000)/(BC21/(1-Y21)) -> 0.67248334 | CX21: =((E21-F21)/1000000000)/O21 -> 5.3279249e-07 | CY21: =(F21/1000000000)/P21 -> 7.1770953e-07 | CZ21: =P21/(BC21/(1-Y21)) -> 0.93698538 | DA21: =(P21-V21)/BC21 -> 0.93698538 | DB21: =(F21/1000)/P21 -> 0.71770953
A22: 1999 | B22: 384134.6 | C22: 122131.04 | D22: 0.31793815 | E22: 362942.29 | F22: 119345.04 | G22: 0.32882651 | H22: 363307.26 | I22: 119346.73 | J22: 0.32850081 | K22: =C22/B22-D22 -> 0 | L22: =I22/H22-J22 -> 0 | M22: =F22/E22-G22 -> 0 | O22: =[3]TablePage!$D$6/1000 -> 408.638 | P22: =WrightZucman!O43 -> 141.956 | Q22: =P22/(P22+O22) -> 0.25782337 | R22: =BC22/(1-Y22) -> 162.98684 | T22: =R22/(R22+O22) -> 0.28512904 | U22: =T22 -> 0.28512904 | V22: 45.068 | W22: =166.191 -> 166.191 | X22: =W22/O22 -> 0.40669492 | Y22: =V22/P22 -> 0.31747866 | Z22: =(V22+W22)/(O22+P22) -> 0.38369288 | AA22: =V22/(P22/(1-BE22)) -> 0.28031559 | AB22: =(V22+W22)/(P22/(1-BE22)+O22) -> 0.37101129 | AD22: =BB22-0.5*AP22+AI22 -> 753.6868 | AE22: =0.5*AP22 -> 93.093049 | AF22: =AD22-AE22 -> 660.59375 | AG22: =AD22 -> 753.6868 | AH22: =AG22-AI22 -> 575.95195 | AI22: =BC22/(1-Y22)+BD22 -> 177.73484 | AK22: =AL22+AM22 -> 846.77984 | AL22: =BB22 -> 669.045 | AM22: =AI22 -> 177.73484 | AN22: =AK22 -> 846.77984 | AO22: =AN22-AP22 -> 660.59375 | AP22: 186.1861 | AQ22: =AF22-AO22 -> 0 | AR22: =Data!AM22/Data!AK22 -> 0.20989499 | AS22: =Data!AI22/Data!AG22 -> 0.23582056 | AV22: ='[1]Assets(BoP)'!$D91 -> 834.9 | AW22: 26.8 | AX22: ='[1]Assets(BoP)'!$CI91 -> 30.123 | AY22: =BK22 -> 17.058 | AZ22: =AV22-AW22-AX22+AY22 -> 795.035 | BA22: 125.99 | BB22: =AZ22-BA22 -> 669.045 | BC22: =BA22-BD22 -> 111.242 | BD22: 14.748 | BE22: =BD22/BA22 -> 0.11705691 | BF22: 130.512 | BG22: =BC22/(1-Y22) -> 162.98684 | BI22: ='[1]Assets(BoP)'!$Q91 -> 55 | BK22: 17.058 | BL22: 37.695 | BM22: =BI22-BK22-BL22 -> 0.247 | BP22: 1999 | BQ22: =Data!AR22*WrightZucman!B43 -> 0.050516091 | BR22: =$BQ22*WrightZucman!C43/WrightZucman!$B43 -> 0.016668166 | BS22: =WrightZucman!C43*Data!AS22-BR22 -> 0.0020588 | BT22: =$BQ22*WrightZucman!D43/WrightZucman!$B43 -> 0.0095339603 | BU22: =$BQ22*WrightZucman!E43/WrightZucman!$B43 -> 0.0052549155 | BV22: =$BQ22*WrightZucman!F43/WrightZucman!$B43 -> 0.011833171 | BW22: =$BQ22*WrightZucman!G43/WrightZucman!$B43 -> 0.0072258784 | BX22: =BQ22-BR22-BT22-BU22-BV22-BW22 -> 0 | BZ22: =Data!AR22*WrightZucman!B43 -> 0.050516091 | CA22: =Data!D22*WrightZucman!B43 -> 0.076519181 | CB22: =Data!Q22*WrightZucman!B43 -> 0.062051167 | CC22: =WrightZucman!C43*Data!$Q22 -> 0.020474251 | CD22: =WrightZucman!D43*Data!$Q22 -> 0.011710988 | CE22: =WrightZucman!E43*Data!$Q22 -> 0.0064548469 | CF22: =WrightZucman!F43*Data!$Q22 -> 0.014535211 | CG22: =WrightZucman!G43*Data!$Q22 -> 0.0088758686 | CH22: =CB22-CC22-CD22-CE22-CF22-CG22 -> 0 | CJ22: =CK22+CL22 -> 223.4 | CK22: 187.6 | CL22: 35.8 | CM22: =BC22*Y22/(1-Y22) -> 51.744844 | CN22: =(CJ22+CM22)/AD22 -> 0.36506523 | CO22: ='[1]Assets(BoP)'!$BN91 -> 0.39528368 | CQ22: =(O22+P22)/AD22 -> 0.73053423 | CR22: =P22/AI22 -> 0.79869539 | CS22: =O22/AL22 -> 0.61077805 | CT22: =O22/(AL22-0.5*AP22) -> 0.70950016 | CU22: =(O22+P22)/AD22 -> 0.73053423 | CV22: =(E22/1000000000)/AD22 -> 4.8155585e-07 | CW22: =(F22/1000)/(BC22/(1-Y22)) -> 0.73223729 | CX22: =((E22-F22)/1000000000)/O22 -> 5.961199e-07 | CY22: =(F22/1000000000)/P22 -> 8.4071857e-07 | CZ22: =P22/(BC22/(1-Y22)) -> 0.870966 | DA22: =(P22-V22)/BC22 -> 0.870966 | DB22: =(F22/1000)/P22 -> 0.84071857
A23: 2000 | B23: 453512.43 | C23: 155955.76 | D23: 0.34388421 | E23: 405764.15 | F23: 149293.38 | G23: 0.36793142 | H23: 419018.46 | I23: 151511.89 | J23: 0.36158762 | K23: =C23/B23-D23 -> 0 | L23: =I23/H23-J23 -> 0 | M23: =F23/E23-G23 -> 0 | O23: =[4]TablePage!$D$6/1000 -> 445.616 | P23: =WrightZucman!O44 -> 172.155 | Q23: =P23/(P23+O23) -> 0.27867122 | R23: =BC23/(1-Y23) -> 199.01084 | T23: =R23/(R23+O23) -> 0.30872254 | U23: =T23 -> 0.30872254 | V23: 59.801 | Y23: =V23/P23 -> 0.3473672 | AA23: =V23/(P23/(1-BE23)) -> 0.3115042 | AD23: =BB23-0.5*AP23+AI23 -> 716.23689 | AE23: =0.5*AP23 -> 94.264944 | AF23: =AD23-AE23 -> 621.97195 | AG23: =AD23 -> 716.23689 | AH23: =AG23-AI23 -> 502.27306 | AI23: =BC23/(1-Y23)+BD23 -> 213.96384 | AK23: =AL23+AM23 -> 810.50184 | AL23: =BB23 -> 596.538 | AM23: =AI23 -> 213.96384 | AN23: =AK23 -> 810.50184 | AO23: =AN23-AP23 -> 621.97195 | AP23: 188.52989 | AQ23: =AF23-AO23 -> 0 | AR23: =Data!AM23/Data!AK23 -> 0.26398933 | AS23: =Data!AI23/Data!AG23 -> 0.29873334 | AV23: ='[1]Assets(BoP)'!$D92 -> 786.6 | AW23: 31.4 | AX23: ='[1]Assets(BoP)'!$CI92 -> 33.473 | AY23: =BK23 -> 19.645 | AZ23: =AV23-AW23-AX23+AY23 -> 741.372 | BA23: 144.834 | BB23: =AZ23-BA23 -> 596.538 | BC23: =BA23-BD23 -> 129.881 | BD23: 14.953 | BE23: =BD23/BA23 -> 0.10324233 | BF23: 149.839 | BG23: =BC23/(1-Y23) -> 199.01084 | BI23: ='[1]Assets(BoP)'!$Q92 -> 55.9 | BK23: 19.645 | BL23: 36.071 | BM23: =BI23-BK23-BL23 -> 0.184 | BP23: 2000 | BQ23: =Data!AR23*WrightZucman!B44 -> 0.063835566 | BR23: =$BQ23*WrightZucman!C44/WrightZucman!$B44 -> 0.019140396 | BS23: =WrightZucman!C44*Data!AS23-BR23 -> 0.0025190944 | BT23: =$BQ23*WrightZucman!D44/WrightZucman!$B44 -> 0.011582071 | BU23: =$BQ23*WrightZucman!E44/WrightZucman!$B44 -> 0.0057335314 | BV23: =$BQ23*WrightZucman!F44/WrightZucman!$B44 -> 0.01449254 | BW23: =$BQ23*WrightZucman!G44/WrightZucman!$B44 -> 0.012887028 | BX23: =BQ23-BR23-BT23-BU23-BV23-BW23 -> 0 | BZ23: =Data!AR23*WrightZucman!B44 -> 0.063835566 | CA23: =Data!D23*WrightZucman!B44 -> 0.083155039 | CB23: =Data!Q23*WrightZucman!B44 -> 0.067385811 | CC23: =WrightZucman!C44*Data!$Q23 -> 0.020204898 | CD23: =WrightZucman!D44*Data!$Q23 -> 0.012226213 | CE23: =WrightZucman!E44*Data!$Q23 -> 0.0060524045 | CF23: =WrightZucman!F44*Data!$Q23 -> 0.015298549 | CG23: =WrightZucman!G44*Data!$Q23 -> 0.013603746 | CH23: =CB23-CC23-CD23-CE23-CF23-CG23 -> 0 | CJ23: =CK23+CL23 -> 229.3 | CK23: 194.1 | CL23: 35.2 | CM23: =BC23*Y23/(1-Y23) -> 69.129837 | CN23: =(CJ23+CM23)/AD23 -> 0.41666359 | CO23: ='[1]Assets(BoP)'!$BN92 -> 0.45339093 | CQ23: =(O23+P23)/AD23 -> 0.86252329 | CR23: =P23/AI23 -> 0.80459858 | CS23: =O23/AL23 -> 0.74700354 | CT23: =O23/(AL23-0.5*AP23) -> 0.88719869 | CU23: =(O23+P23)/AD23 -> 0.86252329 | CV23: =(E23/1000000000)/AD23 -> 5.6652227e-07 | CW23: =(F23/1000)/(BC23/(1-Y23)) -> 0.75017713 | CX23: =((E23-F23)/1000000000)/O23 -> 5.7554211e-07 | CY23: =(F23/1000000000)/P23 -> 8.6720326e-07 | CZ23: =P23/(BC23/(1-Y23)) -> 0.8650534 | DA23: =(P23-V23)/BC23 -> 0.8650534 | DB23: =(F23/1000)/P23 -> 0.86720326
A24: 2001 | B24: 334652.67 | C24: 129048.24 | D24: 0.38561842 | E24: 145674.41 | F24: 122113.2 | G24: 0.83826119 | H24: 269551.54 | I24: 127027.42 | J24: 0.47125465 | K24: =C24/B24-D24 -> 0 | L24: =I24/H24-J24 -> 0 | M24: =F24/E24-G24 -> 0 | O24: =[5]TablePage!$D$6/1000 -> 271.918 | P24: =WrightZucman!O45 -> 141.198 | Q24: =P24/(P24+O24) -> 0.34178778 | R24: =BC24/(1-Y24) -> 173.31503 | T24: =R24/(R24+O24) -> 0.38926813 | U24: =T24 -> 0.38926813 | V24: 55.214 | Y24: =V24/P24 -> 0.39103953 | AA24: =V24/(P24/(1-BE24)) -> 0.33757377 | AD24: =BB24-0.5*AP24+AI24 -> 687.6375 | AE24: =0.5*AP24 -> 96.600531 | AF24: =AD24-AE24 -> 591.03697 | AG24: =AD24 -> 687.6375 | AH24: =AG24-AI24 -> 497.60647 | AI24: =BC24/(1-Y24)+BD24 -> 190.03103 | AK24: =AL24+AM24 -> 784.23803 | AL24: =BB24 -> 594.207 | AM24: =AI24 -> 190.03103 | AN24: =AK24 -> 784.23803 | AO24: =AN24-AP24 -> 591.03697 | AP24: 193.20106 | AQ24: =AF24-AO24 -> 0 | AR24: =Data!AM24/Data!AK24 -> 0.24231295 | AS24: =Data!AI24/Data!AG24 -> 0.2763535 | AV24: ='[1]Assets(BoP)'!$D93 -> 758.7 | AW24: 29.2 | AX24: ='[1]Assets(BoP)'!$CI93 -> 34.164 | AY24: =BK24 -> 21.129 | AZ24: =AV24-AW24-AX24+AY24 -> 716.465 | BA24: 122.258 | BB24: =AZ24-BA24 -> 594.207 | BC24: =BA24-BD24 -> 105.542 | BD24: 16.716 | BE24: =BD24/BA24 -> 0.13672725 | BF24: 127.523 | BG24: =BC24/(1-Y24) -> 173.31503 | BI24: ='[1]Assets(BoP)'!$Q93 -> 13.9 | BK24: 21.129 | BL24: -7.415 | BM24: =BI24-BK24-BL24 -> 0.186 | BP24: 2001 | BQ24: =Data!AR24*WrightZucman!B45 -> 0.0653911 | BR24: =$BQ24*WrightZucman!C45/WrightZucman!$B45 -> 0.021818771 | BS24: =WrightZucman!C45*Data!AS24-BR24 -> 0.0030651395 | BT24: =$BQ24*WrightZucman!D45/WrightZucman!$B45 -> 0.011801769 | BU24: =$BQ24*WrightZucman!E45/WrightZucman!$B45 -> 0.0059583744 | BV24: =$BQ24*WrightZucman!F45/WrightZucman!$B45 -> 0.016972443 | BW24: =$BQ24*WrightZucman!G45/WrightZucman!$B45 -> 0.0088397427 | BX24: =BQ24-BR24-BT24-BU24-BV24-BW24 -> 0 | BZ24: =Data!AR24*WrightZucman!B45 -> 0.0653911 | CA24: =Data!D24*WrightZucman!B45 -> 0.10406383 | CB24: =Data!Q24*WrightZucman!B45 -> 0.092235595 | CC24: =WrightZucman!C45*Data!$Q24 -> 0.03077586 | CD24: =WrightZucman!D45*Data!$Q24 -> 0.016646656 | CE24: =WrightZucman!E45*Data!$Q24 -> 0.0084044191 | CF24: =WrightZucman!F45*Data!$Q24 -> 0.023940007 | CG24: =WrightZucman!G45*Data!$Q24 -> 0.012468653 | CH24: =CB24-CC24-CD24-CE24-CF24-CG24 -> 1.5612511e-17 | CJ24: =CK24+CL24 -> 166.5 | CK24: 137.6 | CL24: 28.9 | CM24: =BC24*Y24/(1-Y24) -> 67.773027 | CN24: =(CJ24+CM24)/AD24 -> 0.34069263 | CO24: ='[1]Assets(BoP)'!$BN93 -> 0.39225125 | CQ24: =(O24+P24)/AD24 -> 0.60077585 | CR24: =P24/AI24 -> 0.74302603 | CS24: =O24/AL24 -> 0.45761494 | CT24: =O24/(AL24-0.5*AP24) -> 0.5464519 | CU24: =(O24+P24)/AD24 -> 0.60077585 | CV24: =(E24/1000000000)/AD24 -> 2.1184768e-07 | CW24: =(F24/1000)/(BC24/(1-Y24)) -> 0.70457365 | CX24: =((E24-F24)/1000000000)/O24 -> 8.6648199e-08 | CY24: =(F24/1000000000)/P24 -> 8.6483663e-07 | CZ24: =P24/(BC24/(1-Y24)) -> 0.81468989 | DA24: =(P24-V24)/BC24 -> 0.81468989 | DB24: =(F24/1000)/P24 -> 0.86483663
A25: 2002 | B25: 376579.77 | C25: 143134.45 | D25: 0.38009065 | E25: 225741.64 | F25: 134372.07 | G25: 0.59524716 | H25: 317607.64 | I25: 139896.32 | J25: 0.440469 | K25: =C25/B25-D25 -> 0 | L25: =I25/H25-J25 -> 0 | M25: =F25/E25-G25 -> 0 | O25: =[6]TablePage!$D$7/1000 -> 306.699 | P25: =WrightZucman!O46 -> 152.871 | Q25: =P25/(P25+O25) -> 0.33263921 | R25: =BC25/(1-Y25) -> 180.4629 | T25: =R25/(R25+O25) -> 0.37043722 | U25: =T25 -> 0.37043722 | V25: 50.916 | Y25: =V25/P25 -> 0.33306513 | AA25: =V25/(P25/(1-BE25)) -> 0.28777258 | AD25: =BB25-0.5*AP25+AI25 -> 831.31849 | AE25: =0.5*AP25 -> 101.9184 | AF25: =AD25-AE25 -> 729.40009 | AG25: =AD25 -> 831.31849 | AH25: =AG25-AI25 -> 631.9126 | AI25: =BC25/(1-Y25)+BD25 -> 199.4059 | AK25: =AL25+AM25 -> 933.2369 | AL25: =BB25 -> 733.831 | AM25: =AI25 -> 199.4059 | AN25: =AK25 -> 933.2369 | AO25: =AN25-AP25 -> 729.40009 | AP25: 203.83681 | AQ25: =AF25-AO25 -> 0 | AR25: =Data!AM25/Data!AK25 -> 0.21367126 | AS25: =Data!AI25/Data!AG25 -> 0.23986703 | AV25: ='[1]Assets(BoP)'!$D94 -> 911.7 | AW25: 23.9 | AX25: ='[1]Assets(BoP)'!$CI94 -> 38.229 | AY25: =BK25 -> 23.56 | AZ25: =AV25-AW25-AX25+AY25 -> 873.131 | BA25: 139.3 | BB25: =AZ25-BA25 -> 733.831 | BC25: =BA25-BD25 -> 120.357 | BD25: 18.943 | BE25: =BD25/BA25 -> 0.13598708 | BF25: 144.675 | BG25: =BC25/(1-Y25) -> 180.4629 | BI25: ='[1]Assets(BoP)'!$Q94 -> 48.2 | BK25: 23.56 | BL25: 24.363 | BM25: =BI25-BK25-BL25 -> 0.277 | BP25: 2002 | BQ25: =Data!AR25*WrightZucman!B46 -> 0.058476521 | BR25: =$BQ25*WrightZucman!C46/WrightZucman!$B46 -> 0.025295984 | BS25: =WrightZucman!C46*Data!AS25-BR25 -> 0.0031012498 | BT25: =$BQ25*WrightZucman!D46/WrightZucman!$B46 -> 0.0069774313 | BU25: =$BQ25*WrightZucman!E46/WrightZucman!$B46 -> 0.0060185936 | BV25: =$BQ25*WrightZucman!F46/WrightZucman!$B46 -> 0.013064513 | BW25: =$BQ25*WrightZucman!G46/WrightZucman!$B46 -> 0.007119999 | BX25: =BQ25-BR25-BT25-BU25-BV25-BW25 -> 0 | BZ25: =Data!AR25*WrightZucman!B46 -> 0.058476521 | CA25: =Data!D25*WrightZucman!B46 -> 0.10402138 | CB25: =Data!Q25*WrightZucman!B46 -> 0.091035098 | CC25: =WrightZucman!C46*Data!$Q25 -> 0.03938029 | CD25: =WrightZucman!D46*Data!$Q25 -> 0.010862328 | CE25: =WrightZucman!E46*Data!$Q25 -> 0.0093696281 | CF25: =WrightZucman!F46*Data!$Q25 -> 0.020338577 | CG25: =WrightZucman!G46*Data!$Q25 -> 0.011084274 | CH25: =CB25-CC25-CD25-CE25-CF25-CG25 -> 0 | CJ25: =CK25+CL25 -> 156.9 | CK25: 126 | CL25: 30.9 | CM25: =BC25*Y25/(1-Y25) -> 60.1059 | CN25: =(CJ25+CM25)/AD25 -> 0.26103822 | CO25: ='[1]Assets(BoP)'!$BN94 -> 0.28192502 | CQ25: =(O25+P25)/AD25 -> 0.55282061 | CR25: =P25/AI25 -> 0.76663228 | CS25: =O25/AL25 -> 0.41794228 | CT25: =O25/(AL25-0.5*AP25) -> 0.48535035 | CU25: =(O25+P25)/AD25 -> 0.55282061 | CV25: =(E25/1000000000)/AD25 -> 2.7154651e-07 | CW25: =(F25/1000)/(BC25/(1-Y25)) -> 0.74459663 | CX25: =((E25-F25)/1000000000)/O25 -> 2.9791283e-07 | CY25: =(F25/1000000000)/P25 -> 8.7898991e-07 | CZ25: =P25/(BC25/(1-Y25)) -> 0.84710486 | DA25: =(P25-V25)/BC25 -> 0.84710486 | DB25: =(F25/1000)/P25 -> 0.87898991
A26: 2003 | B26: 503235.49 | C26: 178213.06 | D26: 0.35413452 | E26: 452940.38 | F26: 178599.68 | G26: 0.39431167 | H26: 461885.84 | I26: 178748.64 | J26: 0.38699745 | K26: =C26/B26-D26 -> 0 | L26: =I26/H26-J26 -> 0 | M26: =F26/E26-G26 -> 0 | O26: =[7]TablePage!$D$7/1000 -> 409.948 | P26: =WrightZucman!O47 -> 207.075 | Q26: =P26/(P26+O26) -> 0.33560337 | R26: =BC26/(1-Y26) -> 224.00829 | T26: =R26/(R26+O26) -> 0.35334974 | U26: =T26 -> 0.35334974 | V26: 59.228 | Y26: =V26/P26 -> 0.28602197 | AA26: =V26/(P26/(1-BE26)) -> 0.25670009 | AD26: =BB26-0.5*AP26+AI26 -> 967.90377 | AE26: =0.5*AP26 -> 116.07352 | AF26: =AD26-AE26 -> 851.83025 | AG26: =AD26 -> 967.90377 | AH26: =AG26-AI26 -> 725.62648 | AI26: =BC26/(1-Y26)+BD26 -> 242.27729 | AK26: =AL26+AM26 -> 1083.9773 | AL26: =BB26 -> 841.7 | AM26: =AI26 -> 242.27729 | AN26: =AK26 -> 1083.9773 | AO26: =AN26-AP26 -> 851.83025 | AP26: 232.14704 | AQ26: =AF26-AO26 -> 0 | AR26: =Data!AM26/Data!AK26 -> 0.22350772 | AS26: =Data!AI26/Data!AG26 -> 0.25031134 | AV26: ='[1]Assets(BoP)'!$D95 -> 1056.3 | AW26: 20.5 | AX26: ='[1]Assets(BoP)'!$CI95 -> 41.554 | AY26: =BK26 -> 25.66 | AZ26: =AV26-AW26-AX26+AY26 -> 1019.906 | BA26: 178.206 | BB26: =AZ26-BA26 -> 841.7 | BC26: =BA26-BD26 -> 159.937 | BD26: 18.269 | BE26: =BD26/BA26 -> 0.10251619 | BF26: 184.137 | BG26: =BC26/(1-Y26) -> 224.00829 | BI26: ='[1]Assets(BoP)'!$Q95 -> 89.2 | BK26: 25.66 | BL26: 63.304 | BM26: =BI26-BK26-BL26 -> 0.236 | BP26: 2003 | BQ26: =Data!AR26*WrightZucman!B47 -> 0.057572869 | BR26: =$BQ26*WrightZucman!C47/WrightZucman!$B47 -> 0.025183543 | BS26: =WrightZucman!C47*Data!AS26-BR26 -> 0.0030200755 | BT26: =$BQ26*WrightZucman!D47/WrightZucman!$B47 -> 0.0066412798 | BU26: =$BQ26*WrightZucman!E47/WrightZucman!$B47 -> 0.0056590655 | BV26: =$BQ26*WrightZucman!F47/WrightZucman!$B47 -> 0.012924213 | BW26: =$BQ26*WrightZucman!G47/WrightZucman!$B47 -> 0.0071647676 | BX26: =BQ26-BR26-BT26-BU26-BV26-BW26 -> 0 | BZ26: =Data!AR26*WrightZucman!B47 -> 0.057572869 | CA26: =Data!D26*WrightZucman!B47 -> 0.091220742 | CB26: =Data!Q26*WrightZucman!B47 -> 0.086447345 | CC26: =WrightZucman!C47*Data!$Q26 -> 0.037813825 | CD26: =WrightZucman!D47*Data!$Q26 -> 0.0099720756 | CE26: =WrightZucman!E47*Data!$Q26 -> 0.0084972521 | CF26: =WrightZucman!F47*Data!$Q26 -> 0.019406084 | CG26: =WrightZucman!G47*Data!$Q26 -> 0.010758108 | CH26: =CB26-CC26-CD26-CE26-CF26-CG26 -> 0 | CJ26: =CK26+CL26 -> 209.8 | CK26: 175.8 | CL26: 34 | CM26: =BC26*Y26/(1-Y26) -> 64.071294 | CN26: =(CJ26+CM26)/AD26 -> 0.28295302 | CO26: ='[1]Assets(BoP)'!$BN95 -> 0.29849245 | CQ26: =(O26+P26)/AD26 -> 0.63748383 | CR26: =P26/AI26 -> 0.85470246 | CS26: =O26/AL26 -> 0.48704764 | CT26: =O26/(AL26-0.5*AP26) -> 0.56495733 | CU26: =(O26+P26)/AD26 -> 0.63748383 | CV26: =(E26/1000000000)/AD26 -> 4.6796013e-07 | CW26: =(F26/1000)/(BC26/(1-Y26)) -> 0.79729046 | CX26: =((E26-F26)/1000000000)/O26 -> 6.6920854e-07 | CY26: =(F26/1000000000)/P26 -> 8.6248788e-07 | CZ26: =P26/(BC26/(1-Y26)) -> 0.92440774 | DA26: =(P26-V26)/BC26 -> 0.92440774 | DB26: =(F26/1000)/P26 -> 0.86248788
A27: 2004 | B27: 649878.74 | C27: 279954.45 | D27: 0.43077951 | E27: 592341.57 | F27: 285282.34 | G27: 0.48161796 | H27: 621229.42 | I27: 285609.59 | J27: 0.45974898 | K27: =C27/B27-D27 -> 0 | L27: =I27/H27-J27 -> 0 | M27: =F27/E27-G27 -> 0 | O27: =[8]TablePage!$D$7/1000 -> 501.374 | P27: =WrightZucman!O48 -> 258.763 | Q27: =P27/(P27+O27) -> 0.34041627 | R27: =BC27/(1-Y27) -> 312.63115 | S27: =BF27+V27 -> 320.252 | T27: =R27/(R27+O27) -> 0.38406532 | U27: =T27 -> 0.38406532 | V27: 74.068 | W27: =[9]TablePage!$I$7/1000 -> 163.544 | X27: =W27/O27 -> 0.32619163 | Y27: =V27/P27 -> 0.28623876 | Z27: =(V27+W27)/(O27+P27) -> 0.31259102 | AA27: =V27/(P27/(1-BE27)) -> 0.2657654 | AB27: =(V27+W27)/(P27/(1-BE27)+O27) -> 0.30460307 | AD27: =BB27-0.5*AP27+AI27 -> 1194.4455 | AE27: =0.5*AP27 -> 146.79168 | AF27: =AD27-AE27 -> 1047.6538 | AG27: =AD27 -> 1194.4455 | AH27: =AG27-AI27 -> 864.62432 | AI27: =BC27/(1-Y27)+BD27 -> 329.82115 | AK27: =AL27+AM27 -> 1341.2372 | AL27: =BB27 -> 1011.416 | AM27: =AI27 -> 329.82115 | AN27: =AK27 -> 1341.2372 | AO27: =AN27-AP27 -> 1047.6538 | AP27: 293.58335 | AQ27: =AF27-AO27 -> 0 | AR27: =Data!AM27/Data!AK27 -> 0.24590815 | AS27: =Data!AI27/Data!AG27 -> 0.2761291 | AV27: ='[1]Assets(BoP)'!$D96 -> 1289.3 | AW27: 20.5 | AX27: ='[1]Assets(BoP)'!$CI96 -> 54.087 | AY27: =BK27 -> 37.037 | AZ27: =AV27-AW27-AX27+AY27 -> 1251.75 | BA27: 240.334 | BB27: =AZ27-BA27 -> 1011.416 | BC27: =BA27-BD27 -> 223.144 | BD27: 17.19 | BE27: =BD27/BA27 -> 0.07152546 | BF27: 246.184 | BG27: =BC27/(1-Y27) -> 312.63115 | BI27: ='[1]Assets(BoP)'!$Q96 -> 128.9 | BK27: 37.037 | BL27: 91.58 | BM27: =BI27-BK27-BL27 -> 0.283 | BP27: 2004 | BQ27: =Data!AR27*WrightZucman!B48 -> 0.067827327 | BR27: =$BQ27*WrightZucman!C48/WrightZucman!$B48 -> 0.028121927 | BS27: =WrightZucman!C48*Data!AS27-BR27 -> 0.0034560512 | BT27: =$BQ27*WrightZucman!D48/WrightZucman!$B48 -> 0.0079655985 | BU27: =$BQ27*WrightZucman!E48/WrightZucman!$B48 -> 0.0084141504 | BV27: =$BQ27*WrightZucman!F48/WrightZucman!$B48 -> 0.015179492 | BW27: =$BQ27*WrightZucman!G48/WrightZucman!$B48 -> 0.0081461596 | BX27: =BQ27-BR27-BT27-BU27-BV27-BW27 -> 0 | BZ27: =Data!AR27*WrightZucman!B48 -> 0.067827327 | CA27: =Data!D27*WrightZucman!B48 -> 0.11881925 | CB27: =Data!Q27*WrightZucman!B48 -> 0.093894916 | CC27: =WrightZucman!C48*Data!$Q27 -> 0.038929824 | CD27: =WrightZucman!D48*Data!$Q27 -> 0.01102696 | CE27: =WrightZucman!E48*Data!$Q27 -> 0.0116479 | CF27: =WrightZucman!F48*Data!$Q27 -> 0.021013317 | CG27: =WrightZucman!G48*Data!$Q27 -> 0.011276915 | CH27: =CB27-CC27-CD27-CE27-CF27-CG27 -> 0 | CJ27: =CK27+CL27 -> 273.9 | CK27: 232.2 | CL27: 41.7 | CM27: =BC27*Y27/(1-Y27) -> 89.487153 | CN27: =(CJ27+CM27)/AD27 -> 0.30423084 | CO27: ='[1]Assets(BoP)'!$BN96 -> 0.30762792 | CQ27: =(O27+P27)/AD27 -> 0.63639322 | CR27: =P27/AI27 -> 0.7845555 | CS27: =O27/AL27 -> 0.49571492 | CT27: =O27/(AL27-0.5*AP27) -> 0.57987497 | CU27: =(O27+P27)/AD27 -> 0.63639322 | CV27: =(E27/1000000000)/AD27 -> 4.9591345e-07 | CW27: =(F27/1000)/(BC27/(1-Y27)) -> 0.91252051 | CX27: =((E27-F27)/1000000000)/O27 -> 6.1243549e-07 | CY27: =(F27/1000000000)/P27 -> 1.1024851e-06 | CZ27: =P27/(BC27/(1-Y27)) -> 0.82769422 | DA27: =(P27-V27)/BC27 -> 0.82769422 | DB27: =(F27/1000)/P27 -> 1.1024851
A28: 2005 | B28: 794746.82 | C28: 336649.97 | D28: 0.42359398 | E28: 726859.38 | F28: 334440.6 | G28: 0.46011734 | H28: 765695.18 | I28: 335154.12 | J28: 0.4377122 | K28: =C28/B28-D28 -> 0 | L28: =I28/H28-J28 -> 0 | M28: =F28/E28-G28 -> 0 | O28: =[10]TablePage!$D$7/1000 -> 577.749 | P28: =WrightZucman!O49 -> 324.862 | Q28: =P28/(P28+O28) -> 0.35991363 | R28: =BC28/(1-Y28) -> 386.75115 | S28: =BF28+V28 -> 385.035 | T28: =R28/(R28+O28) -> 0.40098609 | U28: =T28 -> 0.40098609 | V28: 100.143 | W28: =[10]TablePage!$J$7/1000 -> 205.556 | X28: =W28/O28 -> 0.35578772 | Y28: =V28/P28 -> 0.3082632 | Z28: =(V28+W28)/(O28+P28) -> 0.338683 | AA28: =V28/(P28/(1-BE28)) -> 0.29552449 | AB28: =(V28+W28)/(P28/(1-BE28)+O28) -> 0.33350886 | AD28: =BB28-0.5*AP28+AI28 -> 1363.0911 | AE28: =0.5*AP28 -> 191.08406 | AF28: =AD28-AE28 -> 1172.007 | AG28: =AD28 -> 1363.0911 | AH28: =AG28-AI28 -> 964.80794 | AI28: =BC28/(1-Y28)+BD28 -> 398.28315 | AK28: =AL28+AM28 -> 1554.1751 | AL28: =BB28 -> 1155.892 | AM28: =AI28 -> 398.28315 | AN28: =AK28 -> 1554.1751 | AO28: =AN28-AP28 -> 1172.007 | AP28: 382.16812 | AQ28: =AF28-AO28 -> 0 | AR28: =Data!AM28/Data!AK28 -> 0.25626658 | AS28: =Data!AI28/Data!AG28 -> 0.29219115 | AV28: ='[1]Assets(BoP)'!$D97 -> 1488.6 | AW28: 27.1 | AX28: ='[1]Assets(BoP)'!$CI97 -> 64.628 | AY28: =BK28 -> 38.082 | AZ28: =AV28-AW28-AX28+AY28 -> 1434.954 | BA28: 279.062 | BB28: =AZ28-BA28 -> 1155.892 | BC28: =BA28-BD28 -> 267.53 | BD28: 11.532 | BE28: =BD28/BA28 -> 0.04132415 | BF28: 284.892 | BG28: =BC28/(1-Y28) -> 386.75115 | BI28: ='[1]Assets(BoP)'!$Q97 -> 148.7 | BK28: 38.082 | BL28: 110.146 | BM28: =BI28-BK28-BL28 -> 0.472 | BP28: 2005 | BQ28: =Data!AR28*WrightZucman!B49 -> 0.061106494 | BR28: =$BQ28*WrightZucman!C49/WrightZucman!$B49 -> 0.02425785 | BS28: =WrightZucman!C49*Data!AS28-BR28 -> 0.0034005713 | BT28: =$BQ28*WrightZucman!D49/WrightZucman!$B49 -> 0.0075689918 | BU28: =$BQ28*WrightZucman!E49/WrightZucman!$B49 -> 0.00874753 | BV28: =$BQ28*WrightZucman!F49/WrightZucman!$B49 -> 0.014422499 | BW28: =$BQ28*WrightZucman!G49/WrightZucman!$B49 -> 0.0061096239 | BX28: =BQ28-BR28-BT28-BU28-BV28-BW28 -> 0 | BZ28: =Data!AR28*WrightZucman!B49 -> 0.061106494 | CA28: =Data!D28*WrightZucman!B49 -> 0.10100554 | CB28: =Data!Q28*WrightZucman!B49 -> 0.085821024 | CC28: =WrightZucman!C49*Data!$Q28 -> 0.03406894 | CD28: =WrightZucman!D49*Data!$Q28 -> 0.010630272 | CE28: =WrightZucman!E49*Data!$Q28 -> 0.01228547 | CF28: =WrightZucman!F49*Data!$Q28 -> 0.02025568 | CG28: =WrightZucman!G49*Data!$Q28 -> 0.0085806621 | CH28: =CB28-CC28-CD28-CE28-CF28-CG28 -> 0 | CJ28: =CK28+CL28 -> 374.4 | CK28: 319.5 | CL28: 54.9 | CM28: =BC28*Y28/(1-Y28) -> 119.22115 | CN28: =(CJ28+CM28)/AD28 -> 0.36213365 | CO28: ='[1]Assets(BoP)'!$BN97 -> 0.37616378 | CQ28: =(O28+P28)/AD28 -> 0.66217952 | CR28: =P28/AI28 -> 0.8156559 | CS28: =O28/AL28 -> 0.49982957 | CT28: =O28/(AL28-0.5*AP28) -> 0.59882281 | CU28: =(O28+P28)/AD28 -> 0.66217952 | CV28: =(E28/1000000000)/AD28 -> 5.3324344e-07 | CW28: =(F28/1000)/(BC28/(1-Y28)) -> 0.86474367 | CX28: =((E28-F28)/1000000000)/O28 -> 6.7922018e-07 | CY28: =(F28/1000000000)/P28 -> 1.0294851e-06 | CZ28: =P28/(BC28/(1-Y28)) -> 0.83997683 | DA28: =(P28-V28)/BC28 -> 0.83997683 | DB28: =(F28/1000)/P28 -> 1.0294851
A29: 2006 | B29: 913001.31 | C29: 404474.57 | D29: 0.44301642 | E29: 861480.13 | F29: 406061.84 | G29: 0.4713537 | H29: 884945.29 | I29: 404411.68 | J29: 0.4569906 | K29: =C29/B29-D29 -> 0 | L29: =I29/H29-J29 -> 0 | M29: =F29/E29-G29 -> 0 | O29: =[11]TablePage!$D$7/1000 -> 671.005 | P29: =WrightZucman!O50 -> 365.201 | Q29: =P29/(P29+O29) -> 0.35244054 | R29: =BC29/(1-Y29) -> 433.75743 | S29: =BF29+V29 -> 426.583 | T29: =R29/(R29+O29) -> 0.39262507 | U29: =T29 -> 0.39262507 | V29: 114.027 | W29: =[11]TablePage!$J$7/1000 -> 230.876 | X29: =W29/O29 -> 0.34407493 | Y29: =V29/P29 -> 0.3122308 | Z29: =(V29+W29)/(O29+P29) -> 0.33285177 | AA29: =V29/(P29/(1-BE29)) -> 0.30363745 | AB29: =(V29+W29)/(P29/(1-BE29)+O29) -> 0.32956451 | AD29: =BB29-0.5*AP29+AI29 -> 1507.9641 | AE29: =0.5*AP29 -> 199.92133 | AF29: =AD29-AE29 -> 1308.0428 | AG29: =AD29 -> 1507.9641 | AH29: =AG29-AI29 -> 1065.7637 | AI29: =BC29/(1-Y29)+BD29 -> 442.20043 | AK29: =AL29+AM29 -> 1707.8854 | AL29: =BB29 -> 1265.685 | AM29: =AI29 -> 442.20043 | AN29: =AK29 -> 1707.8854 | AO29: =AN29-AP29 -> 1308.0428 | AP29: 399.84266 | AQ29: =AF29-AO29 -> 0 | AR29: =Data!AM29/Data!AK29 -> 0.25891692 | AS29: =Data!AI29/Data!AG29 -> 0.29324334 | AV29: ='[1]Assets(BoP)'!$D98 -> 1646.3 | AW29: 34.4 | AX29: ='[1]Assets(BoP)'!$CI98 -> 84.33 | AY29: =BK29 -> 44.883 | AZ29: =AV29-AW29-AX29+AY29 -> 1572.453 | BA29: 306.768 | BB29: =AZ29-BA29 -> 1265.685 | BC29: =BA29-BD29 -> 298.325 | BD29: 8.443 | BE29: =BD29/BA29 -> 0.027522427 | BF29: 312.556 | BG29: =BC29/(1-Y29) -> 433.75743 | BI29: ='[1]Assets(BoP)'!$Q98 -> 181.8 | BK29: 44.883 | BL29: 136.522 | BM29: =BI29-BK29-BL29 -> 0.395 | BP29: 2006 | BQ29: =Data!AR29*WrightZucman!B50 -> 0.066632639 | BR29: =$BQ29*WrightZucman!C50/WrightZucman!$B50 -> 0.026838097 | BS29: =WrightZucman!C50*Data!AS29-BR29 -> 0.0035581139 | BT29: =$BQ29*WrightZucman!D50/WrightZucman!$B50 -> 0.0044395764 | BU29: =$BQ29*WrightZucman!E50/WrightZucman!$B50 -> 0.00994899 | BV29: =$BQ29*WrightZucman!F50/WrightZucman!$B50 -> 0.017234376 | BW29: =$BQ29*WrightZucman!G50/WrightZucman!$B50 -> 0.0081715997 | BX29: =BQ29-BR29-BT29-BU29-BV29-BW29 -> 0 | BZ29: =Data!AR29*WrightZucman!B50 -> 0.066632639 | CA29: =Data!D29*WrightZucman!B50 -> 0.11401091 | CB29: =Data!Q29*WrightZucman!B50 -> 0.090701077 | CC29: =WrightZucman!C50*Data!$Q29 -> 0.036532311 | CD29: =WrightZucman!D50*Data!$Q29 -> 0.0060431999 | CE29: =WrightZucman!E50*Data!$Q29 -> 0.013542674 | CF29: =WrightZucman!F50*Data!$Q29 -> 0.023459621 | CG29: =WrightZucman!G50*Data!$Q29 -> 0.011123271 | CH29: =CB29-CC29-CD29-CE29-CF29-CG29 -> 0 | CJ29: =CK29+CL29 -> 425.2 | CK29: 366 | CL29: 59.2 | CM29: =BC29*Y29/(1-Y29) -> 135.43243 | CN29: =(CJ29+CM29)/AD29 -> 0.37178102 | CO29: ='[1]Assets(BoP)'!$BN98 -> 0.37115443 | CQ29: =(O29+P29)/AD29 -> 0.68715562 | CR29: =P29/AI29 -> 0.82587211 | CS29: =O29/AL29 -> 0.53015166 | CT29: =O29/(AL29-0.5*AP29) -> 0.62960018 | CU29: =(O29+P29)/AD29 -> 0.68715562 | CV29: =(E29/1000000000)/AD29 -> 5.712869e-07 | CW29: =(F29/1000)/(BC29/(1-Y29)) -> 0.9361496 | CX29: =((E29-F29)/1000000000)/O29 -> 6.7871072e-07 | CY29: =(F29/1000000000)/P29 -> 1.1118859e-06 | CZ29: =P29/(BC29/(1-Y29)) -> 0.84194754 | DA29: =(P29-V29)/BC29 -> 0.84194754 | DB29: =(F29/1000)/P29 -> 1.1118859
A30: 2007 | B30: 920319.07 | C30: 464895.47 | D30: 0.50514596 | E30: 812182.5 | F30: 474243.76 | G30: 0.58391281 | H30: 880563.09 | I30: 466945.25 | J30: 0.53028028 | K30: =C30/B30-D30 -> 0 | L30: =I30/H30-J30 -> 0 | M30: =F30/E30-G30 -> 0 | O30: =[12]TablePage!$D$7/1000 -> 634.172 | P30: =WrightZucman!O51 -> 419.55 | Q30: =P30/(P30+O30) -> 0.39816005 | R30: =BC30/(1-Y30) -> 488.63339 | S30: =BF30+V30 -> 486.889 | T30: =R30/(R30+O30) -> 0.43518974 | U30: =T30 -> 0.43518974 | V30: 125.181 | W30: =[12]TablePage!$J$7/1000 -> 249.691 | X30: =W30/O30 -> 0.39372757 | Y30: =V30/P30 -> 0.29836968 | Z30: =(V30+W30)/(O30+P30) -> 0.35575987 | AA30: =V30/(P30/(1-BE30)) -> 0.28870981 | AB30: =(V30+W30)/(P30/(1-BE30)+O30) -> 0.35108276 | AD30: =BB30-0.5*AP30+AI30 -> 1386.9445 | AE30: =0.5*AP30 -> 194.32588 | AF30: =AD30-AE30 -> 1192.6186 | AG30: =AD30 -> 1386.9445 | AH30: =AG30-AI30 -> 886.84012 | AI30: =BC30/(1-Y30)+BD30 -> 500.10439 | AK30: =AL30+AM30 -> 1581.2704 | AL30: =BB30 -> 1081.166 | AM30: =AI30 -> 500.10439 | AN30: =AK30 -> 1581.2704 | AO30: =AN30-AP30 -> 1192.6186 | AP30: 388.65175 | AQ30: =AF30-AO30 -> 0 | AR30: =Data!AM30/Data!AK30 -> 0.31626747 | AS30: =Data!AI30/Data!AG30 -> 0.36057995 | AV30: ='[1]Assets(BoP)'!$D99 -> 1533.2 | AW30: 36.5 | AX30: ='[1]Assets(BoP)'!$CI99 -> 116.147 | AY30: =BK30 -> 54.924 | AZ30: =AV30-AW30-AX30+AY30 -> 1435.477 | BA30: 354.311 | BB30: =AZ30-BA30 -> 1081.166 | BC30: =BA30-BD30 -> 342.84 | BD30: 11.471 | BE30: =BD30/BA30 -> 0.032375512 | BF30: 361.708 | BG30: =BC30/(1-Y30) -> 488.63339 | BI30: ='[1]Assets(BoP)'!$Q99 -> 163.7 | BK30: 54.924 | BL30: 108.339 | BM30: =BI30-BK30-BL30 -> 0.437 | BP30: 2007 | BQ30: =Data!AR30*WrightZucman!B51 -> 0.082700684 | BR30: =$BQ30*WrightZucman!C51/WrightZucman!$B51 -> 0.035671021 | BS30: =WrightZucman!C51*Data!AS30-BR30 -> 0.0049978945 | BT30: =$BQ30*WrightZucman!D51/WrightZucman!$B51 -> 0.0056393683 | BU30: =$BQ30*WrightZucman!E51/WrightZucman!$B51 -> 0.011695602 | BV30: =$BQ30*WrightZucman!F51/WrightZucman!$B51 -> 0.02001482 | BW30: =$BQ30*WrightZucman!G51/WrightZucman!$B51 -> 0.0096798727 | BX30: =BQ30-BR30-BT30-BU30-BV30-BW30 -> -1.3877788e-17 | BZ30: =Data!AR30*WrightZucman!B51 -> 0.082700684 | CA30: =Data!D30*WrightZucman!B51 -> 0.13209046 | CB30: =Data!Q30*WrightZucman!B51 -> 0.10411475 | CC30: =WrightZucman!C51*Data!$Q30 -> 0.04490748 | CD30: =WrightZucman!D51*Data!$Q30 -> 0.0070995955 | CE30: =WrightZucman!E51*Data!$Q30 -> 0.014723997 | CF30: =WrightZucman!F51*Data!$Q30 -> 0.025197348 | CG30: =WrightZucman!G51*Data!$Q30 -> 0.012186326 | CH30: =CB30-CC30-CD30-CE30-CF30-CG30 -> 0 | CJ30: =CK30+CL30 -> 386.1 | CK30: 328.2 | CL30: 57.9 | CM30: =BC30*Y30/(1-Y30) -> 145.79339 | CN30: =(CJ30+CM30)/AD30 -> 0.38350012 | CO30: ='[1]Assets(BoP)'!$BN99 -> 0.39025502 | CQ30: =(O30+P30)/AD30 -> 0.75974344 | CR30: =P30/AI30 -> 0.83892485 | CS30: =O30/AL30 -> 0.58656303 | CT30: =O30/(AL30-0.5*AP30) -> 0.71509169 | CU30: =(O30+P30)/AD30 -> 0.75974344 | CV30: =(E30/1000000000)/AD30 -> 5.855912e-07 | CW30: =(F30/1000)/(BC30/(1-Y30)) -> 0.97055128 | CX30: =((E30-F30)/1000000000)/O30 -> 5.3288183e-07 | CY30: =(F30/1000000000)/P30 -> 1.1303629e-06 | CZ30: =P30/(BC30/(1-Y30)) -> 0.85861918 | DA30: =(P30-V30)/BC30 -> 0.85861918 | DB30: =(F30/1000)/P30 -> 1.1303629
A31: 2008 | B31: 803745.25 | C31: 432347.76 | D31: 0.53791641 | E31: 324515.93 | F31: 424531.19 | G31: 1.3081983 | H31: 694662.36 | I31: 423945.55 | J31: 0.61029008 | K31: =C31/B31-D31 -> 0 | L31: =I31/H31-J31 -> 0 | M31: =F31/E31-G31 -> 0 | O31: =[13]TablePage!$D$7/1000 -> 493.292 | P31: =WrightZucman!O52 -> 449.158 | Q31: =P31/(P31+O31) -> 0.4765855 | R31: =BC31/(1-Y31) -> 560.15687 | S31: =BF31+V31 -> 546.244 | T31: =R31/(R31+O31) -> 0.53173617 | U31: =T31 -> 0.53173617 | V31: 140.644 | W31: =[13]TablePage!$J$7/1000 -> 145.831 | X31: =W31/O31 -> 0.29562815 | Y31: =V31/P31 -> 0.31312812 | Z31: =(V31+W31)/(O31+P31) -> 0.30396838 | AA31: =V31/(P31/(1-BE31)) -> 0.30316462 | AB31: =(V31+W31)/(P31/(1-BE31)+O31) -> 0.29928075 | AD31: =BB31-0.5*AP31+AI31 -> 1177.3077 | AE31: =0.5*AP31 -> 174.71117 | AF31: =AD31-AE31 -> 1002.5965 | AG31: =AD31 -> 1177.3077 | AH31: =AG31-AI31 -> 604.50583 | AI31: =BC31/(1-Y31)+BD31 -> 572.80187 | AK31: =AL31+AM31 -> 1352.0189 | AL31: =BB31 -> 779.217 | AM31: =AI31 -> 572.80187 | AN31: =AK31 -> 1352.0189 | AO31: =AN31-AP31 -> 1002.5965 | AP31: 349.42234 | AQ31: =AF31-AO31 -> 0 | AR31: =Data!AM31/Data!AK31 -> 0.42366411 | AS31: =Data!AI31/Data!AG31 -> 0.4865354 | AV31: ='[1]Assets(BoP)'!$D100 -> 1285.8 | AW31: 35.4 | AX31: ='[1]Assets(BoP)'!$CI100 -> 143.918 | AY31: =BK31 -> 70.136 | AZ31: =AV31-AW31-AX31+AY31 -> 1176.618 | BA31: 397.401 | BB31: =AZ31-BA31 -> 779.217 | BC31: =BA31-BD31 -> 384.756 | BD31: 12.645 | BE31: =BD31/BA31 -> 0.031819246 | BF31: 405.6 | BG31: =BC31/(1-Y31) -> 560.15687 | BI31: ='[1]Assets(BoP)'!$Q100 -> 183.7 | BK31: 70.136 | BL31: 113.211 | BM31: =BI31-BK31-BL31 -> 0.353 | BP31: 2008 | BQ31: =Data!AR31*WrightZucman!B52 -> 0.099214773 | BR31: =$BQ31*WrightZucman!C52/WrightZucman!$B52 -> 0.036240251 | BS31: =WrightZucman!C52*Data!AS31-BR31 -> 0.0053780135 | BT31: =$BQ31*WrightZucman!D52/WrightZucman!$B52 -> 0.0032098481 | BU31: =$BQ31*WrightZucman!E52/WrightZucman!$B52 -> 0.017369778 | BV31: =$BQ31*WrightZucman!F52/WrightZucman!$B52 -> 0.029954495 | BW31: =$BQ31*WrightZucman!G52/WrightZucman!$B52 -> 0.012440402 | BX31: =BQ31-BR31-BT31-BU31-BV31-BW31 -> 0 | BZ31: =Data!AR31*WrightZucman!B52 -> 0.099214773 | CA31: =Data!D31*WrightZucman!B52 -> 0.12597068 | CB31: =Data!Q31*WrightZucman!B52 -> 0.11160804 | CC31: =WrightZucman!C52*Data!$Q31 -> 0.040767149 | CD31: =WrightZucman!D52*Data!$Q31 -> 0.0036108016 | CE31: =WrightZucman!E52*Data!$Q31 -> 0.019539498 | CF31: =WrightZucman!F52*Data!$Q31 -> 0.033696217 | CG31: =WrightZucman!G52*Data!$Q31 -> 0.013994376 | CH31: =CB31-CC31-CD31-CE31-CF31-CG31 -> 0 | CJ31: =CK31+CL31 -> 249.4 | CK31: 202 | CL31: 47.4 | CM31: =BC31*Y31/(1-Y31) -> 175.40087 | CN31: =(CJ31+CM31)/AD31 -> 0.360824 | CO31: ='[1]Assets(BoP)'!$BN100 -> 0.34682471 | CQ31: =(O31+P31)/AD31 -> 0.8005129 | CR31: =P31/AI31 -> 0.784142 | CS31: =O31/AL31 -> 0.63306114 | CT31: =O31/(AL31-0.5*AP31) -> 0.81602522 | CU31: =(O31+P31)/AD31 -> 0.8005129 | CV31: =(E31/1000000000)/AD31 -> 2.7564241e-07 | CW31: =(F31/1000)/(BC31/(1-Y31)) -> 0.75787911 | CX31: =((E31-F31)/1000000000)/O31 -> -2.0275063e-07 | CY31: =(F31/1000000000)/P31 -> 9.4517116e-07 | CZ31: =P31/(BC31/(1-Y31)) -> 0.80184325 | DA31: =(P31-V31)/BC31 -> 0.80184325 | DB31: =(F31/1000)/P31 -> 0.94517116
A32: 2009 | B32: 797455.58 | C32: 363778.66 | D32: 0.4561742 | E32: 663980.81 | F32: 374539.09 | G32: 0.56408119 | H32: 728824.32 | I32: 363955.87 | J32: 0.49937393 | K32: =C32/B32-D32 -> 0 | L32: =I32/H32-J32 -> 0 | M32: =F32/E32-G32 -> 0 | O32: ='[14]I.P 1'!$D$7/1000 -> 478.896 | P32: =WrightZucman!O53 -> 398.679 | Q32: =P32/(P32+O32) -> 0.45429621 | R32: =BC32/(1-Y32) -> 459.66584 | S32: =BF32+V32 -> 470.814 | T32: =R32/(R32+O32) -> 0.48975552 | U32: =T32 -> 0.48975552 | V32: 109.424 | W32: ='[14]I.N 1'!$I$8/1000 -> 135.995 | X32: =W32/O32 -> 0.28397606 | Y32: =V32/P32 -> 0.27446643 | Z32: =(V32+W32)/(O32+P32) -> 0.27965587 | AA32: =V32/(P32/(1-BE32)) -> 0.25795222 | AB32: =(V32+W32)/(P32/(1-BE32)+O32) -> 0.27175217 | AD32: =BB32-0.5*AP32+AI32 -> 1255.9881 | AE32: =0.5*AP32 -> 160.52769 | AF32: =AD32-AE32 -> 1095.4605 | AG32: =AD32 -> 1255.9881 | AH32: =AG32-AI32 -> 774.97131 | AI32: =BC32/(1-Y32)+BD32 -> 481.01684 | AK32: =AL32+AM32 -> 1416.5158 | AL32: =BB32 -> 935.499 | AM32: =AI32 -> 481.01684 | AN32: =AK32 -> 1416.5158 | AO32: =AN32-AP32 -> 1095.4605 | AP32: 321.05539 | AQ32: =AF32-AO32 -> 0 | AR32: =Data!AM32/Data!AK32 -> 0.33957745 | AS32: =Data!AI32/Data!AG32 -> 0.38297881 | AV32: ='[1]Assets(BoP)'!$D101 -> 1386.8 | AW32: 47.6 | AX32: ='[1]Assets(BoP)'!$CI101 -> 108.592 | AY32: =BK32 -> 59.745 | AZ32: =AV32-AW32-AX32+AY32 -> 1290.353 | BA32: 354.854 | BB32: =AZ32-BA32 -> 935.499 | BC32: =BA32-BD32 -> 333.503 | BD32: 21.351 | BE32: =BD32/BA32 -> 0.060168407 | BF32: 361.39 | BG32: =BC32/(1-Y32) -> 459.66584 | BI32: ='[1]Assets(BoP)'!$Q101 -> 148.2 | BK32: 59.745 | BL32: 88.218 | BM32: =BI32-BK32-BL32 -> 0.237 | BP32: 2009 | BQ32: =Data!AR32*WrightZucman!B53 -> 0.10273802 | BR32: =$BQ32*WrightZucman!C53/WrightZucman!$B53 -> 0.037628049 | BS32: =WrightZucman!C53*Data!AS32-BR32 -> 0.0048092365 | BT32: =$BQ32*WrightZucman!D53/WrightZucman!$B53 -> 0.012525932 | BU32: =$BQ32*WrightZucman!E53/WrightZucman!$B53 -> 0.019277806 | BV32: =$BQ32*WrightZucman!F53/WrightZucman!$B53 -> 0.021737679 | BW32: =$BQ32*WrightZucman!G53/WrightZucman!$B53 -> 0.011568558 | BX32: =BQ32-BR32-BT32-BU32-BV32-BW32 -> 0 | BZ32: =Data!AR32*WrightZucman!B53 -> 0.10273802 | CA32: =Data!D32*WrightZucman!B53 -> 0.13801398 | CB32: =Data!Q32*WrightZucman!B53 -> 0.1374458 | CC32: =WrightZucman!C53*Data!$Q32 -> 0.050339857 | CD32: =WrightZucman!D53*Data!$Q32 -> 0.016757542 | CE32: =WrightZucman!E53*Data!$Q32 -> 0.025790388 | CF32: =WrightZucman!F53*Data!$Q32 -> 0.029081275 | CG32: =WrightZucman!G53*Data!$Q32 -> 0.01547674 | CH32: =CB32-CC32-CD32-CE32-CF32-CG32 -> 0 | CJ32: =CK32+CL32 -> 197.5 | CK32: 153 | CL32: 44.5 | CM32: =BC32*Y32/(1-Y32) -> 126.16284 | CN32: =(CJ32+CM32)/AD32 -> 0.25769578 | CO32: ='[1]Assets(BoP)'!$BN101 -> 0.26033312 | CQ32: =(O32+P32)/AD32 -> 0.6987128 | CR32: =P32/AI32 -> 0.82882545 | CS32: =O32/AL32 -> 0.51191503 | CT32: =O32/(AL32-0.5*AP32) -> 0.6179532 | CU32: =(O32+P32)/AD32 -> 0.6987128 | CV32: =(E32/1000000000)/AD32 -> 5.2865213e-07 | CW32: =(F32/1000)/(BC32/(1-Y32)) -> 0.81480732 | CX32: =((E32-F32)/1000000000)/O32 -> 6.043937e-07 | CY32: =(F32/1000000000)/P32 -> 9.3945026e-07 | CZ32: =P32/(BC32/(1-Y32)) -> 0.86732353 | DA32: =(P32-V32)/BC32 -> 0.86732353 | DB32: =(F32/1000)/P32 -> 0.93945026
A33: 2010 | B33: 968348.82 | C33: 484185.63 | D33: 0.50001159 | E33: 926337.95 | F33: 481275.5 | G33: 0.51954635 | H33: 933681 | I33: 481537.11 | J33: 0.5157405 | K33: =C33/B33-D33 -> 0 | L33: =I33/H33-J33 -> 0 | M33: =F33/E33-G33 -> 0 | O33: ='[15]I.P 1'!$D$8/1000 -> 705.057 | P33: =WrightZucman!O54 -> 460.173 | Q33: =P33/(P33+O33) -> 0.39492032 | R33: =BC33/(1-Y33) -> 573.94621 | S33: =BF33+V33 -> 566.161 | T33: =R33/(R33+O33) -> 0.44874493 | U33: =T33 -> 0.44874493 | V33: 130 | W33: ='[15]I.P 1'!$J$8/1000 -> 202.855 | X33: =W33/O33 -> 0.28771433 | Y33: =V33/P33 -> 0.28250245 | Z33: =(V33+W33)/(O33+P33) -> 0.28565605 | AA33: =V33/(P33/(1-BE33)) -> 0.27032234 | AB33: =(V33+W33)/(P33/(1-BE33)+O33) -> 0.28066189 | AD33: =BB33-0.5*AP33+AI33 -> 1568.1771 | AE33: =0.5*AP33 -> 195.31407 | AF33: =AD33-AE33 -> 1372.8631 | AG33: =AD33 -> 1568.1771 | AH33: =AG33-AI33 -> 975.67593 | AI33: =BC33/(1-Y33)+BD33 -> 592.50121 | AK33: =AL33+AM33 -> 1763.4912 | AL33: =BB33 -> 1170.99 | AM33: =AI33 -> 592.50121 | AN33: =AK33 -> 1763.4912 | AO33: =AN33-AP33 -> 1372.8631 | AP33: 390.62814 | AQ33: =AF33-AO33 -> 0 | AR33: =Data!AM33/Data!AK33 -> 0.33598195 | AS33: =Data!AI33/Data!AG33 -> 0.37782799 | AV33: ='[1]Assets(BoP)'!$D102 -> 1728.7 | AW33: 72 | AX33: ='[1]Assets(BoP)'!$CI102 -> 115.377 | AY33: =BK33 -> 60.027 | AZ33: =AV33-AW33-AX33+AY33 -> 1601.35 | BA33: 430.36 | BB33: =AZ33-BA33 -> 1170.99 | BC33: =BA33-BD33 -> 411.805 | BD33: 18.555 | BE33: =BD33/BA33 -> 0.043115066 | BF33: 436.161 | BG33: =BC33/(1-Y33) -> 573.94621 | BI33: ='[1]Assets(BoP)'!$Q102 -> 194.1 | BK33: 60.027 | BL33: 133.917 | BM33: =BI33-BK33-BL33 -> 0.156 | BP33: 2010 | BQ33: =Data!AR33*WrightZucman!B54 -> 0.089138276 | BR33: =$BQ33*WrightZucman!C54/WrightZucman!$B54 -> 0.037521646 | BS33: =WrightZucman!C54*Data!AS33-BR33 -> 0.0046732637 | BT33: =$BQ33*WrightZucman!D54/WrightZucman!$B54 -> 0.0041076605 | BU33: =$BQ33*WrightZucman!E54/WrightZucman!$B54 -> 0.015783755 | BV33: =$BQ33*WrightZucman!F54/WrightZucman!$B54 -> 0.020215589 | BW33: =$BQ33*WrightZucman!G54/WrightZucman!$B54 -> 0.011509627 | BX33: =BQ33-BR33-BT33-BU33-BV33-BW33 -> 0 | BZ33: =Data!AR33*WrightZucman!B54 -> 0.089138276 | CA33: =Data!D33*WrightZucman!B54 -> 0.13265645 | CB33: =Data!Q33*WrightZucman!B54 -> 0.10477502 | CC33: =WrightZucman!C54*Data!$Q33 -> 0.044103739 | CD33: =WrightZucman!D54*Data!$Q33 -> 0.0048282313 | CE33: =WrightZucman!E54*Data!$Q33 -> 0.01855256 | CF33: =WrightZucman!F54*Data!$Q33 -> 0.023761832 | CG33: =WrightZucman!G54*Data!$Q33 -> 0.01352866 | CH33: =CB33-CC33-CD33-CE33-CF33-CG33 -> 0 | CJ33: =CK33+CL33 -> 265.5 | CK33: 219.4 | CL33: 46.1 | CM33: =BC33*Y33/(1-Y33) -> 162.14121 | CN33: =(CJ33+CM33)/AD33 -> 0.27269956 | CO33: ='[1]Assets(BoP)'!$BN102 -> 0.26848985 | CQ33: =(O33+P33)/AD33 -> 0.74304743 | CR33: =P33/AI33 -> 0.7766617 | CS33: =O33/AL33 -> 0.60210335 | CT33: =O33/(AL33-0.5*AP33) -> 0.72263441 | CU33: =(O33+P33)/AD33 -> 0.74304743 | CV33: =(E33/1000000000)/AD33 -> 5.9071002e-07 | CW33: =(F33/1000)/(BC33/(1-Y33)) -> 0.83853764 | CX33: =((E33-F33)/1000000000)/O33 -> 6.3124322e-07 | CY33: =(F33/1000000000)/P33 -> 1.0458578e-06 | CZ33: =P33/(BC33/(1-Y33)) -> 0.80177026 | DA33: =(P33-V33)/BC33 -> 0.80177026 | DB33: =(F33/1000)/P33 -> 1.0458578
A34: 2011 | B34: 1095760 | C34: 553897.91 | D34: 0.50549199 | E34: 1041126.7 | F34: 552980.5 | G34: 0.53113659 | H34: 1057248.1 | I34: 553534.95 | J34: 0.52356204 | K34: =C34/B34-D34 -> 0 | L34: =I34/H34-J34 -> 0 | M34: =F34/E34-G34 -> 0 | O34: ='[16]I.P 1'!$D$8/1000 -> 846.797 | P34: =WrightZucman!O55 -> 561.088 | Q34: =P34/(P34+O34) -> 0.39853255 | R34: =BC34/(1-Y34) -> 622.99541 | S34: =BF34+V34 -> 630.816 | T34: =R34/(R34+O34) -> 0.42386626 | U34: =T34 -> 0.42386626 | V34: 163.878 | W34: ='[16]I.P 1'!$J$8/1000 -> 217.634 | X34: =W34/O34 -> 0.25700847 | Y34: =V34/P34 -> 0.29207183 | Z34: =(V34+W34)/(O34+P34) -> 0.27098236 | AA34: =V34/(P34/(1-BE34)) -> 0.28018983 | AB34: =(V34+W34)/(P34/(1-BE34)+O34) -> 0.26647872 | AD34: =BB34-0.5*AP34+AI34 -> 1630.1646 | AE34: =0.5*AP34 -> 212.15481 | AF34: =AD34-AE34 -> 1418.0098 | AG34: =AD34 -> 1630.1646 | AH34: =AG34-AI34 -> 988.46619 | AI34: =BC34/(1-Y34)+BD34 -> 641.69841 | AK34: =AL34+AM34 -> 1842.3194 | AL34: =BB34 -> 1200.621 | AM34: =AI34 -> 641.69841 | AN34: =AK34 -> 1842.3194 | AO34: =AN34-AP34 -> 1418.0098 | AP34: 424.30962 | AQ34: =AF34-AO34 -> 0 | AR34: =Data!AM34/Data!AK34 -> 0.34831007 | AS34: =Data!AI34/Data!AG34 -> 0.39364026 | AV34: ='[1]Assets(BoP)'!$D103 -> 1809.8 | AW34: 76.5 | AX34: ='[1]Assets(BoP)'!$CI103 -> 147.474 | AY34: =BK34 -> 74.534 | AZ34: =AV34-AW34-AX34+AY34 -> 1660.36 | BA34: 459.739 | BB34: =AZ34-BA34 -> 1200.621 | BC34: =BA34-BD34 -> 441.036 | BD34: 18.703 | BE34: =BD34/BA34 -> 0.040681778 | BF34: 466.938 | BG34: =BC34/(1-Y34) -> 622.99541 | BI34: ='[1]Assets(BoP)'!$Q103 -> 228.5 | BK34: 74.534 | BL34: 153.825 | BM34: =BI34-BK34-BL34 -> 0.141 | BP34: 2011 | BQ34: =Data!AR34*WrightZucman!B55 -> 0.095993106 | BR34: =$BQ34*WrightZucman!C55/WrightZucman!$B55 -> 0.039017025 | BS34: =WrightZucman!C55*Data!AS34-BR34 -> 0.0050777998 | BT34: =$BQ34*WrightZucman!D55/WrightZucman!$B55 -> 0.010155278 | BU34: =$BQ34*WrightZucman!E55/WrightZucman!$B55 -> 0.016660392 | BV34: =$BQ34*WrightZucman!F55/WrightZucman!$B55 -> 0.015312066 | BW34: =$BQ34*WrightZucman!G55/WrightZucman!$B55 -> 0.014848346 | BX34: =BQ34-BR34-BT34-BU34-BV34-BW34 -> 0 | BZ34: =Data!AR34*WrightZucman!B55 -> 0.095993106 | CA34: =Data!D34*WrightZucman!B55 -> 0.13931192 | CB34: =Data!Q34*WrightZucman!B55 -> 0.10983425 | CC34: =WrightZucman!C55*Data!$Q34 -> 0.044642851 | CD34: =WrightZucman!D55*Data!$Q34 -> 0.011619557 | CE34: =WrightZucman!E55*Data!$Q34 -> 0.019062637 | CF34: =WrightZucman!F55*Data!$Q34 -> 0.017519897 | CG34: =WrightZucman!G55*Data!$Q34 -> 0.016989314 | CH34: =CB34-CC34-CD34-CE34-CF34-CG34 -> 0 | CJ34: =CK34+CL34 -> 272.4 | CK34: 224 | CL34: 48.4 | CM34: =BC34*Y34/(1-Y34) -> 181.95941 | CN34: =(CJ34+CM34)/AD34 -> 0.27871996 | CO34: ='[1]Assets(BoP)'!$BN103 -> 0.25935783 | CQ34: =(O34+P34)/AD34 -> 0.86364591 | CR34: =P34/AI34 -> 0.8743796 | CS34: =O34/AL34 -> 0.70529917 | CT34: =O34/(AL34-0.5*AP34) -> 0.85667776 | CU34: =(O34+P34)/AD34 -> 0.86364591 | CV34: =(E34/1000000000)/AD34 -> 6.3866357e-07 | CW34: =(F34/1000)/(BC34/(1-Y34)) -> 0.8876157 | CX34: =((E34-F34)/1000000000)/O34 -> 5.7646193e-07 | CY34: =(F34/1000000000)/P34 -> 9.855504e-07 | CZ34: =P34/(BC34/(1-Y34)) -> 0.90062943 | DA34: =(P34-V34)/BC34 -> 0.90062943 | DB34: =(F34/1000)/P34 -> 0.9855504
A35: 2012 | B35: 1081563.7 | C35: 557363.82 | D35: 0.51533149 | E35: 974688.9 | F35: 528835.74 | G35: 0.54256876 | H35: 1031441.3 | I35: 551330.99 | J35: 0.53452485 | K35: =C35/B35-D35 -> 0 | L35: =I35/H35-J35 -> 0 | M35: =F35/E35-G35 -> 0 | O35: ='[17]Table I.P 1'!$D$8/1000 -> 842.024 | P35: =WrightZucman!O56 -> 543.38 | Q35: =P35/(P35+O35) -> 0.39221772 | R35: =BC35/(1-Y35) -> 596.2128 | S35: =BF35+V35 -> 610.923 | T35: =R35/(R35+O35) -> 0.41454425 | U35: =T35 -> 0.41454425 | V35: 152.667 | W35: ='[17]Table I.P 1'!$J$8/1000 -> 223.832 | X35: =W35/O35 -> 0.26582615 | Y35: =V35/P35 -> 0.28095808 | Z35: =(V35+W35)/(O35+P35) -> 0.27176116 | AA35: =V35/(P35/(1-BE35)) -> 0.26833506 | AB35: =(V35+W35)/(P35/(1-BE35)+O35) -> 0.26683782 | AD35: =BB35-0.5*AP35+AI35 -> 1750.5918 | AE35: =0.5*AP35 -> 272.2 | AF35: =AD35-AE35 -> 1478.3918 | AG35: =AD35 -> 1750.5918 | AH35: =AG35-AI35 -> 1134.212 | AI35: =BC35/(1-Y35)+BD35 -> 616.3798 | AK35: =AL35+AM35 -> 2022.7918 | AL35: =BB35 -> 1406.412 | AM35: =AI35 -> 616.3798 | AN35: =AK35 -> 2022.7918 | AO35: =AN35-AP35 -> 1478.3918 | AP35: 544.4 | AQ35: =AF35-AO35 -> 0 | AR35: =Data!AM35/Data!AK35 -> 0.30471737 | AS35: =Data!AI35/Data!AG35 -> 0.35209796 | AV35: ='[1]Assets(BoP)'!$D104 -> 1997.4 | AW35: 72.2 | AX35: ='[1]Assets(BoP)'!$CI104 -> 166.705 | AY35: =BK35 -> 96.786 | AZ35: =AV35-AW35-AX35+AY35 -> 1855.281 | BA35: 448.869 | BB35: =AZ35-BA35 -> 1406.412 | BC35: =BA35-BD35 -> 428.702 | BD35: 20.167 | BE35: =BD35/BA35 -> 0.044928476 | BF35: 458.256 | BG35: =BC35/(1-Y35) -> 596.2128 | BI35: ='[1]Assets(BoP)'!$Q104 -> 243.5 | BK35: 96.786 | BL35: 146.521 | BM35: =BI35-BK35-BL35 -> 0.193 | BP35: 2012 | BQ35: =Data!AR35*WrightZucman!B56 -> 0.091842527 | BR35: =$BQ35*WrightZucman!C56/WrightZucman!$B56 -> 0.038995614 | BS35: =WrightZucman!C56*Data!AS35-BR35 -> 0.0060634387 | BT35: =$BQ35*WrightZucman!D56/WrightZucman!$B56 -> 0.01098122 | BU35: =$BQ35*WrightZucman!E56/WrightZucman!$B56 -> 0.01331351 | BV35: =$BQ35*WrightZucman!F56/WrightZucman!$B56 -> 0.015145583 | BW35: =$BQ35*WrightZucman!G56/WrightZucman!$B56 -> 0.0134066 | BX35: =BQ35-BR35-BT35-BU35-BV35-BW35 -> 0 | BZ35: =Data!AR35*WrightZucman!B56 -> 0.091842527 | CA35: =Data!D35*WrightZucman!B56 -> 0.15532211 | CB35: =Data!Q35*WrightZucman!B56 -> 0.11821534 | CC35: =WrightZucman!C56*Data!$Q35 -> 0.050193301 | CD35: =WrightZucman!D56*Data!$Q35 -> 0.014134505 | CE35: =WrightZucman!E56*Data!$Q35 -> 0.017136518 | CF35: =WrightZucman!F56*Data!$Q35 -> 0.019494674 | CG35: =WrightZucman!G56*Data!$Q35 -> 0.017256338 | CH35: =CB35-CC35-CD35-CE35-CF35-CG35 -> 0 | CJ35: =CK35+CL35 -> 325.4 | CK35: 274.7 | CL35: 50.7 | CM35: =BC35*Y35/(1-Y35) -> 167.5108 | CN35: =(CJ35+CM35)/AD35 -> 0.2815681 | CO35: ='[1]Assets(BoP)'!$BN104 -> 0.28357809 | CQ35: =(O35+P35)/AD35 -> 0.7913918 | CR35: =P35/AI35 -> 0.88156685 | CS35: =O35/AL35 -> 0.59870365 | CT35: =O35/(AL35-0.5*AP35) -> 0.74238678 | CU35: =(O35+P35)/AD35 -> 0.7913918 | CV35: =(E35/1000000000)/AD35 -> 5.567768e-07 | CW35: =(F35/1000)/(BC35/(1-Y35)) -> 0.8869916 | CX35: =((E35-F35)/1000000000)/O35 -> 5.2950172e-07 | CY35: =(F35/1000000000)/P35 -> 9.7323373e-07 | CZ35: =P35/(BC35/(1-Y35)) -> 0.911386 | DA35: =(P35-V35)/BC35 -> 0.911386 | DB35: =(F35/1000)/P35 -> 0.97323373
A36: 2013 | B36: 1164285.7 | C36: 536173.32 | D36: 0.46051698 | E36: 1106775.7 | F36: 525994.35 | G36: 0.47524926 | H36: 1119734.9 | I36: 530098.93 | J36: 0.47341466 | K36: =C36/B36-D36 -> 0 | L36: =I36/H36-J36 -> 0 | M36: =F36/E36-G36 -> 0 | O36: ='[18]Table I.P 1'!$D$8/1000 -> 1019.15 | P36: =WrightZucman!O57 -> 511.726 | Q36: =P36/(P36+O36) -> 0.33427005 | R36: =BC36/(1-Y36) -> 604.32709 | S36: =BF36+V36 -> 606.003 | T36: =R36/(R36+O36) -> 0.37224245 | U36: =T36 -> 0.37224245 | V36: 138.607 | W36: ='[18]Table I.P 1'!$J$8/1000 -> 282.903 | X36: =W36/O36 -> 0.27758721 | Y36: =V36/P36 -> 0.27086175 | Z36: =(V36+W36)/(O36+P36) -> 0.27533909 | AA36: =V36/(P36/(1-BE36)) -> 0.25994455 | AB36: =(V36+W36)/(P36/(1-BE36)+O36) -> 0.27152719 | AD36: =BB36-0.5*AP36+AI36 -> 1753.2541 | AE36: =0.5*AP36 -> 276.625 | AF36: =AD36-AE36 -> 1476.6291 | AG36: =AD36 -> 1753.2541 | AH36: =AG36-AI36 -> 1130.421 | AI36: =BC36/(1-Y36)+BD36 -> 622.83309 | AK36: =AL36+AM36 -> 2029.8791 | AL36: =BB36 -> 1407.046 | AM36: =AI36 -> 622.83309 | AN36: =AK36 -> 2029.8791 | AO36: =AN36-AP36 -> 1476.6291 | AP36: 553.25 | AQ36: =AF36-AO36 -> 0 | AR36: =Data!AM36/Data!AK36 -> 0.30683261 | AS36: =Data!AI36/Data!AG36 -> 0.35524406 | AV36: ='[1]Assets(BoP)'!$D105 -> 2010.7 | AW36: 80.2 | AX36: ='[1]Assets(BoP)'!$CI105 -> 173.877 | AY36: =BK36 -> 109.567 | AZ36: =AV36-AW36-AX36+AY36 -> 1866.19 | BA36: 459.144 | BB36: =AZ36-BA36 -> 1407.046 | BC36: =BA36-BD36 -> 440.638 | BD36: 18.506 | BE36: =BD36/BA36 -> 0.040305438 | BF36: 467.396 | BG36: =BC36/(1-Y36) -> 604.32709 | BI36: ='[1]Assets(BoP)'!$Q105 -> 267.3 | BK36: 109.567 | BL36: 157.632 | BM36: =BI36-BK36-BL36 -> 0.101 | BP36: 2013 | BQ36: =Data!AR36*WrightZucman!B57 -> 0.09173511 | BR36: =$BQ36*WrightZucman!C57/WrightZucman!$B57 -> 0.037023706 | BS36: =WrightZucman!C57*Data!AS36-BR36 -> 0.0058415279 | BT36: =$BQ36*WrightZucman!D57/WrightZucman!$B57 -> 0.0035436556 | BU36: =$BQ36*WrightZucman!E57/WrightZucman!$B57 -> 0.020832018 | BV36: =$BQ36*WrightZucman!F57/WrightZucman!$B57 -> 0.014482819 | BW36: =$BQ36*WrightZucman!G57/WrightZucman!$B57 -> 0.015852912 | BX36: =BQ36-BR36-BT36-BU36-BV36-BW36 -> 0 | BZ36: =Data!AR36*WrightZucman!B57 -> 0.09173511 | CA36: =Data!D36*WrightZucman!B57 -> 0.13768281 | CB36: =Data!Q36*WrightZucman!B57 -> 0.099938205 | CC36: =WrightZucman!C57*Data!$Q36 -> 0.040334423 | CD36: =WrightZucman!D57*Data!$Q36 -> 0.0038605348 | CE36: =WrightZucman!E57*Data!$Q36 -> 0.022694849 | CF36: =WrightZucman!F57*Data!$Q36 -> 0.015777894 | CG36: =WrightZucman!G57*Data!$Q36 -> 0.017270504 | CH36: =CB36-CC36-CD36-CE36-CF36-CG36 -> 0 | CJ36: =CK36+CL36 -> 352.3 | CK36: 298.4 | CL36: 53.9 | CM36: =BC36*Y36/(1-Y36) -> 163.68909 | CN36: =(CJ36+CM36)/AD36 -> 0.29430366 | CO36: ='[1]Assets(BoP)'!$BN105 -> 0.30248221 | CQ36: =(O36+P36)/AD36 -> 0.87316265 | CR36: =P36/AI36 -> 0.82161016 | CS36: =O36/AL36 -> 0.72431889 | CT36: =O36/(AL36-0.5*AP36) -> 0.90156676 | CU36: =(O36+P36)/AD36 -> 0.87316265 | CV36: =(E36/1000000000)/AD36 -> 6.3126944e-07 | CW36: =(F36/1000)/(BC36/(1-Y36)) -> 0.87038022 | CX36: =((E36-F36)/1000000000)/O36 -> 5.6986839e-07 | CY36: =(F36/1000000000)/P36 -> 1.0278828e-06 | CZ36: =P36/(BC36/(1-Y36)) -> 0.84676991 | DA36: =(P36-V36)/BC36 -> 0.84676991 | DB36: =(F36/1000)/P36 -> 1.0278828
A37: 2014 | B37: 1200184.1 | C37: 530081.48 | D37: 0.44166679 | E37: 1127570.3 | F37: 520938.28 | G37: 0.46200071 | H37: 1148277.5 | I37: 528165.97 | J37: 0.4599637 | K37: =C37/B37-D37 -> 0 | L37: =I37/H37-J37 -> 0 | M37: =F37/E37-G37 -> 0 | O37: ='[19]Table I.P 1'!$D$7/1000 -> 1124.857 | P37: =WrightZucman!O58 -> 554.226 | Q37: =P37/(P37+O37) -> 0.3300766 | R37: =BC37/(1-Y37) -> 589.47406 | S37: =BF37+V37 -> 604.929 | T37: =R37/(R37+O37) -> 0.34385077 | U37: =T37 -> 0.34385077 | V37: 133.164 | W37: ='[19]Table I.N 1'!$I$8/1000 -> 331.712 | X37: =W37/O37 -> 0.2948926 | Y37: =V37/P37 -> 0.24027021 | Z37: =(V37+W37)/(O37+P37) -> 0.27686303 | AA37: =V37/(P37/(1-BE37)) -> 0.23266287 | AB37: =(V37+W37)/(P37/(1-BE37)+O37) -> 0.27390689 | AD37: =BB37-0.5*AP37+AI37 -> 1780.6801 | AE37: =0.5*AP37 -> 305.695 | AF37: =AD37-AE37 -> 1474.9851 | AG37: =AD37 -> 1780.6801 | AH37: =AG37-AI37 -> 1176.563 | AI37: =BC37/(1-Y37)+BD37 -> 604.11706 | AK37: =AL37+AM37 -> 2086.3751 | AL37: =BB37 -> 1482.258 | AM37: =AI37 -> 604.11706 | AN37: =AK37 -> 2086.3751 | AO37: =AN37-AP37 -> 1474.9851 | AP37: 611.39 | AQ37: =AF37-AO37 -> 0 | AR37: =Data!AM37/Data!AK37 -> 0.28955343 | AS37: =Data!AI37/Data!AG37 -> 0.33926199 | AV37: ='[1]Assets(BoP)'!$D106 -> 2120.2 | AW37: 104 | AX37: ='[1]Assets(BoP)'!$CI106 -> 197.747 | AY37: =BK37 -> 126.289 | AZ37: =AV37-AW37-AX37+AY37 -> 1944.742 | BA37: 462.484 | BB37: =AZ37-BA37 -> 1482.258 | BC37: =BA37-BD37 -> 447.841 | BD37: 14.643 | BE37: =BD37/BA37 -> 0.031661636 | BF37: 471.765 | BG37: =BC37/(1-Y37) -> 589.47406 | BI37: ='[1]Assets(BoP)'!$Q106 -> 288.5 | BK37: 126.289 | BL37: 162.098 | BM37: =BI37-BK37-BL37 -> 0.113 | BP37: 2014 | BQ37: =Data!AR37*WrightZucman!B58 -> 0.09777116 | BR37: =$BQ37*WrightZucman!C58/WrightZucman!$B58 -> 0.032168076 | BS37: =WrightZucman!C58*Data!AS37-BR37 -> 0.0055223957 | BT37: =$BQ37*WrightZucman!D58/WrightZucman!$B58 -> 0.011571667 | BU37: =$BQ37*WrightZucman!E58/WrightZucman!$B58 -> 0.019949619 | BV37: =$BQ37*WrightZucman!F58/WrightZucman!$B58 -> 0.018983093 | BW37: =$BQ37*WrightZucman!G58/WrightZucman!$B58 -> 0.015098704 | BX37: =BQ37-BR37-BT37-BU37-BV37-BW37 -> 0 | BZ37: =Data!AR37*WrightZucman!B58 -> 0.09777116 | CA37: =Data!D37*WrightZucman!B58 -> 0.14913404 | CB37: =Data!Q37*WrightZucman!B58 -> 0.11145429 | CC37: =WrightZucman!C58*Data!$Q37 -> 0.036670016 | CD37: =WrightZucman!D58*Data!$Q37 -> 0.013191129 | CE37: =WrightZucman!E58*Data!$Q37 -> 0.02274158 | CF37: =WrightZucman!F58*Data!$Q37 -> 0.021639788 | CG37: =WrightZucman!G58*Data!$Q37 -> 0.017211776 | CH37: =CB37-CC37-CD37-CE37-CF37-CG37 -> 0 | CJ37: =CK37+CL37 -> 396.1 | CK37: 339.6 | CL37: 56.5 | CM37: =BC37*Y37/(1-Y37) -> 141.63306 | CN37: =(CJ37+CM37)/AD37 -> 0.30198185 | CO37: ='[1]Assets(BoP)'!$BN106 -> 0.32519111 | CQ37: =(O37+P37)/AD37 -> 0.9429448 | CR37: =P37/AI37 -> 0.91741492 | CS37: =O37/AL37 -> 0.75888071 | CT37: =O37/(AL37-0.5*AP37) -> 0.95605335 | CU37: =(O37+P37)/AD37 -> 0.9429448 | CV37: =(E37/1000000000)/AD37 -> 6.3322454e-07 | CW37: =(F37/1000)/(BC37/(1-Y37)) -> 0.88373403 | CX37: =((E37-F37)/1000000000)/O37 -> 5.3929703e-07 | CY37: =(F37/1000000000)/P37 -> 9.3993837e-07 | CZ37: =P37/(BC37/(1-Y37)) -> 0.94020422 | DA37: =(P37-V37)/BC37 -> 0.94020422 | DB37: =(F37/1000)/P37 -> 0.93993837
A38: 2015 | B38: 1088345.4 | C38: 470021.05 | D38: 0.43186755 | E38: 873410.97 | F38: 433442.06 | G38: 0.49626358 | H38: 1006062.3 | I38: 461607.1 | J38: 0.45882556 | K38: =C38/B38-D38 -> 0 | L38: =I38/H38-J38 -> 0 | M38: =F38/E38-G38 -> 0 | O38: ='[20]Table I.P 1'!$D$8/1000 -> 1043.51 | P38: =WrightZucman!O59 -> 478.188 | Q38: =P38/(P38+O38) -> 0.31424632 | R38: =BC38/(1-Y38) -> 523.94626 | S38: =BF38+V38 -> 534.883 | T38: =R38/(R38+O38) -> 0.33426531 | U38: =T38 -> 0.33426531 | V38: 91.422 | W38: ='[20]Table I.P 1'!$J$8/1000 -> 300.987 | X38: =W38/O38 -> 0.2884371 | Y38: =V38/P38 -> 0.19118422 | Z38: =(V38+W38)/(O38+P38) -> 0.25787574 | AA38: =V38/(P38/(1-BE38)) -> 0.18672211 | AB38: =(V38+W38)/(P38/(1-BE38)+O38) -> 0.25595364 | AD38: =BB38-0.5*AP38+AI38 -> 1647.3343 | AE38: =0.5*AP38 -> 345.85 | AF38: =AD38-AE38 -> 1301.4843 | AG38: =AD38 -> 1647.3343 | AH38: =AG38-AI38 -> 1113.261 | AI38: =BC38/(1-Y38)+BD38 -> 534.07326 | AK38: =AL38+AM38 -> 1993.1843 | AL38: =BB38 -> 1459.111 | AM38: =AI38 -> 534.07326 | AN38: =AK38 -> 1993.1843 | AO38: =AN38-AP38 -> 1301.4843 | AP38: 691.7 | AQ38: =AF38-AO38 -> 0 | AR38: =Data!AM38/Data!AK38 -> 0.26794977 | AS38: =Data!AI38/Data!AG38 -> 0.32420455 | AV38: ='[1]Assets(BoP)'!$D107 -> 2060.5 | AW38: 101.2 | AX38: ='[1]Assets(BoP)'!$CI107 -> 203.052 | AY38: =BK38 -> 136.766 | AZ38: =AV38-AW38-AX38+AY38 -> 1893.014 | BA38: 433.903 | BB38: =AZ38-BA38 -> 1459.111 | BC38: =BA38-BD38 -> 423.776 | BD38: 10.127 | BE38: =BD38/BA38 -> 0.023339318 | BF38: 443.461 | BG38: =BC38/(1-Y38) -> 523.94626 | BI38: ='[1]Assets(BoP)'!$Q107 -> 275 | BK38: 136.766 | BL38: 138.041 | BM38: =BI38-BK38-BL38 -> 0.193 | BP38: 2015 | BQ38: =Data!AR38*WrightZucman!B59 -> 0.11520728 | BR38: =$BQ38*WrightZucman!C59/WrightZucman!$B59 -> 0.041242438 | BS38: =WrightZucman!C59*Data!AS38-BR38 -> 0.0086586538 | BT38: =$BQ38*WrightZucman!D59/WrightZucman!$B59 -> 0.018393851 | BU38: =$BQ38*WrightZucman!E59/WrightZucman!$B59 -> 0.022225484 | BV38: =$BQ38*WrightZucman!F59/WrightZucman!$B59 -> 0.017379069 | BW38: =$BQ38*WrightZucman!G59/WrightZucman!$B59 -> 0.015966441 | BX38: =BQ38-BR38-BT38-BU38-BV38-BW38 -> 0 | BZ38: =Data!AR38*WrightZucman!B59 -> 0.11520728 | CA38: =Data!D38*WrightZucman!B59 -> 0.18568513 | CB38: =Data!Q38*WrightZucman!B59 -> 0.13511288 | CC38: =WrightZucman!C59*Data!$Q38 -> 0.048368336 | CD38: =WrightZucman!D59*Data!$Q38 -> 0.021571954 | CE38: =WrightZucman!E59*Data!$Q38 -> 0.026065619 | CF38: =WrightZucman!F59*Data!$Q38 -> 0.020381837 | CG38: =WrightZucman!G59*Data!$Q38 -> 0.018725135 | CH38: =CB38-CC38-CD38-CE38-CF38-CG38 -> 0 | CJ38: =CK38+CL38 -> 385.3 | CK38: 329.1 | CL38: 56.2 | CM38: =BC38*Y38/(1-Y38) -> 100.17026 | CN38: =(CJ38+CM38)/AD38 -> 0.29470052 | CO38: ='[1]Assets(BoP)'!$BN107 -> 0.34985102 | CQ38: =(O38+P38)/AD38 -> 0.9237336 | CR38: =P38/AI38 -> 0.89536032 | CS38: =O38/AL38 -> 0.71516835 | CT38: =O38/(AL38-0.5*AP38) -> 0.93734533 | CU38: =(O38+P38)/AD38 -> 0.9237336 | CV38: =(E38/1000000000)/AD38 -> 5.3019657e-07 | CW38: =(F38/1000)/(BC38/(1-Y38)) -> 0.82726435 | CX38: =((E38-F38)/1000000000)/O38 -> 4.2162405e-07 | CY38: =(F38/1000000000)/P38 -> 9.0642605e-07 | CZ38: =P38/(BC38/(1-Y38)) -> 0.91266613 | DA38: =(P38-V38)/BC38 -> 0.91266613 | DB38: =(F38/1000)/P38 -> 0.90642605
A39: 2016 | B39: 1051327.3 | C39: 456590.59 | D39: 0.43429919 | E39: 919528.92 | F39: 447739.11 | G39: 0.48692227 | H39: 974896.53 | I39: 450193.43 | J39: 0.46178585 | K39: =C39/B39-D39 -> 0 | L39: =I39/H39-J39 -> 0 | M39: =F39/E39-G39 -> 0 | O39: 1032.917 | P39: =WrightZucman!O60 -> 434.09 | Q39: =P39/(P39+O39) -> 0.29590179 | R39: =BC39/(1-Y39) -> 525.25104 | S39: =BF39+V39 -> 538.862 | T39: =R39/(R39+O39) -> 0.33709525 | U39: =T39 -> 0.33709525 | V39: 86.941 | W39: ='[21]Table I.P 1'!$J$8/1000 -> 288.815 | X39: =W39/O39 -> 0.27961104 | Y39: =V39/P39 -> 0.20028335 | Z39: =(V39+W39)/(O39+P39) -> 0.25613784 | AA39: =V39/(P39/(1-BE39)) -> 0.19075885 | AB39: =(V39+W39)/(P39/(1-BE39)+O39) -> 0.25240869 | AD39: =BB39-0.5*AP39+AI39 -> 1621.091 | AE39: =0.5*AP39 -> 349.86 | AF39: =AD39-AE39 -> 1271.231 | AG39: =AD39 -> 1621.091 | AH39: =AG39-AI39 -> 1074.867 | AI39: =BC39/(1-Y39)+BD39 -> 546.22404 | AK39: =AL39+AM39 -> 1970.951 | AL39: =BB39 -> 1424.727 | AM39: =AI39 -> 546.22404 | AN39: =AK39 -> 1970.951 | AO39: =AN39-AP39 -> 1271.231 | AP39: 699.72 | AQ39: =AF39-AO39 -> 0 | AR39: =Data!AM39/Data!AK39 -> 0.27713729 | AS39: =Data!AI39/Data!AG39 -> 0.3369484 | AV39: ='[1]Assets(BoP)'!$D108 -> 2037.7 | AW39: 92.5 | AX39: ='[1]Assets(BoP)'!$CI108 -> 217.962 | AY39: =BK39 -> 138.514 | AZ39: =AV39-AW39-AX39+AY39 -> 1865.752 | BA39: 441.025 | BB39: =AZ39-BA39 -> 1424.727 | BC39: 420.052 | BD39: 20.973 | BE39: =BD39/BA39 -> 0.047555127 | BF39: 451.921 | BG39: =BC39/(1-Y39) -> 525.25104 | BI39: ='[1]Assets(BoP)'!$Q108 -> 272.3 | BK39: 138.514 | BL39: 133.597 | BM39: =BI39-BK39-BL39 -> 0.189 | BP39: 2016 | BQ39: =Data!AR39*WrightZucman!B60 -> 0.13316751 | BR39: =$BQ39*WrightZucman!C60/WrightZucman!$B60 -> 0.049103782 | BS39: =WrightZucman!C60*Data!AS39-BR39 -> 0.010597461 | BT39: =$BQ39*WrightZucman!D60/WrightZucman!$B60 -> 0.027517731 | BU39: =$BQ39*WrightZucman!E60/WrightZucman!$B60 -> 0.027146801 | BV39: =$BQ39*WrightZucman!F60/WrightZucman!$B60 -> 0.012212581 | BW39: =$BQ39*WrightZucman!G60/WrightZucman!$B60 -> 0.017186611 | BX39: =BQ39-BR39-BT39-BU39-BV39-BW39 -> 0 | BZ39: =Data!AR39*WrightZucman!B60 -> 0.13316751 | CA39: =Data!D39*WrightZucman!B60 -> 0.20868552 | CB39: =Data!Q39*WrightZucman!B60 -> 0.14218405 | CC39: =WrightZucman!C60*Data!$Q39 -> 0.052428516 | CD39: =WrightZucman!D60*Data!$Q39 -> 0.02938091 | CE39: =WrightZucman!E60*Data!$Q39 -> 0.028984865 | CF39: =WrightZucman!F60*Data!$Q39 -> 0.013039474 | CG39: =WrightZucman!G60*Data!$Q39 -> 0.018350287 | CH39: =CB39-CC39-CD39-CE39-CF39-CG39 -> 0 | CJ39: =CK39+CL39 -> 365.3 | CK39: 311.9 | CL39: 53.4 | CM39: =BC39*Y39/(1-Y39) -> 105.19904 | CN39: =(CJ39+CM39)/AD39 -> 0.29023604 | CO39: ='[1]Assets(BoP)'!$BN108 -> 0.3352252 | CQ39: =(O39+P39)/AD39 -> 0.90495041 | CR39: =P39/AI39 -> 0.79471054 | CS39: =O39/AL39 -> 0.72499293 | CT39: =O39/(AL39-0.5*AP39) -> 0.96097192 | CU39: =(O39+P39)/AD39 -> 0.90495041 | CV39: =(E39/1000000000)/AD39 -> 5.6722843e-07 | CW39: =(F39/1000)/(BC39/(1-Y39)) -> 0.85242879 | CX39: =((E39-F39)/1000000000)/O39 -> 4.5675481e-07 | CY39: =(F39/1000000000)/P39 -> 1.031443e-06 | CZ39: =P39/(BC39/(1-Y39)) -> 0.82644292 | DA39: =(P39-V39)/BC39 -> 0.82644292 | DB39: =(F39/1000)/P39 -> 1.031443
A40: 2017 | B40: 1126485.3 | C40: 548974.07 | D40: 0.48733352 | E40: 1018099.5 | F40: 545806.19 | G40: 0.53610298 | H40: 1056784.7 | I40: 541416.89 | J40: 0.5123247 | K40: =C40/B40-D40 -> 0 | L40: =I40/H40-J40 -> 0 | M40: =F40/E40-G40 -> 0 | O40: 978.191 | P40: 538.833 | Q40: =P40/(P40+O40) -> 0.35519082 | R40: =BC40/(1-Y40) -> 632.73861 | S40: =BF40+V40 -> 650.102 | T40: =R40/(R40+O40) -> 0.39277856 | U40: =T40 -> 0.39277856 | V40: 105.566 | W40: ='[22]Table I.P 1'!$J$8/1000 -> 233.927 | X40: =W40/O40 -> 0.23914246 | Y40: =V40/P40 -> 0.19591599 | Z40: =(V40+W40)/(O40+P40) -> 0.22378881 | AA40: =V40/(P40/(1-BE40)) -> 0.18643162 | AB40: =(V40+W40)/(P40/(1-BE40)+O40) -> 0.21981679 | AD40: =BB40-0.5*AP40+AI40 -> 1708.8731 | AE40: =0.5*AP40 -> 373.4945 | AF40: =AD40-AE40 -> 1335.3786 | AG40: =AD40 -> 1708.8731 | AH40: =AG40-AI40 -> 1050.2515 | AI40: =BC40/(1-Y40)+BD40 -> 658.62161 | AK40: =AL40+AM40 -> 2082.3676 | AL40: =BB40 -> 1423.746 | AM40: =AI40 -> 658.62161 | AN40: =AK40 -> 2082.3676 | AO40: =AN40-AP40 -> 1335.3786 | AP40: 746.989 | AQ40: =AF40-AO40 -> 0 | AR40: =Data!AM40/Data!AK40 -> 0.31628499 | AS40: =Data!AI40/Data!AG40 -> 0.38541282 | AT40: =596/(596+765) -> 0.4379133 | AV40: ='[1]Assets(BoP)'!$D109 -> 2128.9 | AW40: 78.8 | AX40: ='[1]Assets(BoP)'!$CI109 -> 236.304 | AY40: =BK40 -> 144.608 | AZ40: =AV40-AW40-AX40+AY40 -> 1958.404 | BA40: 534.658 | BB40: =AZ40-BA40 -> 1423.746 | BC40: 508.775 | BD40: 25.883 | BE40: =BD40/BA40 -> 0.048410386 | BF40: 544.536 | BG40: =BC40/(1-Y40) -> 632.73861 | BI40: ='[1]Assets(BoP)'!$Q109 -> 305.2 | BK40: 144.608 | BL40: 160.507 | BM40: =BI40-BK40-BL40 -> 0.085 | BP40: 2017 | BQ40: =Data!AR40*WrightZucman!B61 -> 0.14476783 | BR40: =$BQ40*WrightZucman!C61/WrightZucman!$B61 -> 0.04770281 | BS40: =WrightZucman!C61*Data!AS40-BR40 -> 0.010426015 | BT40: =$BQ40*WrightZucman!D61/WrightZucman!$B61 -> 0.034494553 | BU40: =$BQ40*WrightZucman!E61/WrightZucman!$B61 -> 0.021654333 | BV40: =$BQ40*WrightZucman!F61/WrightZucman!$B61 -> 0.020456891 | BW40: =$BQ40*WrightZucman!G61/WrightZucman!$B61 -> 0.020459239 | BX40: =BQ40-BR40-BT40-BU40-BV40-BW40 -> 0 | BZ40: =Data!AR40*WrightZucman!B61 -> 0.14476783 | CA40: =Data!D40*WrightZucman!B61 -> 0.223059 | CB40: =Data!Q40*WrightZucman!B61 -> 0.16257554 | CC40: =WrightZucman!C61*Data!$Q40 -> 0.053570675 | CD40: =WrightZucman!D61*Data!$Q40 -> 0.038737686 | CE40: =WrightZucman!E61*Data!$Q40 -> 0.024318007 | CF40: =WrightZucman!F61*Data!$Q40 -> 0.022973269 | CG40: =WrightZucman!G61*Data!$Q40 -> 0.022975905 | CH40: =CB40-CC40-CD40-CE40-CF40-CG40 -> 2.7755576e-17 | CJ40: =CK40+CL40 -> 299.6 | CK40: 245.4 | CL40: 54.2 | CM40: =BC40*Y40/(1-Y40) -> 123.96361 | CN40: =(CJ40+CM40)/AD40 -> 0.24786136 | CO40: ='[1]Assets(BoP)'!$BN109 -> 0.25715673 | CQ40: =(O40+P40)/AD40 -> 0.88773355 | CR40: =P40/AI40 -> 0.81812226 | CS40: =O40/AL40 -> 0.68705443 | CT40: =O40/(AL40-0.5*AP40) -> 0.93138739 | CU40: =(O40+P40)/AD40 -> 0.88773355 | CV40: =(E40/1000000000)/AD40 -> 5.9577246e-07 | CW40: =(F40/1000)/(BC40/(1-Y40)) -> 0.86260927 | CX40: =((E40-F40)/1000000000)/O40 -> 4.8282323e-07 | CY40: =(F40/1000000000)/P40 -> 1.0129413e-06 | CZ40: =P40/(BC40/(1-Y40)) -> 0.85158862 | DA40: =(P40-V40)/BC40 -> 0.85158862 | DB40: =(F40/1000)/P40 -> 1.0129413
A41: 2018 | B41: 1293487 | C41: 634368.77 | D41: 0.49043304 | E41: 1186167 | F41: 614061.62 | G41: 0.51768564 | H41: 1227695.3 | I41: 625100.96 | J41: 0.50916619 | K41: =C41/B41-D41 -> 0 | L41: =I41/H41-J41 -> 0 | M41: =F41/E41-G41 -> 0 | O41: 1202.74 | P41: 556.233 | Q41: =P41/(P41+O41) -> 0.316226 | R41: =BC41/(1-Y41) -> 673.29426 | S41: =BF41+V41 -> 684.53 | T41: =R41/(R41+O41) -> 0.3588923 | U41: =T41 -> 0.3588923 | V41: 118.108 | W41: ='[23]Table I.P 1'!$J$8/1000 -> 218.916 | X41: =W41/O41 -> 0.1820144 | Y41: =V41/P41 -> 0.21233548 | Z41: =(V41+W41)/(O41+P41) -> 0.19160271 | AA41: =V41/(P41/(1-BE41)) -> 0.2015612 | AB41: =(V41+W41)/(P41/(1-BE41)+O41) -> 0.18841778 | AD41: =BB41-0.5*AP41+AI41 -> 1860.8998 | AE41: =0.5*AP41 -> 408.62347 | AF41: =AD41-AE41 -> 1452.2763 | AG41: =AD41 -> 1860.8998 | AH41: =AG41-AI41 -> 1159.2195 | AI41: =BC41/(1-Y41)+BD41 -> 701.68026 | AK41: =AL41+AM41 -> 2269.5233 | AL41: =BB41 -> 1567.843 | AM41: =AI41 -> 701.68026 | AN41: =AK41 -> 2269.5233 | AO41: =AN41-AP41 -> 1452.2763 | AP41: 817.24694 | AQ41: =AF41-AO41 -> 0 | AR41: =Data!AM41/Data!AK41 -> 0.30917518 | AS41: =Data!AI41/Data!AG41 -> 0.37706504 | AT41: =658/(658+856) -> 0.4346103 | AV41: ='[1]Assets(BoP)'!$D110 -> 2305 | AW41: 63.5 | AX41: ='[1]Assets(BoP)'!$CI110 -> 273.516 | AY41: =BK41 -> 159.28 | AZ41: =AV41-AW41-AX41+AY41 -> 2127.264 | BA41: 559.421 | BB41: =AZ41-BA41 -> 1567.843 | BC41: 530.33 | BD41: 28.386 | BE41: =BD41/BA41 -> 0.050741749 | BF41: 566.422 | BG41: =BC41/(1-Y41) -> 673.29426 | BI41: ='[1]Assets(BoP)'!$Q110 -> 344.4 | BK41: 159.28 | BL41: 185.042 | BM41: =BI41-BK41-BL41 -> 0.078 | BP41: 2018 | BQ41: =Data!AR41*WrightZucman!B62 -> 0.14644763 | BR41: =$BQ41*WrightZucman!C62/WrightZucman!$B62 -> 0.055359195 | BS41: =WrightZucman!C62*Data!AS41-BR41 -> 0.012155983 | BT41: =$BQ41*WrightZucman!D62/WrightZucman!$B62 -> 0.017478867 | BU41: =$BQ41*WrightZucman!E62/WrightZucman!$B62 -> 0.022394694 | BV41: =$BQ41*WrightZucman!F62/WrightZucman!$B62 -> 0.022034511 | BW41: =$BQ41*WrightZucman!G62/WrightZucman!$B62 -> 0.029180359 | BX41: =BQ41-BR41-BT41-BU41-BV41-BW41 -> 0 | BZ41: =Data!AR41*WrightZucman!B62 -> 0.14644763 | CA41: =Data!D41*WrightZucman!B62 -> 0.2323044 | CB41: =Data!Q41*WrightZucman!B62 -> 0.1497874 | CC41: =WrightZucman!C62*Data!$Q41 -> 0.056621676 | CD41: =WrightZucman!D62*Data!$Q41 -> 0.017877477 | CE41: =WrightZucman!E62*Data!$Q41 -> 0.022905411 | CF41: =WrightZucman!F62*Data!$Q41 -> 0.022537014 | CG41: =WrightZucman!G62*Data!$Q41 -> 0.029845825 | CH41: =CB41-CC41-CD41-CE41-CF41-CG41 -> 0 | CJ41: =CK41+CL41 -> 269.3 | CK41: 208.8 | CL41: 60.5 | CM41: =BC41*Y41/(1-Y41) -> 142.96426 | CN41: =(CJ41+CM41)/AD41 -> 0.22154028 | CO41: ='[1]Assets(BoP)'!$BN110 -> 0.21610621 | CQ41: =(O41+P41)/AD41 -> 0.94522715 | CR41: =P41/AI41 -> 0.79271576 | CS41: =O41/AL41 -> 0.76713038 | CT41: =O41/(AL41-0.5*AP41) -> 1.0375429 | CU41: =(O41+P41)/AD41 -> 0.94522715 | CV41: =(E41/1000000000)/AD41 -> 6.3741583e-07 | CW41: =(F41/1000)/(BC41/(1-Y41)) -> 0.91202563 | CX41: =((E41-F41)/1000000000)/O41 -> 4.7566836e-07 | CY41: =(F41/1000000000)/P41 -> 1.1039647e-06 | CZ41: =P41/(BC41/(1-Y41)) -> 0.82613656 | DA41: =(P41-V41)/BC41 -> 0.82613656 | DB41: =(F41/1000)/P41 -> 1.1039647
A42: 2019 | B42: 1221693.2 | C42: 571134.52 | D42: 0.46749424 | E42: 1081752.1 | F42: 559740.73 | G42: 0.51743899 | H42: 1128955.1 | I42: 568699.99 | J42: 0.50374014 | K42: =C42/B42-D42 -> 0 | L42: =I42/H42-J42 -> 0 | M42: =F42/E42-G42 -> 0 | O42: 1139.434 | P42: =WrightZucman!O63 -> 510.847 | Q42: =P42/(P42+O42) -> 0.30955152 | R42: =BC42/(1-Y42) -> 691.08972 | S42: =BF42+V42 -> 660.718 | T42: =R42/(R42+O42) -> 0.37753661 | U42: =T42 -> 0.37753661 | V42: 111.605 | W42: ='[24]Table I.P 1'!$J$8/1000 -> 207.239 | X42: =W42/O42 -> 0.1818789 | Y42: =V42/P42 -> 0.2184705 | Z42: =(V42+W42)/(O42+P42) -> 0.19320588 | AA42: =V42/(P42/(1-BE42)) -> 0.208944 | AB42: =(V42+W42)/(P42/(1-BE42)+O42) -> 0.19051701 | AD42: =BB42-0.5*AP42+AI42 -> 1938.8336 | AE42: =0.5*AP42 -> 424.93908 | AF42: =AD42-AE42 -> 1513.8946 | AG42: =AD42 -> 1938.8336 | AH42: =AG42-AI42 -> 1223.9769 | AI42: =BC42/(1-Y42)+BD42 -> 714.85672 | AK42: =AL42+AM42 -> 2363.7727 | AL42: =BB42 -> 1648.916 | AM42: =AI42 -> 714.85672 | AN42: =AK42 -> 2363.7727 | AO42: =AN42-AP42 -> 1513.8946 | AP42: 849.87815 | AQ42: =AF42-AO42 -> 0 | AR42: =Data!AM42/Data!AK42 -> 0.30242193 | AS42: =Data!AI42/Data!AG42 -> 0.36870451 | AT42: =602/(602+911) -> 0.397885 | AV42: ='[1]Assets(BoP)'!$D111 -> 2367.8 | AW42: 54.9 | AX42: ='[1]Assets(BoP)'!$CI111 -> 286.739 | AY42: =BK42 -> 167.802 | AZ42: =AV42-AW42-AX42+AY42 -> 2193.963 | BA42: 545.047 | BB42: =AZ42-BA42 -> 1648.916 | BC42: 540.107 | BD42: 23.767 | BE42: =BD42/BA42 -> 0.043605414 | BF42: 549.113 | BG42: =BC42/(1-Y42) -> 691.08972 | BI42: ='[1]Assets(BoP)'!$Q111 -> 351.3 | BK42: 167.802 | BL42: 183.339 | BM42: =BI42-BK42-BL42 -> 0.159 | BP42: 2019 | BQ42: =Data!AR42*WrightZucman!B63 -> 0.13677946 | BR42: =$BQ42*WrightZucman!C63/WrightZucman!$B63 -> 0.049163907 | BS42: =WrightZucman!C63*Data!AS42-BR42 -> 0.010775378 | BT42: =$BQ42*WrightZucman!D63/WrightZucman!$B63 -> 0.018618431 | BU42: =$BQ42*WrightZucman!E63/WrightZucman!$B63 -> 0.024053593 | BV42: =$BQ42*WrightZucman!F63/WrightZucman!$B63 -> 0.018533775 | BW42: =$BQ42*WrightZucman!G63/WrightZucman!$B63 -> 0.026409757 | BX42: =BQ42-BR42-BT42-BU42-BV42-BW42 -> 0 | BZ42: =Data!AR42*WrightZucman!B63 -> 0.13677946 | CA42: =Data!D42*WrightZucman!B63 -> 0.21143841 | CB42: =Data!Q42*WrightZucman!B63 -> 0.14000404 | CC42: =WrightZucman!C63*Data!$Q42 -> 0.050322945 | CD42: =WrightZucman!D63*Data!$Q42 -> 0.019057361 | CE42: =WrightZucman!E63*Data!$Q42 -> 0.024620656 | CF42: =WrightZucman!F63*Data!$Q42 -> 0.018970709 | CG42: =WrightZucman!G63*Data!$Q42 -> 0.027032366 | CH42: =CB42-CC42-CD42-CE42-CF42-CG42 -> 0 | CJ42: =CK42+CL42 -> 286.5 | CK42: 217 | CL42: 69.5 | CM42: =BC42*Y42/(1-Y42) -> 150.98272 | CN42: =(CJ42+CM42)/AD42 -> 0.22564221 | CO42: ='[1]Assets(BoP)'!$BN111 -> 0.22486457 | CQ42: =(O42+P42)/AD42 -> 0.85117205 | CR42: =P42/AI42 -> 0.71461453 | CS42: =O42/AL42 -> 0.69102004 | CT42: =O42/(AL42-0.5*AP42) -> 0.93092768 | CU42: =(O42+P42)/AD42 -> 0.85117205 | CV42: =(E42/1000000000)/AD42 -> 5.5793963e-07 | CW42: =(F42/1000)/(BC42/(1-Y42)) -> 0.80993931 | CX42: =((E42-F42)/1000000000)/O42 -> 4.5813219e-07 | CY42: =(F42/1000000000)/P42 -> 1.0957111e-06 | CZ42: =P42/(BC42/(1-Y42)) -> 0.73919057 | DA42: =(P42-V42)/BC42 -> 0.73919057 | DB42: =(F42/1000)/P42 -> 1.0957111
A43: 2020 | B43: 1089645 | C43: 452252.43 | D43: 0.41504568 | E43: 760867.57 | F43: 414037.46 | G43: 0.54416494 | H43: 939797.86 | I43: 435283.76 | J43: 0.46316743 | K43: =C43/B43-D43 -> 0 | L43: =I43/H43-J43 -> 0 | M43: =F43/E43-G43 -> 0 | O43: 686.941 | P43: =WrightZucman!O64 -> 431.991 | Q43: =P43/(P43+O43) -> 0.3860744 | R43: =BC43/(1-Y43) -> 565.91377 | S43: =BF43+V43 -> 573.395 | T43: =R43/(R43+O43) -> 0.45169942 | U43: =T43 -> 0.45169942 | V43: 91.489 | W43: 130.321 | X43: =W43/O43 -> 0.18971207 | Y43: =V43/P43 -> 0.2117845 | Z43: =(V43+W43)/(O43+P43) -> 0.19823367 | AA43: =V43/(P43/(1-BE43)) -> 0.19642661 | AB43: =(V43+W43)/(P43/(1-BE43)+O43) -> 0.19242517 | AD43: =BB43-0.5*AP43+AI43 -> 1785.6163 | AE43: =0.5*AP43 -> 409.97546 | AF43: =AD43-AE43 -> 1375.6408 | AG43: =AD43 -> 1785.6163 | AH43: =AG43-AI43 -> 1185.0785 | AI43: =BC43/(1-Y43)+BD43 -> 600.53777 | AK43: =AL43+AM43 -> 2195.5918 | AL43: =BB43 -> 1595.054 | AM43: =AI43 -> 600.53777 | AN43: =AK43 -> 2195.5918 | AO43: =AN43-AP43 -> 1375.6408 | AP43: 819.95093 | AQ43: =AF43-AO43 -> 0 | AR43: =Data!AM43/Data!AK43 -> 0.27351978 | AS43: =Data!AI43/Data!AG43 -> 0.3363196 | AV43: ='[1]Assets(BoP)'!$D112 -> 2243.8 | AW43: 88.5 | AX43: ='[1]Assets(BoP)'!$CI112 -> 255.824 | AY43: =BK43 -> 173.041 | AZ43: =AV43-AW43-AX43+AY43 -> 2072.517 | BA43: 477.463 | BB43: =AZ43-BA43 -> 1595.054 | BC43: 446.062 | BD43: 34.624 | BE43: =BD43/BA43 -> 0.072516614 | BF43: 481.906 | BG43: =BC43/(1-Y43) -> 565.91377 | BI43: ='[1]Assets(BoP)'!$Q112 -> 311.2 | BK43: 173.041 | BL43: 137.923 | BM43: =BI43-BK43-BL43 -> 0.236 | BP43: 2020 | BQ43: =Data!AR43*WrightZucman!B64 -> 0.13167339 | BR43: =$BQ43*WrightZucman!C64/WrightZucman!$B64 -> 0.056211384 | BS43: =WrightZucman!C64*Data!AS43-BR43 -> 0.01290607 | BT43: =$BQ43*WrightZucman!D64/WrightZucman!$B64 -> 0.018419281 | BU43: =$BQ43*WrightZucman!E64/WrightZucman!$B64 -> 0.015797996 | BV43: =$BQ43*WrightZucman!F64/WrightZucman!$B64 -> 0.012912049 | BW43: =$BQ43*WrightZucman!G64/WrightZucman!$B64 -> 0.02833268 | BX43: =BQ43-BR43-BT43-BU43-BV43-BW43 -> 0 | BZ43: =Data!AR43*WrightZucman!B64 -> 0.13167339 | CA43: =Data!D43*WrightZucman!B64 -> 0.19980446 | CB43: =Data!Q43*WrightZucman!B64 -> 0.18585759 | CC43: =WrightZucman!C64*Data!$Q43 -> 0.079342623 | CD43: =WrightZucman!D64*Data!$Q43 -> 0.025998899 | CE43: =WrightZucman!E64*Data!$Q43 -> 0.022298942 | CF43: =WrightZucman!F64*Data!$Q43 -> 0.018225415 | CG43: =WrightZucman!G64*Data!$Q43 -> 0.039991706 | CH43: =CB43-CC43-CD43-CE43-CF43-CG43 -> 0 | CJ43: =CK43+CL43 -> 268.5 | CK43: 192.7 | CL43: 75.8 | CM43: =BC43*Y43/(1-Y43) -> 119.85177 | CN43: =(CJ43+CM43)/AD43 -> 0.21748892 | CO43: ='[1]Assets(BoP)'!$BN112 -> 0.22776134 | CR43: =P43/AI43 -> 0.71934027 | CW43: =(F43/1000)/(BC43/(1-Y43)) -> 0.73162641 | CY43: =(F43/1000000000)/P43 -> 9.5844001e-07 | CZ43: =P43/(BC43/(1-Y43)) -> 0.76335128 | DA43: =(P43-V43)/BC43 -> 0.76335128 | DB43: =(F43/1000)/P43 -> 0.95844001
O44: 1738.953 | P44: 614.627 | Q44: =P44/(P44+O44) -> 0.26114557 | BA44: 598.9 | BC44: 567.522 | BD44: 35.279 | BF44: 601.94
A45: 2017-2020 | D45: =D43-D40 -> -0.072287839 | G45: =G43-G40 -> 0.0080619665 | J45: =J43-J40 -> -0.049157269 | Q45: =Q43-Q40 -> 0.030883579 | T45: =T43-T40 -> 0.058920858 | W45: =(O42+P42)/AK42 -> 0.69815553 | BC45: 587.424 | BD45: 36.356
BA48: =AX39-AY39 -> 79.448
Z49: =420/0.8 -> 525

Sheet AppendixTableFigures

Sheet RawSources

Sheet WrightZucman
A3: Profits of U.S. multinationals abroad: country breakdown
B5: [1] | C5: [2] | D5: [3] | E5: [4] | F5: [5] | G5: [6] | H5: [7] | I5: [8] | J5: [9] | K5: [10] | L5: [11] | M5: [12] | N5: [13] | O5: [14] | P5: [15]
B6: Excluding Puerto Rico | H6: Including Puerto Rico | O6: Memo: Foreign profits, excl. Puerto Rico ($bn) | P6: Memo: Puerto Rico profits ($bn)
B7: % of foreign pre-tax profits | H7: % of foreign pre-tax profits
B8: Total havens (excl. Puerto Rico) | C8: Ireland | D8: Netherlands + Luxembourg | E8: Switzerland | F8: Bermuda and Carribbean havens | G8: Singapore | H8: Total havens (incl. Puerto Rico) | I8: Ireland | J8: Netherlands + Luxembourg | K8: Switzerland | L8: Bermuda and Carribbean havens | M8: Singapore | N8: Puerto Rico
A10: 1966 | B10: 0.033040657 | C10: 0.0018986374 | D10: 0.0056880976 | E10: 0.012101307 | F10: 0.012953766 | G10: 0.00039884875 | H10: =I10+J10+K10+L10+M10+N10 -> 0.038162096 | I10: =C10*$O10/($O10+$P10) -> 0.0018885814 | J10: =D10*$O10/($O10+$P10) -> 0.0056579709 | K10: =E10*$O10/($O10+$P10) -> 0.012037213 | L10: =F10*$O10/($O10+$P10) -> 0.012885157 | M10: =G10*$O10/($O10+$P10) -> 0.00039673627 | N10: =P10/(P10+O10) -> 0.0052964375 | O10: 9.4228155 | P10: 0.050173091 | R10: =B10-C10-D10-E10-F10-G10 -> 3.3068166e-18
A11: 1967 | B11: 0.036199535 | C11: 0.0025292381 | D11: 0.0067474486 | E11: 0.012981742 | F11: 0.013311777 | G11: 0.00062932912 | H11: =I11+J11+K11+L11+M11+N11 -> 0.041739457 | I11: =C11*$O11/($O11+$P11) -> 0.0025147 | J11: =D11*$O11/($O11+$P11) -> 0.0067086643 | K11: =E11*$O11/($O11+$P11) -> 0.012907123 | L11: =F11*$O11/($O11+$P11) -> 0.013235261 | M11: =G11*$O11/($O11+$P11) -> 0.00062571173 | N11: =P11/(P11+O11) -> 0.005747997 | O11: 10.24499 | P11: 0.059228619 | R11: =B11-C11-D11-E11-F11-G11 -> 7.1557343e-18
A12: 1968 | B12: 0.035579051 | C12: 0.0016850845 | D12: 0.0046494211 | E12: 0.01426469 | F12: 0.014098335 | G12: 0.00088152058 | H12: =I12+J12+K12+L12+M12+N12 -> 0.041073912 | I12: =C12*$O12/($O12+$P12) -> 0.0016754836 | J12: =D12*$O12/($O12+$P12) -> 0.0046229307 | K12: =E12*$O12/($O12+$P12) -> 0.014183416 | L12: =F12*$O12/($O12+$P12) -> 0.014018009 | M12: =G12*$O12/($O12+$P12) -> 0.00087649805 | N12: =P12/(P12+O12) -> 0.005697575 | O12: 11.682861 | P12: 0.066945403 | R12: =B12-C12-D12-E12-F12-G12 -> 5.6378513e-18
A13: 1969 | B13: 0.037168832 | C13: 0.001684149 | D13: 0.0046210538 | E13: 0.015195924 | F13: 0.014552993 | G13: 0.001114712 | H13: =I13+J13+K13+L13+M13+N13 -> 0.042889131 | I13: =C13*$O13/($O13+$P13) -> 0.0016741432 | J13: =D13*$O13/($O13+$P13) -> 0.0045935996 | K13: =E13*$O13/($O13+$P13) -> 0.015105643 | L13: =F13*$O13/($O13+$P13) -> 0.014466532 | M13: =G13*$O13/($O13+$P13) -> 0.0011080893 | N13: =P13/(P13+O13) -> 0.0059411241 | O13: 13.434164 | P13: 0.080291054 | R13: =B13-C13-D13-E13-F13-G13 -> -2.8189256e-18
A14: 1970 | B14: 0.04787263 | C14: 0.0043901505 | D14: 0.011349787 | E14: 0.015940051 | F14: 0.014861916 | G14: 0.0013307242 | H14: =I14+J14+K14+L14+M14+N14 -> 0.054978519 | I14: =C14*$O14/($O14+$P14) -> 0.004357386 | J14: =D14*$O14/($O14+$P14) -> 0.011265082 | K14: =E14*$O14/($O14+$P14) -> 0.015821088 | L14: =F14*$O14/($O14+$P14) -> 0.014750999 | M14: =G14*$O14/($O14+$P14) -> 0.0013207928 | N14: =P14/(P14+O14) -> 0.0074631715 | O14: 14.508209 | P14: 0.10909142 | R14: =B14-C14-D14-E14-F14-G14 -> 7.3725748e-18
A15: 1971 | B15: 0.048041311 | C15: 0.003745169 | D15: 0.0099224382 | E15: 0.016536697 | F15: 0.016886825 | G15: 0.00095018062 | H15: =I15+J15+K15+L15+M15+N15 -> 0.055180847 | I15: =C15*$O15/($O15+$P15) -> 0.0037170809 | J15: =D15*$O15/($O15+$P15) -> 0.0098480215 | K15: =E15*$O15/($O15+$P15) -> 0.016412675 | L15: =F15*$O15/($O15+$P15) -> 0.016760177 | M15: =G15*$O15/($O15+$P15) -> 0.00094305442 | N15: =P15/(P15+O15) -> 0.0074998387 | O15: 18.588267 | P15: 0.14046245 | R15: =B15-C15-D15-E15-F15-G15 -> -1.9515639e-18
A16: 1972 | B16: 0.045857491 | C16: 0.0026950101 | D16: 0.0071900952 | E16: 0.016112459 | F16: 0.016893106 | G16: 0.0029668205 | H16: =I16+J16+K16+L16+M16+N16 -> 0.05267156 | I16: =C16*$O16/($O16+$P16) -> 0.0026757635 | J16: =D16*$O16/($O16+$P16) -> 0.0071387467 | K16: =E16*$O16/($O16+$P16) -> 0.015997391 | L16: =F16*$O16/($O16+$P16) -> 0.016772463 | M16: =G16*$O16/($O16+$P16) -> 0.0029456328 | N16: =P16/(P16+O16) -> 0.0071415634 | O16: 22.297871 | P16: 0.16038708 | R16: =B16-C16-D16-E16-F16-G16 -> -4.3368087e-18
A17: 1973 | B17: 0.058957352 | C17: 0.0046483781 | D17: 0.012851813 | E17: 0.017490886 | F17: 0.019648998 | G17: 0.0043172778 | H17: =I17+J17+K17+L17+M17+N17 -> 0.064529579 | I17: =C17*$O17/($O17+$P17) -> 0.0046208535 | J17: =D17*$O17/($O17+$P17) -> 0.012775713 | K17: =E17*$O17/($O17+$P17) -> 0.017387316 | L17: =F17*$O17/($O17+$P17) -> 0.019532649 | M17: =G17*$O17/($O17+$P17) -> 0.0042917137 | N17: =P17/(P17+O17) -> 0.0059213322 | O17: 33.961296 | P17: 0.20229397 | R17: =B17-C17-D17-E17-F17-G17 -> -8.6736174e-18
A18: 1974 | B18: 0.051899077 | C18: 0.0046263527 | D18: 0.012432364 | E18: 0.012665266 | F18: 0.018402148 | G18: 0.0037729461 | H18: =I18+J18+K18+L18+M18+N18 -> 0.056035664 | I18: =C18*$O18/($O18+$P18) -> 0.0046061678 | J18: =D18*$O18/($O18+$P18) -> 0.012378122 | K18: =E18*$O18/($O18+$P18) -> 0.012610007 | L18: =F18*$O18/($O18+$P18) -> 0.018321859 | M18: =G18*$O18/($O18+$P18) -> 0.0037564847 | N18: =P18/(P18+O18) -> 0.0043630242 | O18: 61.350979 | P18: 0.2688488 | R18: =B18-C18-D18-E18-F18-G18 -> -1.2576745e-17
A19: 1975 | B19: 0.051837146 | C19: 0.0034229566 | D19: 0.0091923485 | E19: 0.010897782 | F19: 0.024151503 | G19: 0.0041725567 | H19: =I19+J19+K19+L19+M19+N19 -> 0.057027266 | I19: =C19*$O19/($O19+$P19) -> 0.0034042197 | J19: =D19*$O19/($O19+$P19) -> 0.0091420308 | K19: =E19*$O19/($O19+$P19) -> 0.010838129 | L19: =F19*$O19/($O19+$P19) -> 0.0240193 | M19: =G19*$O19/($O19+$P19) -> 0.0041497166 | N19: =P19/(P19+O19) -> 0.0054738693 | O19: 58.650392 | P19: 0.32281161 | R19: =B19-C19-D19-E19-F19-G19 -> 0
A20: 1976 | B20: 0.044775938 | C20: 0.0031938091 | D20: 0.0086560178 | E20: 0.0085150865 | F20: 0.021721507 | G20: 0.0026895179 | H20: =I20+J20+K20+L20+M20+N20 -> 0.050436455 | I20: =C20*$O20/($O20+$P20) -> 0.003174883 | J20: =D20*$O20/($O20+$P20) -> 0.0086047235 | K20: =E20*$O20/($O20+$P20) -> 0.0084646273 | L20: =F20*$O20/($O20+$P20) -> 0.021592788 | M20: =G20*$O20/($O20+$P20) -> 0.0026735803 | N20: =P20/(P20+O20) -> 0.0059258526 | O20: 76.248688 | P20: 0.45453198 | R20: =B20-C20-D20-E20-F20-G20 -> 0
A21: 1977 | B21: 0.056318961 | C21: 0.0043814958 | D21: 0.014294448 | E21: 0.010946461 | F21: 0.024061836 | G21: 0.0026347201 | H21: =I21+J21+K21+L21+M21+N21 -> 0.063992655 | I21: =C21*$O21/($O21+$P21) -> 0.004345867 | J21: =D21*$O21/($O21+$P21) -> 0.014178211 | K21: =E21*$O21/($O21+$P21) -> 0.010857448 | L21: =F21*$O21/($O21+$P21) -> 0.023866173 | M21: =G21*$O21/($O21+$P21) -> 0.0026132954 | N21: =P21/(P21+O21) -> 0.0081316604 | O21: 68.698 | P21: 0.56320863 | R21: =B21-C21-D21-E21-F21-G21 -> 0
... A25: 1981 | B25: 0.12598686 | C25: 0.014050324 | D25: 0.021697768 | E25: 0.027974266 | F25: 0.051037503 | G25: 0.011226998 | H25: =I25+J25+K25+L25+M25+N25 -> 0.14098174 | I25: =C25*$O25/($O25+$P25) -> 0.013809272 | J25: =D25*$O25/($O25+$P25) -> 0.021325514 | K25: =E25*$O25/($O25+$P25) -> 0.02749433 | L25: =F25*$O25/($O25+$P25) -> 0.050161885 | M25: =G25*$O25/($O25+$P25) -> 0.011034384 | N25: =P25/(P25+O25) -> 0.017156352 | O25: 63.904519 | P25: 1.1155065 | R25: =B25-C25-D25-E25-F25-G25 -> 1.5612511e-17
A26: 1982 | B26: 0.14980868 | C26: 0.014092394 | D26: 0.018777415 | E26: 0.027251517 | F26: 0.0780028 | G26: 0.011684554 | H26: 0.16880182 | I26: 0.013777572 | J26: 0.01835793 | K26: 0.026642722 | L26: 0.076260229 | M26: 0.011423523 | N26: 0.022339847 | O26: 53.575 | P26: 1.2242059 | R26: =B26-C26-D26-E26-F26-G26 -> 0 | T26: =H26*Data!AS5 -> 0.044806433
A27: 1983 | B27: 0.14000414 | C27: 0.016455871 | D27: 0.026846331 | E27: 0.021384016 | F27: 0.062739084 | G27: 0.012578833 | H27: 0.15880203 | I27: 0.016096176 | J27: 0.026259521 | K27: 0.020916602 | L27: 0.061367726 | M27: 0.012303883 | N27: 0.021858119 | O27: 58.034 | P27: 1.296861 | R27: =B27-C27-D27-E27-F27-G27 -> 2.2551405e-17 | T27: =H27*Data!AS6 -> 0.03702164
A28: 1984 | B28: 0.13324542 | C28: 0.017157927 | D28: 0.024511325 | E28: 0.023270245 | F28: 0.056934533 | G28: 0.011371393 | H28: 0.15138456 | I28: 0.016798852 | J28: 0.02399836 | K28: 0.022783254 | L28: 0.055743027 | M28: 0.011133417 | N28: 0.020927649 | O28: 64.46 | P28: 1.377831 | R28: =B28-C28-D28-E28-F28-G28 -> -1.5612511e-17 | T28: =H28*Data!AS7 -> 0.033370346
A29: 1985 | B29: 0.14040937 | C29: 0.017740623 | D29: 0.029354988 | E29: 0.027616024 | F29: 0.057545349 | G29: 0.0081523907 | H29: 0.1595201 | I29: 0.017346207 | J29: 0.028702357 | K29: 0.027002055 | L29: 0.05626598 | M29: 0.0079711438 | N29: 0.022232359 | O29: 62.681 | P29: 1.4252328 | R29: =B29-C29-D29-E29-F29-G29 -> 0 | T29: =H29*Data!AS8 -> 0.03301202
A30: 1986 | B30: 0.1469127 | C30: 0.015330021 | D30: 0.043417317 | E30: 0.028548616 | F30: 0.046611072 | G30: 0.013005678 | H30: 0.16763138 | I30: 0.014957706 | J30: 0.042362854 | K30: 0.027855264 | L30: 0.045479043 | M30: 0.012689813 | N30: 0.024286698 | O30: 56.36 | P30: 1.4028694 | R30: =B30-C30-D30-E30-F30-G30 -> -1.5612511e-17 | T30: =H30*Data!AS9 -> 0.033711088
A31: 1987 | B31: 0.17109846 | C31: 0.028148274 | D31: 0.051779798 | E31: 0.030286297 | F31: 0.047362161 | G31: 0.013521932 | H31: 0.19494794 | I31: 0.027338381 | J31: 0.050289969 | K31: 0.029414888 | L31: 0.045999439 | M31: 0.013132874 | N31: 0.028772393 | O31: 70.626 | P31: 2.0922789 | R31: =B31-C31-D31-E31-F31-G31 -> 0 | T31: =H31*Data!AS10 -> 0.040363811
A32: 1988 | B32: 0.13982085 | C32: 0.022911034 | D32: 0.054729839 | E32: 0.025577136 | F32: 0.022325489 | G32: 0.014277349 | H32: 0.15991606 | I32: 0.022375795 | J32: 0.053451259 | K32: 0.024979612 | L32: 0.021803928 | M32: 0.013943807 | N32: 0.023361658 | O32: 80.267 | P32: 1.9200252 | R32: =B32-C32-D32-E32-F32-G32 -> 0 | T32: =H32*Data!AS11 -> 0.036439173
A33: 1989 | B33: 0.16793233 | C33: 0.031298923 | D33: 0.049057177 | E33: 0.024966703 | F33: 0.04822768 | G33: 0.014381849 | H33: 0.19180191 | I33: 0.030401048 | J33: 0.04764987 | K33: 0.024250482 | L33: 0.046844169 | M33: 0.013969276 | N33: 0.028687068 | O33: 85.594 | P33: 2.5279607 | R33: =B33-C33-D33-E33-F33-G33 -> 0 | T33: =H33*Data!AS12 -> 0.045208932
A34: 1990 | B34: 0.19557789 | C34: 0.037268696 | D34: 0.055879397 | E34: 0.030493645 | F34: 0.046621342 | G34: 0.025314809 | H34: 0.22223828 | I34: 0.036033526 | J34: 0.054027426 | K34: 0.029483015 | L34: 0.045076204 | M34: 0.024475819 | N34: 0.033142291 | O34: 84.575 | P34: 2.8990918 | R34: =B34-C34-D34-E34-F34-G34 -> 0 | T34: =H34*Data!AS13 -> 0.052931504
A35: 1991 | B35: 0.2082782 | C35: 0.041118129 | D35: 0.058607659 | E35: 0.038116806 | F35: 0.046875213 | G35: 0.023560388 | H35: 0.23597269 | I35: 0.039679814 | J35: 0.056557558 | K35: 0.036783477 | L35: 0.045235515 | M35: 0.022736244 | N35: 0.034980078 | O35: 73.301 | P35: 2.6570174 | R35: =B35-C35-D35-E35-F35-G35 -> 0 | T35: =H35*Data!AS14 -> 0.045972267
A36: 1992 | B36: 0.19422005 | C36: 0.049894164 | D36: 0.054530793 | E36: 0.021628004 | F36: 0.046481489 | G36: 0.021685602 | H36: 0.22111926 | I36: 0.048228556 | J36: 0.052710402 | K36: 0.020906 | L36: 0.044929806 | M36: 0.020961675 | N36: 0.033382821 | O36: 69.447 | P36: 2.3984022 | R36: =B36-C36-D36-E36-F36-G36 -> 0 | T36: =H36*Data!AS15 -> 0.041646683
A37: 1993 | B37: 0.19241872 | C37: 0.045089243 | D37: 0.042039926 | E37: 0.027037283 | F37: 0.043828859 | G37: 0.034423408 | H37: 0.21917563 | I37: 0.043595339 | J37: 0.040647052 | K37: 0.026141479 | L37: 0.042376714 | M37: 0.033282886 | N37: 0.03313216 | O37: 73.787 | P37: 2.5284973 | R37: =B37-C37-D37-E37-F37-G37 -> 0 | T37: =H37*Data!AS16 -> 0.040337027
... A64: 2020 | B64: 0.48140355 | C64: 0.20551123 | D64: 0.067341681 | E64: 0.057758148 | F64: 0.047207002 | G64: 0.10358549 | H64: 0.51954491 | I64: 0.19039643 | J64: 0.062388882 | K64: 0.053510192 | L64: 0.043735055 | M64: 0.095967059 | N64: 0.073547294 | O64: 431.991 | P64: 34.294 | R64: =B64-C64-D64-E64-F64-G64 -> 0 | T64: =H64*Data!AS43 -> 0.17473314
A66: Notes: Tax havens include Bermuda, Bermuda and Caribbean tax havens, Ireland, Luxembourg, Netherlands, Singapore, and Switzerland. All sectors are included.
A67: Profit measure is profit-type return in the BEA survey since 1994; and net income plus foreign income taxes paid minus income from equity investment minus capital gains before.
A68: Puerto Rico profits are from SOI tabulations of form 8975 (CBCR) in 2016–2020; before that they are taken from Saez-Zucman 2019.
A69: Computations with links to the raw data can be found in file WrightZucman2018Appendix sheet T.A3c; last updated in July. 2023 using the 2020 BEA survey.

Sheet PuertoRico
A1: Profits in Puerto Rico
B3: CBCR (+ imputed backward) | C3: NIPA implicit reinvested earnings | D3: Primary income NIPA Table 4.3 | E3: CFC current earning before tax | F3: PR national accounts | G3: SOI
A4: 1980
A5: 1981 | G5: 4.217 | H5: Treasury report 1985: https://home.treasury.gov/system/files/131/Report-Possessions-1985.pdf
A6: 1982 | B6: =WrightZucman!P26 -> 1.2242059 | C6: 4.515
A7: 1983 | B7: =WrightZucman!P27 -> 1.296861 | C7: 4.918 | H7: Re-read Grubert-Slemrod
A8: 1984 | B8: =WrightZucman!P28 -> 1.377831 | C8: 5.531
A9: 1985 | B9: =WrightZucman!P29 -> 1.4252328 | C9: 6.095
A10: 1986 | B10: =WrightZucman!P30 -> 1.4028694 | C10: 6.777 | D10: 8.05
A11: 1987 | B11: =WrightZucman!P31 -> 2.0922789 | C11: 7.667 | D11: 9
A12: 1988 | B12: =WrightZucman!P32 -> 1.9200252 | C12: 8.498 | D12: 9.9
A13: 1989 | B13: =WrightZucman!P33 -> 2.5279607 | C13: 9.061 | D13: 10.5
A14: 1990 | B14: =WrightZucman!P34 -> 2.8990918 | C14: 9.662 | D14: 11.1
A15: 1991 | B15: =WrightZucman!P35 -> 2.6570174 | C15: 10.479 | D15: 12
A16: 1992 | B16: =WrightZucman!P36 -> 2.3984022 | C16: 11.688 | D16: 13.2
A17: 1993 | B17: =WrightZucman!P37 -> 2.5284973 | C17: 12.782 | D17: 14.3
A18: 1994 | B18: =WrightZucman!P38 -> 2.8804182 | C18: 13.896 | D18: 15.3
A19: 1995 | B19: =WrightZucman!P39 -> 4.3449844 | C19: 14.892 | D19: 16.5 | G19: 13.144 | H19: https://www.irs.gov/pub/irs-soi/95poss.pdf
A20: 1996 | B20: =WrightZucman!P40 -> 4.5867989 | C20: 15.609 | D20: 17.4 | H20: https://www.irs.gov/statistics/soi-tax-stats-soi-bulletin-articles-index-by-topic
A21: 1997 | B21: =WrightZucman!P41 -> 5.8526667 | C21: 17.488 | D21: 19.4 | H21: https://www.irs.gov/statistics/soi-tax-stats-us-possessions-corporations (links broken!!)
A22: 1998 | B22: =WrightZucman!P42 -> 5.9681763 | C22: 19.338 | D22: 21.4
A23: 1999 | B23: =WrightZucman!P43 -> 6.1744256 | C23: 20.546 | D23: 22.1
A24: 2000 | B24: =WrightZucman!P44 -> 7.4159496 | C24: 23.229 | D24: 25
A25: 2001 | B25: =WrightZucman!P45 -> 6.802973 | C25: 26.277 | D25: 28.3
A26: 2002 | B26: =WrightZucman!P46 -> 7.5382665 | C26: 27.402 | D26: 29.4
A27: 2003 | B27: =WrightZucman!P47 -> 9.5957526 | C27: 28.353 | D27: 30.5
A28: 2004 | B28: =WrightZucman!P48 -> 12.817008 | C28: 29.621 | D28: 31.9 | E28: 3.2
A29: 2005 | B29: =WrightZucman!P49 -> 13.765356 | C29: 30.65 | D29: 33
A30: 2006 | B30: =WrightZucman!P50 -> 16.753089 | C30: 30.418 | D30: 32.7 | E30: =2.558 -> 2.558
A31: 2007 | B31: =WrightZucman!P51 -> 19.605751 | C31: 30.922 | D31: 33.2
A32: 2008 | B32: =WrightZucman!P52 -> 18.474596 | C32: 32.546 | D32: 35 | E32: =6.456 -> 6.456
A33: 2009 | B33: =WrightZucman!P53 -> 21.854052 | C33: 33.507 | D33: 36
A34: 2010 | B34: =WrightZucman!P54 -> 21.930306 | C34: 34.156 | D34: 36.7 | E34: 7.737
A35: 2011 | B35: =WrightZucman!P55 -> 27.758206 | C35: 33.883 | D35: 36.4
A36: 2012 | B36: =WrightZucman!P56 -> 29.580077 | C36: 33.213 | D36: 35.8 | E36: =8.985 -> 8.985
A37: 2013 | B37: =WrightZucman!P57 -> 27.643499 | C37: 33.136 | D37: 35.7
A38: 2014 | B38: =WrightZucman!P58 -> 34.203537 | C38: 33.179 | D38: 35.7 | E38: =9.579 -> 9.579
A39: 2015 | B39: =WrightZucman!P59 -> 38.128415 | C39: 33.171 | D39: 35.7
A40: 2016 | B40: =WrightZucman!P60 -> 38.92594 | C40: 33.166 | D40: 35.7 | E40: =9.513 -> 9.513
A41: 2017 | B41: =WrightZucman!P61 -> 34.335 | C41: 33.212 | D41: 35.7
A42: 2018 | B42: =WrightZucman!P62 -> 37.765 | C42: 33.237 | D42: 35.7
A43: 2019 | B43: =WrightZucman!P63 -> 33.364 | C43: 32.883 | D43: 35.4
A44: 2020 | B44: 34.294 | C44: 32.624 | D44: 35.1
B48: NIPA implicit = difference between reinvested earnings on US direct investment abroad in NIPA Table 4.1 line 19 (treats Puerto Rico as foreign) and reinvested earnings on USDIA in the international accounts Table 4.2 line 14 (treats Puerto Rico as US)

Sheet PJ_2025
B1: Table II.F 1. Value Added of Affiliates, Country by Component | C1: Table I.P 1. Value Added of U.S. Parents, Industry of U.S. Parent by Component
B2: 2020 | C2: 2020
B3: Profit-type return 1 | C3: Profit-type return 1
B4: U.S. MNE Activities: Revised 2020 Statistics, Majority-Owned Foreign Affiliates | C4: U.S. MNE Activities: Revised 2020 Statistics, All Affiliates and All Parents
B5: foreign | C5: domestic | D5: % of foreign
A6: BEA now | B6: 439354 | C6: 817256 | D6: =B6/(B6+C6) -> 0.34963433
A7: Our table | B7: 431.991 | C7: 686.941 | D7: =B7/(B7+C7) -> 0.3860744
A8: Source: https://www.bea.gov/worldwide-activities-us-multinational-enterprises-revised-2020-statistics
